Workbook

Sheet 検索条件_開発側提供
A1: 後台主地址 | B1: https://common-legacy-app-admin.us.ikemen-sengoku.jp/admin/
A2: Redmine | B2: https://redmine.ls.aws.cybird.ne.jp/issues/315490
A3: Slack | B3: https://isweetygroup.slack.com/archives/C0666R2V5BL/p1769738886049559
A5: 活動資訊 | E5: 連結生成公式用資訊
A6: 後台位置 | B6: 搜尋欄位 | C6: 關鍵字 | D6: 其他備註 | E6: 對應頁面前綴 | F6: 可查詢關鍵字 | G6: 快速連結
A7: キャンペーンバナー管理 | B7: リンク(http)： | C7: collection/203 | E7: campaign | F7: ?link= | G7: {=IF(NOT(ISBLANK(E7:E29)),IF(NOT(ISBLANK(F7:F29)), HYPERLINK($B$1&E7:E29&F7:F29&C7:C29,"Search"), HYPERLINK($B$1&E7:E29,"Page Link") ),)} -> Search
A8: エントリーフラッシュ管理 | B8: ~などで検索できます： | C8: collection/203 | E8: entryflash | G8: Page Link
A9: コレクトイベント | B9: ID | C9: 203 | D9: Mystic Matrimony | E9: isgame/collection/ | F9: all_setting/ | G9: Search
A10: セット販売管理 | B10: セット販売ID： | C10: 843 | D10: Mystic Matrimony | E10: combinedsale | F10: ?combinedsale_mst_id= | G10: Search
A11: 道具資訊
A12: 後台位置 | B12: 搜尋欄位 | C12: 關鍵字 | D12: 其他備註
A13: アイテム管理 | B13: ID | C13: 18146 | E13: itemtrial | G13: Page Link
C14: 18147
C15: 18148
C16: 18149
C17: 18150
C18: 18151
B19: アイテムCD | C19: cpn_0203001
C20: cpn_0203002
C21: it170001508
C22: it170001509
C23: it170001510
C24: it170001511
A25: 商店道具資訊
A26: 後台位置 | B26: 搜尋欄位 | C26: 關鍵字 | D26: 其他備註
A27: ショップアイテム管理 | B27: id検索 | C27: 11883 | D27: cpn_0203001
C28: 11884 | D28: cpn_0203002

Sheet 導線
A1: No | B1: 大項目 | C1: 確認方法 | D1: 確認項目 | E1: 大項目 | F1: 確認方法 | G1: 確認項目 | H1: 詳細 | I1: テスト環境 | M1: 本番環境 | Q1: 備考 | R1: テスターコメント | S1: チケットURL
I2: 確認 | J2: 担当 | K2: 担当者 | L2: 日付 | M2: 確認 | N2: 担当 | O2: 担当者 | P2: 日付
A3: =ROW()-2 -> 1 | B3: 開催告知エンフラ | C3: 管理ツール エントリーフラッシュ管理 | D3: 再生開始日時が右記の通り設定されているか | E3: 活動開始告知EF (Enter Flash) | F3: 管理工具 開場動畫管理 | G3: 播放開始日期/時間是否如右方所示設定 | H3: ='参照_概要'!$C$36 -> 46074.708 | I3: OK | J3: IW | K3: Bill | L3: 46062
A4: =ROW()-2 -> 2 | D4: 再生終了日時が右記の通り設定されているか | G4: 播放結束日期/時間是否如右方所示設定 | H4: ='参照_概要'!$D$36 -> 46080.708 | I4: OK | J4: IW | K4: Bill | L4: 46062
A5: =ROW()-2 -> 3 | C5: 実機 | D5: 左記時刻にマイページにアクセスした際、エンフラが再生されるか | F5: 實體機台 | G5: 在右方所示時間點進入「Mypage頁面(Home)」時，是否會播放EF | H5: ='参照_概要'!$C$17+1/24/60 -> 46074.709 | I5: OK | J5: IW | K5: Bill | L5: 46064 | M5: OK | N5: {=IF(M5:M25="OK",{"IW","Bill","2/12"},)} -> IW | O5: Bill | P5: 2/12
A6: =ROW()-2 -> 4 | D6: エンフラ再生後、イベントマイページへ遷移するか | G6: EF播放後，是否會轉跳至「未參加活動 TOP」頁面 | I6: OK | J6: IW | K6: Bill | L6: 46064 | M6: OK | N6: IW | O6: Bill | P6: 2/12
A7: =ROW()-2 -> 5 | B7: ランキング応援セット発売エンフラ | C7: エントリーフラッシュ管理 | D7: 再生開始日時が右記の通り設定されているか | E7: 排行榜應援禮包發售EF (Enter Flash) | F7: 管理工具 開場動畫管理 | G7: 播放開始日期/時間是否如右方所示設定 | H7: ='参照_概要'!$C$37 -> 46079.708 | I7: OK | J7: IW | K7: Bill | L7: 46062
A8: =ROW()-2 -> 6 | D8: 再生終了日時が右記の通り設定されているか | G8: 播放結束日期/時間是否如右方所示設定 | H8: ='参照_概要'!$D$37 -> 46080.708 | I8: OK | J8: IW | K8: Bill | L8: 46062
A9: =ROW()-2 -> 7 | C9: 実機 | D9: 左記時刻にマイページにアクセスした際、エンフラが再生されるか | F9: 實體機台 | G9: 在右方所示時間點進入「Mypage頁面(Home)」時，是否會播放EF | H9: ='参照_概要'!$C$37+1/24/60 -> 46079.709 | I9: OK | J9: IW | K9: Bill | L9: 46064 | M9: OK | N9: IW | O9: Bill | P9: 2/12
A10: =ROW()-2 -> 8 | D10: エンフラ再生後、イベントマイページへ遷移するか | G10: EF播放後，是否會轉跳至「活動主面」 | I10: OK | J10: IW | K10: Bill | L10: 46064 | M10: OK | N10: IW | O10: Bill | P10: 2/12
A11: =ROW()-2 -> 9 | B11: イベントバナー | C11: キャンペーンバナー管理 | D11: 公開開始日時が右記の通り設定されているか | E11: 活動橫幅 (Banner) | F11: 管理工具 活動橫幅管理 | G11: 公開開始日期/時間是否如右方所示設定 | H11: ='参照_概要'!$C$17 -> 46074.708 | I11: OK | J11: IW | K11: Bill | L11: 46062
A12: =ROW()-2 -> 10 | D12: 公開終了日時が右記の通り設定されているか | G12: 公開結束日期/時間是否如右方所示設定 | H12: ='参照_概要'!$D$17 -> 46080.708 | I12: OK | J12: IW | K12: Bill | L12: 46062
A13: =ROW()-2 -> 11 | D13: バナー文言が右記の通り設定されているか | G13: 橫幅文字是否如右方所示設定 | H13: ='参照_概要'!$E$17 -> The only thing left to do, is to fall head over heels… | I13: OK | J13: IW | K13: Bill | L13: 46062
A14: =ROW()-2 -> 12 | C14: 実機 | D14: マイページにバナー画像が表示されているか | F14: 實體機台 | G14: 在「Mypage頁面(Home)」上是否顯示橫幅圖片 | H14: ='参照_概要'!$C$17+1/24/60 -> 46074.709 | I14: OK | J14: IW | K14: Bill | L14: 46064 | M14: OK | N14: IW | O14: Bill | P14: 2/12
A15: =ROW()-2 -> 13 | D15: イベント一覧にバナー画像が表示されているか | G15: 在「活動一覽(Events)」上是否顯示橫幅圖片 | I15: OK | J15: IW | K15: Bill | L15: 46064 | M15: OK | N15: IW | O15: Bill | P15: 2/12
A16: =ROW()-2 -> 14 | D16: バナーをタップすると、イベントマイページ画面へ遷移するか | G16: 點擊橫幅後，是否會轉跳到「活動主面」 | I16: OK | J16: IW | K16: Bill | L16: 46064 | M16: OK | N16: IW | O16: Bill | P16: 2/12
A17: =ROW()-2 -> 15 | B17: セット販売バナー | C17: キャンペーンバナー管理 | D17: 公開開始日時が右記の通り設定されているか | E17: 禮包販售橫幅 (Banner) | F17: 管理工具 活動橫幅管理 | G17: 公開開始日期/時間是否如右方所示設定 | H17: ='参照_概要'!$C$18 -> 46074.708 | I17: OK | J17: IW | K17: Bill | L17: 46062
A18: =ROW()-2 -> 16 | D18: 公開終了日時が右記の通り設定されているか | G18: 公開結束日期/時間是否如右方所示設定 | H18: ='参照_概要'!$D$18 -> 46080.708 | I18: OK | J18: IW | K18: Bill | L18: 46062
A19: =ROW()-2 -> 17 | C19: 実機 | D19: ショップ画面にバナー画像が表示されているか | F19: 實體機台 | G19: 在「商店畫面(Shop)」上是否顯示橫幅圖片 | H19: ='参照_概要'!$C$17+1/24/60 -> 46074.709 | I19: OK | J19: IW | K19: Bill | L19: 46064 | M19: OK | N19: IW | O19: Bill | P19: 2/12
A20: =ROW()-2 -> 18 | D20: バナーをタップすると、セット販売画面へ遷移するか | G20: 點擊橫幅後，是否會轉跳到「禮包販售畫面」 | I20: OK | J20: IW | K20: Bill | L20: 46064 | M20: OK | N20: IW | O20: Bill | P20: 2/12
A21: =ROW()-2 -> 19 | B21: 最終ランキングバナー | C21: キャンペーンバナー管理 | D21: 公開開始日時が右記の通り設定されているか | E21: 最終排行榜橫幅 (Banner) | F21: 管理工具 活動橫幅管理 | G21: 公開開始日期/時間是否如右方所示設定 | H21: ='参照_概要'!$C$19 -> 46080.729 | I21: OK | J21: IW | K21: Bill | L21: 46062
A22: =ROW()-2 -> 20 | D22: 公開終了日時が右記の通り設定されているか | G22: 公開結束日期/時間是否如右方所示設定 | H22: ='参照_概要'!$D$19 -> 46087.729 | I22: OK | J22: IW | K22: Bill | L22: 46062
A23: =ROW()-2 -> 21 | D23: バナー文言が右記の通り設定されているか | G23: 橫幅文字是否如右方所示設定 | H23: ='参照_概要'!$E$19 -> Check your Ranking! | I23: OK | J23: IW | K23: Bill | L23: 46062
A24: =ROW()-2 -> 22 | C24: 実機 | D24: イベント一覧にバナー画像が表示されているか | F24: 實體機台 | G24: 在「活動一覽(Events)」上是否顯示橫幅圖片 | H24: ='参照_概要'!$C$19+1/24/60 -> 46080.73 | I24: OK | J24: IW | K24: Bill | L24: 46064 | M24: OK | N24: IW | O24: Bill | P24: 2/12
A25: =ROW()-2 -> 23 | D25: バナーをタップすると、最終ランキング画面へ遷移するか | G25: 點擊橫幅後，是否會轉跳到「最終排行榜畫面」 | I25: OK | J25: IW | K25: Bill | L25: 46064

Sheet 本編促進
A1: No | B1: 画面 | C1: 確認方法 | D1: 確認項目 | E1: 画面 | F1: 確認方法 | G1: 確認項目 | H1: 日時 / 詳細 | I1: テスト環境 | M1: 本番環境 | Q1: 備考 | R1: テスターコメント | S1: チケットURL
I2: 確認 | J2: 担当 | K2: 担当者 | L2: 日付 | M2: 確認 | N2: 担当 | O2: 担当者 | P2: 日付
A3: =ROW()-2 -> 1 | B3: 本編促進全体 | C3: 管理ツール コレクションイベント | D3: イベント開始日時が右記の日時に設定されているか | E3: 本篇促進活動整體 | F3: 管理工具 收集活動 | G3: 活動開始日期/時間是否如右方所示設定 | H3: ='参照_概要'!$C$17 -> 46074.708 | I3: OK | J3: IW | K3: Bill | L3: 46062
A4: =ROW()-2 -> 2 | D4: イベント終了日時が右記の日時に設定されているか | G4: 活動結束日期/時間是否如右方所示設定 | H4: ='参照_概要'!$D$17 -> 46080.708 | I4: OK | J4: IW | K4: Bill | L4: 46062
A5: =ROW()-2 -> 3 | D5: ランキング開始日時が右記の日時に設定されているか | G5: 排行榜開始日期/時間是否如右方所示設定 | H5: ='参照_概要'!$C$19 -> 46080.729 | I5: OK | J5: IW | K5: Bill | L5: 46062
A6: =ROW()-2 -> 4 | D6: ランキング終了日時が右記の日時に設定されているか | G6: 排行榜結束日期/時間是否如右方所示設定 | H6: ='参照_概要'!$D$19 -> 46087.729 | I6: OK | J6: IW | K6: Bill | L6: 46062
A7: =ROW()-2 -> 5 | B7: 未参加TOP | C7: 実機 | D7: 画面内に日本語表記が残っていないか | E7: 本篇促進活動整體 | F7: 實體機台 | G7: 畫面內的文字是否還有日文表記 (日文未殘留) | I7: OK | J7: IW | K7: Bill | L7: 46064
A8: =ROW()-2 -> 6 | D8: イベントタイトル画像が表示されているか | G8: 活動標題圖片是否顯示 | I8: OK | J8: IW | K8: Bill | L8: 46064 | M8: OK | N8: {=IF(M8:M74="OK",{"IW","Bill","2/12"},)} -> IW | O8: Bill | P8: 2/12
A9: =ROW()-2 -> 7 | D9: イベント訴求画像が表示されているか | G9: 活動宣傳圖片是否顯示 | I9: OK | J9: IW | K9: Bill | L9: 46064 | M9: OK | N9: IW | O9: Bill | P9: 2/12
A10: =ROW()-2 -> 8 | D10: 早期前半クリア特典画像が表示されているか | G10: 早期前半達成特典圖片是否顯示 | I10: OK | J10: IW | K10: Bill | L10: 46064 | M10: OK | N10: IW | O10: Bill | P10: 2/12
A11: =ROW()-2 -> 9 | D11: 早期後半クリア特典画像が表示されているか | G11: 早期後半達成特典圖片是否顯示 | I11: OK | J11: IW | K11: Bill | L11: 46064 | M11: OK | N11: IW | O11: Bill | P11: 2/12
A12: =ROW()-2 -> 10 | D12: 早期特典～イベント名～画像が表示されているか | G12: 早期特典～活動名稱～圖片是否顯示 | I12: OK | J12: IW | K12: Bill | L12: 46064 | M12: OK | N12: IW | O12: Bill | P12: 2/12
A13: =ROW()-2 -> 11 | D13: 早期全コレクション特典画像が表示されているか | G13: 早期全收集特典圖片是否顯示 | I13: OK | J13: IW | K13: Bill | L13: 46064 | M13: OK | N13: IW | O13: Bill | P13: 2/12
A14: =ROW()-2 -> 12 | D14: コレクション特典画像が表示されているか | G14: 收集特典圖片是否顯示 | I14: OK | J14: IW | K14: Bill | L14: 46064 | M14: OK | N14: IW | O14: Bill | P14: 2/12
A15: =ROW()-2 -> 13 | D15: 特別コレクション特典画像が表示されているか | G15: 特別收集特典圖片是否顯示 | I15: OK | J15: IW | K15: Bill | L15: 46064 | M15: OK | N15: IW | O15: Bill | P15: 2/12
A16: =ROW()-2 -> 14 | D16: ランキング特典画像が表示されているか | G16: 排行榜特典圖片是否顯示 | I16: OK | J16: IW | K16: Bill | L16: 46064 | M16: OK | N16: IW | O16: Bill | P16: 2/12
A17: =ROW()-2 -> 15 | D17: [ Enter ] ボタンをタップすると、イベントへ参加できるか | G17: 點擊 [ Enter ] 按鈕後，是否可以參加活動 | I17: OK | J17: IW | K17: Bill | L17: 46064 | M17: OK | N17: IW | O17: Bill | P17: 2/12
A18: =ROW()-2 -> 16 | B18: イベントマイページ | C18: 実機 | D18: 画面内に日本語表記が残っていないか | E18: 活動主頁 | F18: 實體機台 | G18: 畫面內是否沒有殘留日文標記 | I18: OK | J18: IW | K18: Bill | L18: 46064
A19: =ROW()-2 -> 17 | D19: イベントタイトル画像が表示されているか | G19: 活動標題圖片是否顯示 | I19: OK | J19: IW | K19: Bill | L19: 46064 | M19: OK | N19: IW | O19: Bill | P19: 2/12
A20: =ROW()-2 -> 18 | D20: コレクトアイテムが使用できるか | G20: 收集道具是否可以使用 | I20: OK | J20: IW | K20: Bill | L20: 46064 | M20: OK | N20: IW | O20: Bill | P20: 2/12
A21: =ROW()-2 -> 19 | D21: 1回に使用する単位が正しいか | G21: 單次使用的單位是否正確 | H21: 10 | I21: OK | J21: IW | K21: Bill | L21: 46064 | M21: OK | N21: IW | O21: Bill | P21: 2/12
A22: =ROW()-2 -> 20 | D22: 使用個数のMAX値が正しいか | G22: 使用數量的最大值是否正確 | H22: 100 | I22: OK | J22: IW | K22: Bill | L22: 46064 | M22: OK | N22: IW | O22: Bill | P22: 2/12
A23: =ROW()-2 -> 21 | D23: メニュー内のヘルプ押下で、ヘルプ画面へ遷移するか | G23: 點擊選單中的「幫助」，是否會跳轉到幫助畫面 | I23: OK | J23: IW | K23: Bill | L23: 46064 | M23: OK | N23: IW | O23: Bill | P23: 2/12
A24: =ROW()-2 -> 22 | D24: ヘルプ画面内に日本語表記が残っていないか | G24: 幫助畫面內是否沒有殘留日文標記 | I24: OK | J24: IW | K24: Bill | L24: 46064
A25: =ROW()-2 -> 23 | D25: 「イベントの説明を聞く」押下で、ストーリーが再生されるか | G25: 點擊「聽取活動說明」，故事是否會播放 | I25: OK | J25: IW | K25: Bill | L25: 46064 | M25: OK | N25: IW | O25: Bill | P25: 2/12
A26: =ROW()-2 -> 24 | D26: メニュー内のフィーバー押下で、フィーバースケジュールモーダルが表示されるか | G26: 點擊選單中的「Fever（加倍時間）」，是否會顯示 Fever 排程彈窗 | I26: OK | J26: IW | K26: Bill | L26: 46064 | M26: OK | N26: IW | O26: Bill | P26: 2/12
A27: =ROW()-2 -> 25 | D27: フィーバースケジュールモーダル内に日本語が残っていないか | G27: Fever 排程彈窗內是否沒有殘留日文 | I27: OK | J27: IW | K27: Bill | L27: 46064
A28: =ROW()-2 -> 26 | D28: 「コレクション特典」押下で、特典一覧へ遷移するか | G28: 點擊「收集特典」，是否會跳轉到特典一覽頁面 | I28: OK | J28: IW | K28: Bill | L28: 46064 | M28: OK | N28: IW | O28: Bill | P28: 2/12
A29: =ROW()-2 -> 27 | D29: 「特別コレクション特典」押下で、特典一覧へ遷移するか | G29: 點擊「特別收集特典」，是否會跳轉到特典一覽頁面 | I29: OK | J29: IW | K29: Bill | L29: 46064 | M29: OK | N29: IW | O29: Bill | P29: 2/12
A30: =ROW()-2 -> 28 | D30: 「物語を読んで恋のハートGET」押下で、ストーリーが再生されるか | G30: 點擊「閱讀故事獲得愛戀之心」，故事是否會播放
A31: =ROW()-2 -> 29 | D31: 「姫磨きで恋のハートGET」押下で、姫磨きへ遷移するか | G31: 點擊「姬磨練獲得愛戀之心」，是否會跳轉到姬磨練頁面
A32: =ROW()-2 -> 30 | D32: 「応援セットで恋のハートGET」押下で、セット販売へ遷移するか | G32: 點擊「應援禮包獲得愛戀之心」，是否會跳轉到禮包販售頁面
A33: =ROW()-2 -> 31 | D33: 「お相手変更で恋のハートGET」押下で、お相手変更へ遷移するか | G33: 點擊「變更對象獲得愛戀之心」，是否會跳轉到變更對象頁面
A34: =ROW()-2 -> 32 | D34: 任意のセット購入訴求ポップアップが表示されるか | G34: 是否會顯示任意禮包購買宣傳彈窗 | H34: 任1禮包確認 | I34: OK | J34: IW | K34: Bill | L34: 46064 | M34: OK | N34: IW | O34: Bill | P34: 2/12
A35: =ROW()-2 -> 33 | B35: ランキング | C35: 実機 | D35: 画面内に日本語表記が残っていないか | E35: 排行榜 | F35: 實體機台 | G35: 畫面內是否沒有殘留日文標記 | I35: OK | J35: IW | K35: Bill | L35: 46064
A36: =ROW()-2 -> 34 | B36: 特典一覧 | C36: 実機 | D36: 画面内に日本語表記が残っていないか | E36: 特典一覽 | F36: 實體機台 | G36: 畫面內是否沒有殘留日文標記 | I36: OK | J36: IW | K36: Bill | L36: 46064
A37: =ROW()-2 -> 35 | B37: 特典一覧 ＞特典詳細 | C37: 実機 | D37: 着用イメージ画像が表示されているか | E37: 特典一覽 ＞特典詳情 | F37: 實體機台 | G37: 穿戴形象圖片(Sample Image)是否顯示 | I37: OK | J37: IW | K37: Bill | L37: 46064 | M37: OK | N37: IW | O37: Bill | P37: 2/12
A38: =ROW()-2 -> 36 | D38: 早期前半クリア特典画像が表示されているか | G38: 早期前半達成特典圖片是否顯示 | I38: OK | J38: IW | K38: Bill | L38: 46064 | M38: OK | N38: IW | O38: Bill | P38: 2/12
A39: =ROW()-2 -> 37 | D39: 訴求画像押下で、早期前半クリア特典モーダルが表示されるか | G39: 點擊宣傳圖片後，是否會顯示早期前半達成特典彈窗 | I39: OK | J39: IW | K39: Bill | L39: 46064 | M39: OK | N39: IW | O39: Bill | P39: 2/12
A40: =ROW()-2 -> 38 | D40: 早期後半クリア特典画像が表示されているか | G40: 早期後半達成特典圖片是否顯示 | I40: OK | J40: IW | K40: Bill | L40: 46064 | M40: OK | N40: IW | O40: Bill | P40: 2/12
A41: =ROW()-2 -> 39 | D41: 訴求画像押下で、早期後半クリア特典モーダルが表示されるか | G41: 點擊宣傳圖片後，是否會顯示早期後半達成特典彈窗 | I41: OK | J41: IW | K41: Bill | L41: 46064 | M41: OK | N41: IW | O41: Bill | P41: 2/12
A42: =ROW()-2 -> 40 | D42: 早期特典～イベント名～画像が表示されているか | G42: 早期特典～活動名稱～圖片是否顯示 | I42: OK | J42: IW | K42: Bill | L42: 46064 | M42: OK | N42: IW | O42: Bill | P42: 2/12
A43: =ROW()-2 -> 41 | D43: 訴求画像押下で、早期特典～イベント名～特典モーダルが表示されるか | G43: 點擊宣傳圖片後，是否會顯示早期特典～活動名稱～特典彈窗 | I43: OK | J43: IW | K43: Bill | L43: 46064 | M43: OK | N43: IW | O43: Bill | P43: 2/12
A44: =ROW()-2 -> 42 | D44: 早期全コレクション特典画像が表示されているか | G44: 早期全收集特典圖片是否顯示 | I44: OK | J44: IW | K44: Bill | L44: 46064 | M44: OK | N44: IW | O44: Bill | P44: 2/12
A45: =ROW()-2 -> 43 | D45: 訴求画像押下で、早期全コレクション特典モーダルが表示されるか | G45: 點擊宣傳圖片後，是否會顯示早期全收集特典彈窗 | I45: OK | J45: IW | K45: Bill | L45: 46064 | M45: OK | N45: IW | O45: Bill | P45: 2/12
A46: =ROW()-2 -> 44 | D46: ストーリー特典画像が表示されているか | G46: 故事特典圖片是否顯示 | I46: OK | J46: IW | K46: Bill | L46: 46064 | M46: OK | N46: IW | O46: Bill | P46: 2/12
A47: =ROW()-2 -> 45 | D47: 訴求画像押下で、ストーリー特典モーダルが表示されるか | G47: 點擊宣傳圖片後，是否會顯示故事特典彈窗 | I47: OK | J47: IW | K47: Bill | L47: 46064 | M47: OK | N47: IW | O47: Bill | P47: 2/12
A48: =ROW()-2 -> 46 | D48: コレクション特典画像が表示されているか | G48: 收集特典圖片是否顯示 | I48: OK | J48: IW | K48: Bill | L48: 46064 | M48: OK | N48: IW | O48: Bill | P48: 2/12
A49: =ROW()-2 -> 47 | D49: 訴求画像押下で、コレクション特典モーダルが表示されるか | G49: 點擊宣傳圖片後，是否會顯示收集特典彈窗 | I49: OK | J49: IW | K49: Bill | L49: 46064 | M49: OK | N49: IW | O49: Bill | P49: 2/12
... A55: =ROW()-2 -> 53 | D55: 訴求画像押下で、本編・続編連動特典モーダルが表示されるか | G55: 點擊宣傳圖片後，是否會顯示本篇・續篇連動特典彈窗 | I55: OK | J55: IW | K55: Bill | L55: 46064 | M55: OK | N55: IW | O55: Bill | P55: 2/12
B56: イベント専用アイテム | E56: 活動專屬道具
A57: =ROW()-2 -> 55 | B57: ='参照_仕様'!C5 -> Shaved Ice (+50 Stamina) | C57: 管理ツール アイテム管理 | D57: 使用開始日時が右記の通り設定されているか | E57: ='参照_仕様'!C5 -> Shaved Ice (+50 Stamina) | F57: 管理工具 道具管理 | G57: 使用開始日期/時間是否如右方所示設定 | H57: ='参照_仕様'!$D$5 -> 46074.708 | I57: OK | J57: IW | K57: Bill | L57: 46062
A58: =ROW()-2 -> 56 | D58: 使用終了日時が右記の通り設定されているか | G58: 使用結束日期/時間是否如右方所示設定 | H58: ='参照_仕様'!$E$5 -> 46080.708 | I58: OK | J58: IW | K58: Bill | L58: 46062
A59: =ROW()-2 -> 57 | C59: 実機 | D59: アイテムサムネイルが表示されているか | F59: 實體機台 | G59: 道具縮圖是否顯示 | M59: OK | N59: IW | O59: Bill | P59: 2/12
A60: =ROW()-2 -> 58 | D60: アイテムが正常に使用できるか | G60: 道具是否能正常使用，效果是否正確 | M60: OK | N60: IW | O60: Bill | P60: 2/12
A61: =ROW()-2 -> 59 | B61: ='参照_仕様'!C6 -> Shaved Ice (+100 Stamina) | C61: 管理ツール アイテム管理 | D61: 使用開始日時が右記の通り設定されているか | E61: ='参照_仕様'!C6 -> Shaved Ice (+100 Stamina) | F61: 管理工具 道具管理 | G61: 使用開始日期/時間是否如右方所示設定 | H61: ='参照_仕様'!$D$6 -> 46074.708 | I61: OK | J61: IW | K61: Bill | L61: 46062
A62: =ROW()-2 -> 60 | D62: 使用終了日時が右記の通り設定されているか | G62: 使用結束日期/時間是否如右方所示設定 | H62: ='参照_仕様'!$E$6 -> 46080.708 | I62: OK | J62: IW | K62: Bill | L62: 46062
A63: =ROW()-2 -> 61 | C63: 実機 | D63: アイテムサムネイルが表示されているか | F63: 實體機台 | G63: 道具縮圖是否顯示 | M63: OK | N63: IW | O63: Bill | P63: 2/12
A64: =ROW()-2 -> 62 | D64: アイテムが正常に使用できるか | G64: 道具是否能正常使用，效果是否正確 | M64: OK | N64: IW | O64: Bill | P64: 2/12
A65: =ROW()-2 -> 63 | B65: ='参照_仕様'!C7 -> Limited Chapter Ticket | C65: 管理ツール アイテム管理 | D65: 使用開始日時が右記の通り設定されているか | E65: ='参照_仕様'!C7 -> Limited Chapter Ticket | F65: 管理工具 道具管理 | G65: 使用開始日期/時間是否如右方所示設定 | H65: ='参照_仕様'!$D$7 -> 46074.708 | I65: OK | J65: IW | K65: Bill | L65: 46062
A66: =ROW()-2 -> 64 | D66: 使用終了日時が右記の通り設定されているか | G66: 使用結束日期/時間是否如右方所示設定 | H66: ='参照_仕様'!$E$7 -> 46080.708 | I66: OK | J66: IW | K66: Bill | L66: 46062
A67: =ROW()-2 -> 65 | C67: 実機 | D67: アイテムサムネイルが表示されているか | F67: 實體機台 | G67: 道具縮圖是否顯示 | M67: OK | N67: IW | O67: Bill | P67: 2/12
A68: =ROW()-2 -> 66 | D68: アイテムが正常に使用できるか | G68: 道具是否能正常使用，效果是否正確 | M68: OK | N68: IW | O68: Bill | P68: 2/12
B69: コレクトアイテム取得 | E69: 獲得收集特典
A70: =ROW()-2 -> 68 | B70: コレクトアイテム取得 | C70: 実機 | D70: イベント参加後に取得できるか | E70: 獲得收集特典 | F70: 實體機台 | G70: 參加活動後是否能取得 | H70: 10個 | M70: OK | N70: IW | O70: Bill | P70: 2/12
A71: =ROW()-2 -> 69 | D71: 0:00～12:00の間にイベントマイページアクセスで取得できるか | G71: 在 0:00～12:00 期間內進入活動主頁是否能取得 | H71: 1個 | M71: OK | N71: IW | O71: Bill | P71: 2/12
A72: =ROW()-2 -> 70 | D72: 12:00～24:00の間にイベントマイページアクセスで取得できるか | G72: 在 12:00～24:00 期間內進入活動主頁是否能取得 | H72: 1個 | M72: OK | N72: IW | O72: Bill | P72: 2/12
A73: =ROW()-2 -> 71 | D73: お相手変更で取得できるか | G73: 變更對象後是否能取得 | H73: 10個 | M73: OK | N73: IW | O73: Bill | P73: 2/12
A74: =ROW()-2 -> 72 | D74: 物語の5チケまたは10チケ読了で取得できるか | G74: 閱讀故事 5 節或 10 節後是否能取得 | H74: 5個 | M74: OK | N74: IW | O74: Bill | P74: 2/12
A75: =ROW()-2 -> 73 | D75: 姫磨きを5回実行で取得できるか | G75: 執行姬磨練 5 次後是否能取得 | H75: 2個 | M75: OK | N75: IW | O75: Bill | P75: 46064

Sheet 特典
A1: No | B1: ボーナス名 | C1: 確認方法 | D1: 確認項目 | E1: 特典名稱 | F1: 確認方法 | G1: 確認項目 | H1: 取得期間/条件 | I1: table | J1: ID | K1: Column | L1: Result | M1: テスト環境 | Q1: 本番環境 | U1: 備考 | V1: テスターコメント | W1: チケットURL
M2: 確認 | N2: 担当 | O2: 担当者 | P2: 日付 | Q2: 確認 | R2: 担当 | S2: 担当者 | T2: 日付
A3: =ROW()-2 -> 1 | B3: ='参照_各種特典'!C12&" "&'参照_各種特典'!D12 -> 早期前半特典 Early Clear Bonus Gold | C3: 管理ツール コレクションイベント＞該当イベント＞各種特典 | D3: 開始日時が右記の通り設定されているか | E3: ='参照_各種特典'!C12&" "&'参照_各種特典'!D12 -> 早期前半特典 Early Clear Bonus Gold | F3: 管理工具 收集活動＞該活動＞各種特典 | G3: 開始日期時間是否按右側設定 | H3: ='参照_各種特典'!I12 -> 46074.708 | I3: BonusGroup!B5:J | J3: ce_203_bonus_group_001 | K3: 6 | L3: =IF(ISTEXT(I3:I137), VLOOKUP(J3:J137,INDIRECT(I3:I137),K3:K137,0), ) -> 46074.708 | M3: OK | N3: IW | O3: Bill | P3: 46062
A4: =ROW()-2 -> 2 | D4: 終了日時が右記の通り設定されているか | G4: 結束日期時間是否按右側設定 | H4: ='参照_各種特典'!J12 -> 46075.958 | I4: BonusGroup!B5:J | J4: ce_203_bonus_group_001 | K4: 7 | L4: =IF(ISTEXT(I4:I138), VLOOKUP(J4:J138,INDIRECT(I4:I138),K4:K138,0), ) -> 46075.958 | M4: OK | N4: IW | O4: Bill | P4: 46062
A5: =ROW()-2 -> 3 | D5: 特典内容が右記の通り設定されているか | G5: 特典內容是否按右側設定 | H5: ='参照_各種特典'!F12 -> Blue Anemone Hair Clip | I5: Bonus!A5:L | J5: ce_203_bonus_group_001 | K5: 6 | L5: =IF(ISTEXT(I5:I139), VLOOKUP(J5:J139,INDIRECT(I5:I139),K5:K139,0), ) -> Blue Anemone Hair Clip | M5: OK | N5: IW | O5: Bill | P5: 46063 | U5: ①ボーナス詳細＞確認を押下後、遷移先で「プレゼントID」を確認する ②プレゼント登録ページで、①の「プレゼントID」を検索し、表示されたアイテムが仕様書通りかを確認する | V5: 2026/2/9 驗證單配置資料與後台不符
A6: =ROW()-2 -> 4 | C6: コレクションイベント＞該当イベント＞エンジン設定＞EARLY_BONUS_GOLDの値 | D6: 取得条件の数値が右記の通り設定されているか | F6: 收集活動＞該活動＞引擎設定＞EARLY_BONUS_GOLD的值 | G6: 取得條件的數值是否按右側設定 | H6: 140 | I6: BonusGroup!B5:J | J6: ce_203_bonus_group_001 | K6: 9 | L6: =IF(ISTEXT(I6:I140), VLOOKUP(J6:J140,INDIRECT(I6:I140),K6:K140,0), ) -> 140 | M6: OK | N6: IW | O6: Bill | P6: 46062 | U6: IDの数値が大きい方が採用される
A7: =ROW()-2 -> 5 | C7: 実機 | D7: 特典一覧にてモーダル内の特典内容が右記の通り表示されているか | F7: 實體機台 | G7: 特典一覽中的彈窗內特典內容是否按右側顯示 | H7: ='参照_各種特典'!G13 -> Collect 140 Hearts by 2/22 11:00 PM PST for this! | I7: BonusGroup!B5:J | J7: ce_203_bonus_group_001 | K7: 5 | L7: =IF(ISTEXT(I7:I141), VLOOKUP(J7:J141,INDIRECT(I7:I141),K7:K141,0), ) -> Collect 140 Hearts by 2/22 11:00 PM PST for this! | M7: OK | N7: IW | O7: Bill | P7: 46064 | V7: 2026/2/9 驗證單配置資料與後台不符，驗證單資料時間錯誤
A8: =ROW()-2 -> 6 | D8: サムネイル画像が表示されているか | G8: 是否正常顯示縮圖 | L8: =IF(ISTEXT(I8:I142), VLOOKUP(J8:J142,INDIRECT(I8:I142),K8:K142,0), ) | M8: OK | N8: IW | O8: Bill | P8: 46064 | Q8: OK | R8: {=IF(Q8:Q137="OK",{"IW","Bill","2/12"},)} -> IW | S8: Bill | T8: 2/12
A9: =ROW()-2 -> 7 | B9: ='参照_各種特典'!C14&" "&'参照_各種特典'!D14 -> 早期後半特典 Early Clear Bonus Silver | C9: コレクションイベント＞該当イベント＞各種特典 | D9: 開始日時が右記の通り設定されているか | E9: ='参照_各種特典'!C14&" "&'参照_各種特典'!D14 -> 早期後半特典 Early Clear Bonus Silver | F9: 收集活動＞該活動＞各種特典 | G9: 開始日期時間是否按右側設定 | H9: ='参照_各種特典'!I14 -> 46074.708 | I9: BonusGroup!B5:J | J9: ce_203_bonus_group_002 | K9: 6 | L9: =IF(ISTEXT(I9:I143), VLOOKUP(J9:J143,INDIRECT(I9:I143),K9:K143,0), ) -> 46074.708 | M9: OK | N9: IW | O9: Bill | P9: 46062
A10: =ROW()-2 -> 8 | D10: 終了日時が右記の通り設定されているか | G10: 結束日期時間是否按右側設定 | H10: ='参照_各種特典'!J14 -> 46076.958 | I10: BonusGroup!B5:J | J10: ce_203_bonus_group_002 | K10: 7 | L10: =IF(ISTEXT(I10:I144), VLOOKUP(J10:J144,INDIRECT(I10:I144),K10:K144,0), ) -> 46076.958 | M10: OK | N10: IW | O10: Bill | P10: 46062
A11: =ROW()-2 -> 9 | D11: 特典内容が右記の通り設定されているか | G11: 特典內容是否按右側設定 | H11: ='参照_各種特典'!F14 -> Shining Silver Ash Hair | I11: Bonus!A5:L | J11: ce_203_bonus_group_002 | K11: 6 | L11: =IF(ISTEXT(I11:I145), VLOOKUP(J11:J145,INDIRECT(I11:I145),K11:K145,0), ) -> Shining Silver Ash Hair | M11: OK | N11: IW | O11: Bill | P11: 46063 | V11: 2026/2/9 驗證單配置資料與後台不符
A12: =ROW()-2 -> 10 | C12: コレクションイベント＞該当イベント＞エンジン設定＞EARLY_BONUS_SILVERの値 | D12: 取得条件の数値が右記の通り設定されているか | F12: 收集活動＞該活動＞引擎設定＞EARLY_BONUS_SILVER的值 | G12: 取得條件的數值是否按右側設定 | H12: 240 | I12: BonusGroup!B5:J | J12: ce_203_bonus_group_002 | K12: 9 | L12: =IF(ISTEXT(I12:I146), VLOOKUP(J12:J146,INDIRECT(I12:I146),K12:K146,0), ) -> 240 | M12: OK | N12: IW | O12: Bill | P12: 46062 | U12: IDの数値が大きい方が採用される
A13: =ROW()-2 -> 11 | C13: 実機 | D13: 特典一覧にてモーダル内の特典内容が右記の通り表示されているか | F13: 實體機台 | G13: 特典一覽中的彈窗內特典內容是否按右側顯示 | H13: ='参照_各種特典'!G15 -> Collect 240 Hearts by 2/23 11:00 PM PST for this! | I13: BonusGroup!B5:J | J13: ce_203_bonus_group_002 | K13: 5 | L13: =IF(ISTEXT(I13:I147), VLOOKUP(J13:J147,INDIRECT(I13:I147),K13:K147,0), ) -> Collect 240 Hearts by 2/23 11:00 PM PST for this! | M13: OK | N13: IW | O13: Bill | P13: 46064 | V13: 2026/2/9 驗證單配置資料與後台不符，驗證單資料時間錯誤
A14: =ROW()-2 -> 12 | D14: サムネイル画像が表示されているか | G14: 是否正常顯示縮圖 | L14: =IF(ISTEXT(I14:I148), VLOOKUP(J14:J148,INDIRECT(I14:I148),K14:K148,0), ) | M14: OK | N14: IW | O14: Bill | P14: 46064 | Q14: OK | R14: IW | S14: Bill | T14: 2/12
A15: =ROW()-2 -> 13 | B15: ='参照_各種特典'!C16&" "&'参照_各種特典'!D16 -> 早期～演技派な彼編～特典 Early Clear Bonus Mystic Matrimony ~My Fated Bride~ | C15: コレクションイベント＞該当イベント＞各種特典 | D15: 開始日時が右記の通り設定されているか | E15: ='参照_各種特典'!C16&" "&'参照_各種特典'!D16 -> 早期～演技派な彼編～特典 Early Clear Bonus Mystic Matrimony ~My Fated Bride~ | F15: 收集活動＞該活動＞各種特典 | G15: 開始日期時間是否按右側設定 | H15: ='参照_各種特典'!I16 -> 46074.708 | I15: BonusGroup!B5:J | J15: ce_203_bonus_group_003 | K15: 6 | L15: =IF(ISTEXT(I15:I149), VLOOKUP(J15:J149,INDIRECT(I15:I149),K15:K149,0), ) -> 46074.708 | M15: OK | N15: IW | O15: Bill | P15: 46062
A16: =ROW()-2 -> 14 | D16: 終了日時が右記の通り設定されているか | G16: 結束日期時間是否按右側設定 | H16: ='参照_各種特典'!J16 -> 46077.958 | I16: BonusGroup!B5:J | J16: ce_203_bonus_group_003 | K16: 7 | L16: =IF(ISTEXT(I16:I150), VLOOKUP(J16:J150,INDIRECT(I16:I150),K16:K150,0), ) -> 46077.958 | M16: OK | N16: IW | O16: Bill | P16: 46063 | V16: 2026/2/9 驗證單配置資料與後台不符
A17: =ROW()-2 -> 15 | D17: 特典内容が右記の通り設定されているか | G17: 特典內容是否按右側設定 | H17: ='参照_各種特典'!F16 -> Effect: Shiny White Spider Lily | I17: Bonus!A5:L | J17: ce_203_bonus_group_003 | K17: 6 | L17: =IF(ISTEXT(I17:I151), VLOOKUP(J17:J151,INDIRECT(I17:I151),K17:K151,0), ) -> Effect: Shiny White Spider Lily | M17: OK | N17: IW | O17: Bill | P17: 46063 | V17: 2026/2/9 驗證單配置資料與後台不符
A18: =ROW()-2 -> 16 | C18: コレクションイベント＞該当イベント＞エンジン設定＞EARLY_BONUS_COPPERの値 | D18: 取得条件の数値が右記の通り設定されているか | F18: 收集活動＞該活動＞引擎設定＞EARLY_BONUS_COPPER的值 | G18: 取得條件的數值是否按右側設定 | H18: 400 | I18: BonusGroup!B5:J | J18: ce_203_bonus_group_003 | K18: 9 | L18: =IF(ISTEXT(I18:I152), VLOOKUP(J18:J152,INDIRECT(I18:I152),K18:K152,0), ) -> 400 | M18: OK | N18: IW | O18: Bill | P18: 46062 | U18: IDの数値が大きい方が採用される
A19: =ROW()-2 -> 17 | C19: 実機 | D19: 特典一覧にてモーダル内の特典内容が右記の通り表示されているか | F19: 實體機台 | G19: 特典一覽中的彈窗內特典內容是否按右側顯示 | H19: ='参照_各種特典'!G17 -> Collect 400 Hearts by 2/24 11:00 PM PST for this! | I19: BonusGroup!B5:J | J19: ce_203_bonus_group_003 | K19: 5 | L19: =IF(ISTEXT(I19:I153), VLOOKUP(J19:J153,INDIRECT(I19:I153),K19:K153,0), ) -> Collect 400 Hearts by 2/24 11:00 PM PST for this! | M19: OK | N19: IW | O19: Bill | P19: 46064 | V19: 2026/2/9 驗證單配置資料與後台不符，驗證單資料時間錯誤
A20: =ROW()-2 -> 18 | D20: サムネイル画像が表示されているか | G20: 是否正常顯示縮圖 | L20: =IF(ISTEXT(I20:I154), VLOOKUP(J20:J154,INDIRECT(I20:I154),K20:K154,0), ) | M20: OK | N20: IW | O20: Bill | P20: 46064 | Q20: OK | R20: IW | S20: Bill | T20: 2/12
A21: =ROW()-2 -> 19 | B21: ='参照_各種特典'!C18&" "&'参照_各種特典'!D18 -> 早期全コレクション特典 Early Clear Bonus Platinum | C21: コレクションイベント＞該当イベント＞各種特典 | D21: 開始日時が右記の通り設定されているか | E21: ='参照_各種特典'!C18&" "&'参照_各種特典'!D18 -> 早期全コレクション特典 Early Clear Bonus Platinum | F21: 收集活動＞該活動＞各種特典 | G21: 開始日期時間是否按右側設定 | H21: ='参照_各種特典'!I18 -> 46074.708 | I21: BonusGroup!B5:J | J21: ce_203_bonus_group_004 | K21: 6 | L21: =IF(ISTEXT(I21:I155), VLOOKUP(J21:J155,INDIRECT(I21:I155),K21:K155,0), ) -> 46074.708 | M21: OK | N21: IW | O21: Bill | P21: 46062
A22: =ROW()-2 -> 20 | D22: 終了日時が右記の通り設定されているか | G22: 結束日期時間是否按右側設定 | H22: ='参照_各種特典'!J18 -> 46078.958 | I22: BonusGroup!B5:J | J22: ce_203_bonus_group_004 | K22: 7 | L22: =IF(ISTEXT(I22:I156), VLOOKUP(J22:J156,INDIRECT(I22:I156),K22:K156,0), ) -> 46078.958 | M22: OK | N22: IW | O22: Bill | P22: 46063 | V22: 2026/2/9 驗證單配置資料與後台不符
A23: =ROW()-2 -> 21 | D23: 特典内容が右記の通り設定されているか | G23: 特典內容是否按右側設定 | H23: ='参照_各種特典'!F18 -> The Forest Where Spirits Dwell | I23: Bonus!A5:L | J23: ce_203_bonus_group_004 | K23: 6 | L23: =IF(ISTEXT(I23:I157), VLOOKUP(J23:J157,INDIRECT(I23:I157),K23:K157,0), ) -> The Forest Where Spirits Dwell | M23: OK | N23: IW | O23: Bill | P23: 46063 | V23: 2026/2/9 驗證單配置資料與後台不符
A24: =ROW()-2 -> 22 | C24: コレクションイベント＞該当イベント＞エンジン設定＞EARLY_BONUS_ALL_COLLECTION値 | D24: 取得条件の数値が右記の通り設定されているか | F24: 收集活動＞該活動＞引擎設定＞EARLY_BONUS_ALL_COLLECTION値 | G24: 取得條件的數值是否按右側設定 | H24: 560 | I24: BonusGroup!B5:J | J24: ce_203_bonus_group_004 | K24: 9 | L24: =IF(ISTEXT(I24:I158), VLOOKUP(J24:J158,INDIRECT(I24:I158),K24:K158,0), ) -> 560 | M24: OK | N24: IW | O24: Bill | P24: 46062 | U24: IDの数値が大きい方が採用される
A25: =ROW()-2 -> 23 | C25: 実機 | D25: 特典一覧にてモーダル内の特典内容が右記の通り表示されているか | F25: 實體機台 | G25: 特典一覽中的彈窗內特典內容是否按右側顯示 | H25: ='参照_各種特典'!G19 -> Collect 560 Hearts by 2/25 11:00 PM PST for this! | I25: BonusGroup!B5:J | J25: ce_203_bonus_group_004 | K25: 5 | L25: =IF(ISTEXT(I25:I159), VLOOKUP(J25:J159,INDIRECT(I25:I159),K25:K159,0), ) -> Collect 560 Hearts by 2/25 11:00 PM PST for this! | M25: OK | N25: IW | O25: Bill | P25: 46064 | V25: 2026/2/9 驗證單配置資料與後台不符
A26: =ROW()-2 -> 24 | D26: サムネイル画像が表示されているか | G26: 是否正常顯示縮圖 | L26: =IF(ISTEXT(I26:I160), VLOOKUP(J26:J160,INDIRECT(I26:I160),K26:K160,0), ) | M26: OK | N26: IW | O26: Bill | P26: 46064 | Q26: OK | R26: IW | S26: Bill | T26: 2/12
A27: =ROW()-2 -> 25 | B27: Bonus Stories | C27: 実機 | D27: 特典内容が右記の通り表示されているか | E27: "Bonus Storiesと Special Colletion Bonuses内のストーリー ※故事名稱在「Bonus Stories」看不到，所以請大致確認圖片人物等有符合即可。而故事名稱會出現在「Collection Bonus」&「Special Collection Bonus」，出現在該處時須確認 | F27: 實體機台 | G27: 特典內容是否按右側設定 | H27: ='参照_仕様'!C11 -> Mystic Matrimony Bonus Story ～Masamune～ | I27: Bonus!J5:L | J27: 6314 | K27: 2 | L27: =IF(ISTEXT(I27:I161), VLOOKUP(J27:J161,INDIRECT(I27:I161),K27:K161,0), ) -> Mystic Matrimony Bonus Story ～Masamune～ | M27: OK | N27: IW | O27: Bill | P27: 46062
A28: =ROW()-2 -> 26 | D28: 訴求バナー画像が表示されているか | G28: 是否顯示宣傳橫幅圖片 | L28: =IF(ISTEXT(I28:I162), VLOOKUP(J28:J162,INDIRECT(I28:I162),K28:K162,0), ) | M28: OK | N28: IW | O28: Bill | P28: 46064 | Q28: OK | R28: IW | S28: Bill | T28: 2/12
A29: =ROW()-2 -> 27 | D29: サムネイル画像が表示されているか | G29: 是否正常顯示縮圖 | L29: =IF(ISTEXT(I29:I163), VLOOKUP(J29:J163,INDIRECT(I29:I163),K29:K163,0), ) | M29: OK | N29: IW | O29: Bill | P29: 46064 | Q29: OK | R29: IW | S29: Bill | T29: 2/12
A30: =ROW()-2 -> 28 | C30: 実機 | D30: 特典内容が右記の通り表示されているか | F30: 實體機台 | G30: 特典內容是否按右側設定 | H30: ='参照_仕様'!C12 -> Mystic Matrimony Bonus Story ～Nobunaga～ | I30: Bonus!J5:L | J30: 6315 | K30: 2 | L30: =IF(ISTEXT(I30:I164), VLOOKUP(J30:J164,INDIRECT(I30:I164),K30:K164,0), ) -> Mystic Matrimony Bonus Story ～Nobunaga～ | M30: OK | N30: IW | O30: Bill | P30: 46062
A31: =ROW()-2 -> 29 | D31: 訴求バナー画像が表示されているか | G31: 是否顯示宣傳橫幅圖片 | L31: =IF(ISTEXT(I31:I165), VLOOKUP(J31:J165,INDIRECT(I31:I165),K31:K165,0), ) | M31: OK | N31: IW | O31: Bill | P31: 46064 | Q31: OK | R31: IW | S31: Bill | T31: 2/12
A32: =ROW()-2 -> 30 | D32: サムネイル画像が表示されているか | G32: 是否正常顯示縮圖 | L32: =IF(ISTEXT(I32:I166), VLOOKUP(J32:J166,INDIRECT(I32:I166),K32:K166,0), ) | M32: OK | N32: IW | O32: Bill | P32: 46064 | Q32: OK | R32: IW | S32: Bill | T32: 2/12
A33: =ROW()-2 -> 31 | C33: 実機 | D33: 特典内容が右記の通り表示されているか | F33: 實體機台 | G33: 特典內容是否按右側設定 | H33: ='参照_仕様'!C13 -> Mystic Matrimony Bonus Story ～Kanetsugu～ | I33: Bonus!J5:L | J33: 6316 | K33: 2 | L33: =IF(ISTEXT(I33:I167), VLOOKUP(J33:J167,INDIRECT(I33:I167),K33:K167,0), ) -> Mystic Matrimony Bonus Story ～Kanetsugu～ | M33: OK | N33: IW | O33: Bill | P33: 46062
A34: =ROW()-2 -> 32 | D34: 訴求バナー画像が表示されているか | G34: 是否顯示宣傳橫幅圖片 | L34: =IF(ISTEXT(I34:I168), VLOOKUP(J34:J168,INDIRECT(I34:I168),K34:K168,0), ) | M34: OK | N34: IW | O34: Bill | P34: 46064 | Q34: OK | R34: IW | S34: Bill | T34: 2/12
A35: =ROW()-2 -> 33 | D35: サムネイル画像が表示されているか | G35: 是否正常顯示縮圖 | L35: =IF(ISTEXT(I35:I169), VLOOKUP(J35:J169,INDIRECT(I35:I169),K35:K169,0), ) | M35: OK | N35: IW | O35: Bill | P35: 46064 | Q35: OK | R35: IW | S35: Bill | T35: 2/12
A36: =ROW()-2 -> 34 | C36: 実機 | D36: 特典内容が右記の通り表示されているか | F36: 實體機台 | G36: 特典內容是否按右側設定 | H36: ='参照_仕様'!C14 -> Mystic Matrimony Bonus Story ～Kicho～ | I36: Bonus!J5:L | J36: 6317 | K36: 2 | L36: =IF(ISTEXT(I36:I170), VLOOKUP(J36:J170,INDIRECT(I36:I170),K36:K170,0), ) -> Mystic Matrimony Bonus Story ～Kicho～ | M36: OK | N36: IW | O36: Bill | P36: 46062
A37: =ROW()-2 -> 35 | D37: 訴求バナー画像が表示されているか | G37: 是否顯示宣傳橫幅圖片 | L37: =IF(ISTEXT(I37:I171), VLOOKUP(J37:J171,INDIRECT(I37:I171),K37:K171,0), ) | M37: OK | N37: IW | O37: Bill | P37: 46064 | Q37: OK | R37: IW | S37: Bill | T37: 2/12
A38: =ROW()-2 -> 36 | D38: サムネイル画像が表示されているか | G38: 是否正常顯示縮圖 | L38: =IF(ISTEXT(I38:I172), VLOOKUP(J38:J172,INDIRECT(I38:I172),K38:K172,0), ) | M38: OK | N38: IW | O38: Bill | P38: 46064 | Q38: OK | R38: IW | S38: Bill | T38: 2/12
A39: =ROW()-2 -> 37 | C39: 実機 | D39: 特典内容が右記の通り表示されているか | F39: 實體機台 | G39: 特典內容是否按右側設定 | H39: ='参照_仕様'!C15 -> Mystic Matrimony Bonus Story ～Motonari～ | I39: Bonus!J5:L | J39: 6318 | K39: 2 | L39: =IF(ISTEXT(I39:I173), VLOOKUP(J39:J173,INDIRECT(I39:I173),K39:K173,0), ) -> Mystic Matrimony Bonus Story ～Motonari～ | M39: OK | N39: IW | O39: Bill | P39: 46062
A40: =ROW()-2 -> 38 | D40: 訴求バナー画像が表示されているか | G40: 是否顯示宣傳橫幅圖片 | L40: =IF(ISTEXT(I40:I174), VLOOKUP(J40:J174,INDIRECT(I40:I174),K40:K174,0), ) | M40: OK | N40: IW | O40: Bill | P40: 46064 | Q40: OK | R40: IW | S40: Bill | T40: 2/12
A41: =ROW()-2 -> 39 | D41: サムネイル画像が表示されているか | G41: 是否正常顯示縮圖 | L41: =IF(ISTEXT(I41:I175), VLOOKUP(J41:J175,INDIRECT(I41:I175),K41:K175,0), ) | M41: OK | N41: IW | O41: Bill | P41: 46064 | Q41: OK | R41: IW | S41: Bill | T41: 2/12
A42: =ROW()-2 -> 40 | C42: 実機 | D42: 特典内容が右記の通り表示されているか | F42: 實體機台 | G42: 特典內容是否按右側設定 | H42: ='参照_仕様'!C16 -> Mystic Matrimony Bonus Story ～Yoshimoto～ | I42: Bonus!J5:L | J42: 6319 | K42: 2 | L42: =IF(ISTEXT(I42:I176), VLOOKUP(J42:J176,INDIRECT(I42:I176),K42:K176,0), ) -> Mystic Matrimony Bonus Story ～Yoshimoto～ | M42: OK | N42: IW | O42: Bill | P42: 46062
A43: =ROW()-2 -> 41 | D43: 訴求バナー画像が表示されているか | G43: 是否顯示宣傳橫幅圖片 | L43: =IF(ISTEXT(I43:I177), VLOOKUP(J43:J177,INDIRECT(I43:I177),K43:K177,0), ) | M43: OK | N43: IW | O43: Bill | P43: 46064 | Q43: OK | R43: IW | S43: Bill | T43: 2/12
A44: =ROW()-2 -> 42 | D44: サムネイル画像が表示されているか | G44: 是否正常顯示縮圖 | L44: =IF(ISTEXT(I44:I178), VLOOKUP(J44:J178,INDIRECT(I44:I178),K44:K178,0), ) | M44: OK | N44: IW | O44: Bill | P44: 46064 | Q44: OK | R44: IW | S44: Bill | T44: 2/12
A45: =ROW()-2 -> 43 | C45: 実機 | D45: 特典内容が右記の通り表示されているか | F45: 實體機台 | G45: 特典內容是否按右側設定 | H45: ='参照_仕様'!C17 -> Mystic Matrimony After Story ～Masamune～ | I45: Bonus!J5:L | J45: 6320 | K45: 2 | L45: =IF(ISTEXT(I45:I179), VLOOKUP(J45:J179,INDIRECT(I45:I179),K45:K179,0), ) -> Mystic Matrimony After Story ～Masamune～ | M45: OK | N45: IW | O45: Bill | P45: 46062
A46: =ROW()-2 -> 44 | D46: 訴求バナー画像が表示されているか | G46: 是否顯示宣傳橫幅圖片 | L46: =IF(ISTEXT(I46:I180), VLOOKUP(J46:J180,INDIRECT(I46:I180),K46:K180,0), ) | M46: OK | N46: IW | O46: Bill | P46: 46064 | Q46: OK | R46: IW | S46: Bill | T46: 2/12
A47: =ROW()-2 -> 45 | D47: サムネイル画像が表示されているか | G47: 是否正常顯示縮圖 | L47: =IF(ISTEXT(I47:I181), VLOOKUP(J47:J181,INDIRECT(I47:I181),K47:K181,0), ) | M47: OK | N47: IW | O47: Bill | P47: 46064 | Q47: OK | R47: IW | S47: Bill | T47: 2/12
A48: =ROW()-2 -> 46 | C48: 実機 | D48: 特典内容が右記の通り表示されているか | F48: 實體機台 | G48: 特典內容是否按右側設定 | H48: ='参照_仕様'!C18 -> Mystic Matrimony After Story ～Nobunaga～ | I48: Bonus!J5:L | J48: 6321 | K48: 2 | L48: =IF(ISTEXT(I48:I182), VLOOKUP(J48:J182,INDIRECT(I48:I182),K48:K182,0), ) -> Mystic Matrimony After Story ～Nobunaga～ | M48: OK | N48: IW | O48: Bill | P48: 46062
A49: =ROW()-2 -> 47 | D49: 訴求バナー画像が表示されているか | G49: 是否顯示宣傳橫幅圖片 | L49: =IF(ISTEXT(I49:I183), VLOOKUP(J49:J183,INDIRECT(I49:I183),K49:K183,0), ) | M49: OK | N49: IW | O49: Bill | P49: 46064 | Q49: OK | R49: IW | S49: Bill | T49: 2/12
A50: =ROW()-2 -> 48 | D50: サムネイル画像が表示されているか | G50: 是否正常顯示縮圖 | L50: =IF(ISTEXT(I50:I184), VLOOKUP(J50:J184,INDIRECT(I50:I184),K50:K184,0), ) | M50: OK | N50: IW | O50: Bill | P50: 46064 | Q50: OK | R50: IW | S50: Bill | T50: 2/12
A51: =ROW()-2 -> 49 | C51: 実機 | D51: 特典内容が右記の通り表示されているか | F51: 實體機台 | G51: 特典內容是否按右側設定 | H51: ='参照_仕様'!C19 -> Mystic Matrimony After Story ～Kanetsugu～ | I51: Bonus!J5:L | J51: 6322 | K51: 2 | L51: =IF(ISTEXT(I51:I185), VLOOKUP(J51:J185,INDIRECT(I51:I185),K51:K185,0), ) -> Mystic Matrimony After Story ～Kanetsugu～ | M51: OK | N51: IW | O51: Bill | P51: 46062
A52: =ROW()-2 -> 50 | D52: 訴求バナー画像が表示されているか | G52: 是否顯示宣傳橫幅圖片 | L52: =IF(ISTEXT(I52:I186), VLOOKUP(J52:J186,INDIRECT(I52:I186),K52:K186,0), ) | M52: OK | N52: IW | O52: Bill | P52: 46064 | Q52: OK | R52: IW | S52: Bill | T52: 2/12
A53: =ROW()-2 -> 51 | D53: サムネイル画像が表示されているか | G53: 是否正常顯示縮圖 | L53: =IF(ISTEXT(I53:I187), VLOOKUP(J53:J187,INDIRECT(I53:I187),K53:K187,0), ) | M53: OK | N53: IW | O53: Bill | P53: 46064 | Q53: OK | R53: IW | S53: Bill | T53: 2/12
A54: =ROW()-2 -> 52 | C54: 実機 | D54: 特典内容が右記の通り表示されているか | F54: 實體機台 | G54: 特典內容是否按右側設定 | H54: ='参照_仕様'!C20 -> Mystic Matrimony After Story ～Kicho～ | I54: Bonus!J5:L | J54: 6323 | K54: 2 | L54: =IF(ISTEXT(I54:I188), VLOOKUP(J54:J188,INDIRECT(I54:I188),K54:K188,0), ) -> Mystic Matrimony After Story ～Kicho～ | M54: OK | N54: IW | O54: Bill | P54: 46062
A55: =ROW()-2 -> 53 | D55: 訴求バナー画像が表示されているか | G55: 是否顯示宣傳橫幅圖片 | L55: =IF(ISTEXT(I55:I189), VLOOKUP(J55:J189,INDIRECT(I55:I189),K55:K189,0), ) | M55: OK | N55: IW | O55: Bill | P55: 46064 | Q55: OK | R55: IW | S55: Bill | T55: 2/12
A56: =ROW()-2 -> 54 | D56: サムネイル画像が表示されているか | G56: 是否正常顯示縮圖 | L56: =IF(ISTEXT(I56:I190), VLOOKUP(J56:J190,INDIRECT(I56:I190),K56:K190,0), ) | M56: OK | N56: IW | O56: Bill | P56: 46064 | Q56: OK | R56: IW | S56: Bill | T56: 2/12
A57: =ROW()-2 -> 55 | C57: 実機 | D57: 特典内容が右記の通り表示されているか | F57: 實體機台 | G57: 特典內容是否按右側設定 | H57: ='参照_仕様'!C21 -> Mystic Matrimony After Story ～Motonari～ | I57: Bonus!J5:L | J57: 6324 | K57: 2 | L57: =IF(ISTEXT(I57:I191), VLOOKUP(J57:J191,INDIRECT(I57:I191),K57:K191,0), ) -> Mystic Matrimony After Story ～Motonari～ | M57: OK | N57: IW | O57: Bill | P57: 46062
A58: =ROW()-2 -> 56 | D58: 訴求バナー画像が表示されているか | G58: 是否顯示宣傳橫幅圖片 | L58: =IF(ISTEXT(I58:I192), VLOOKUP(J58:J192,INDIRECT(I58:I192),K58:K192,0), ) | M58: OK | N58: IW | O58: Bill | P58: 46064 | Q58: OK | R58: IW | S58: Bill | T58: 2/12
A59: =ROW()-2 -> 57 | D59: サムネイル画像が表示されているか | G59: 是否正常顯示縮圖 | L59: =IF(ISTEXT(I59:I193), VLOOKUP(J59:J193,INDIRECT(I59:I193),K59:K193,0), ) | M59: OK | N59: IW | O59: Bill | P59: 46064 | Q59: OK | R59: IW | S59: Bill | T59: 2/12
A60: =ROW()-2 -> 58 | C60: 実機 | D60: 特典内容が右記の通り表示されているか | F60: 實體機台 | G60: 特典內容是否按右側設定 | H60: ='参照_仕様'!C22 -> Mystic Matrimony After Story ～Yoshimoto～ | I60: Bonus!J5:L | J60: 6325 | K60: 2 | L60: =IF(ISTEXT(I60:I194), VLOOKUP(J60:J194,INDIRECT(I60:I194),K60:K194,0), ) -> Mystic Matrimony After Story ～Yoshimoto～ | M60: OK | N60: IW | O60: Bill | P60: 46062
A61: =ROW()-2 -> 59 | D61: 訴求バナー画像が表示されているか | G61: 是否顯示宣傳橫幅圖片 | L61: =IF(ISTEXT(I61:I195), VLOOKUP(J61:J195,INDIRECT(I61:I195),K61:K195,0), ) | M61: OK | N61: IW | O61: Bill | P61: 46064 | Q61: OK | R61: IW | S61: Bill | T61: 2/12
A62: =ROW()-2 -> 60 | D62: サムネイル画像が表示されているか | G62: 是否正常顯示縮圖 | L62: =IF(ISTEXT(I62:I196), VLOOKUP(J62:J196,INDIRECT(I62:I196),K62:K196,0), ) | M62: OK | N62: IW | O62: Bill | P62: 46064 | Q62: OK | R62: IW | S62: Bill | T62: 2/12
A63: =ROW()-2 -> 61 | C63: 実機 | D63: 特典内容が右記の通り表示されているか | F63: 實體機台 | G63: 特典內容是否按右側設定 | H63: ='参照_仕様'!C29 -> Demon of My Dreams | I63: Bonus!J5:L | J63: 6313 | K63: 2 | L63: =IF(ISTEXT(I63:I197), VLOOKUP(J63:J197,INDIRECT(I63:I197),K63:K197,0), ) -> Demon of My Dreams | M63: OK | N63: IW | O63: Bill | P63: 46064 | V63: 2026/2/9 驗證單配置資料與後台不符，僅存在單一類似項目且無名稱備註
A64: =ROW()-2 -> 62 | D64: 訴求バナー画像が表示されているか | G64: 是否顯示宣傳橫幅圖片 | M64: OK | N64: IW | O64: Bill | P64: 46064
A65: =ROW()-2 -> 63 | D65: サムネイル画像が表示されているか | G65: 是否正常顯示縮圖 | M65: OK | N65: IW | O65: Bill | P65: 46064
A66: =ROW()-2 -> 64 | B66: ='参照_各種特典'!C78&" "&'参照_各種特典'!D78 -> 本編・続編連動特典 Extra Bonus | C66: プレゼント登録 | D66: 特典内容が右記の通り設定されているか | E66: ='参照_各種特典'!C78&" "&'参照_各種特典'!D78 -> 本編・続編連動特典 Extra Bonus | F66: 禮物登錄 | G66: 特典內容是否按右側設定 | H66: ='参照_各種特典'!$F$78 -> Nine-Tailed Fox Yoshimoto | I66: Bonus!C5:L | J66: 171919 | K66: 4 | L66: =IF(ISTEXT(I66:I137), VLOOKUP(J66:J137,INDIRECT(I66:I137),K66:K137,0), ) -> Nine-Tailed Fox Yoshimoto | M66: OK | N66: IW | O66: Bill | P66: 46062
A67: =ROW()-2 -> 65 | D67: 個数が右記の通り設定されているか | G67: 個數是否按右側設定 | H67: ='参照_各種特典'!$H$78 -> 1 | I67: Bonus!A5:L | J67: ce_203_bonus_group_025 | K67: 7 | L67: =IF(ISTEXT(I67:I138), VLOOKUP(J67:J138,INDIRECT(I67:I138),K67:K138,0), ) -> 1 | M67: OK | N67: IW | O67: Bill | P67: 46062
A68: =ROW()-2 -> 66 | C68: コレクションイベント＞該当イベント＞本編連動 | D68: 取得開始日時が右記の通り設定されているか | F68: 收集活動＞該活動＞本篇連動 | G68: 取得開始日期時間是否按右側設定 | H68: ='参照_各種特典'!$I$78 -> 46074.708 | I68: ExtraBounus!A5:AA | J68: 249 | K68: 16 | L68: =IF(ISTEXT(I68:I139), VLOOKUP(J68:J139,INDIRECT(I68:I139),K68:K139,0), ) -> 46074.708 | M68: OK | N68: IW | O68: Bill | P68: 46064 | V68: 2026/2/9 驗證單配置資料與後台不符，後台無日期設定
A69: =ROW()-2 -> 67 | D69: 取得終了日時が右記の通り設定されているか | G69: 取得結束日期時間是否按右側設定 | H69: ='参照_各種特典'!$J$78 -> 46080.708 | I69: ExtraBounus!A5:AA | J69: 249 | K69: 17 | L69: =IF(ISTEXT(I69:I140), VLOOKUP(J69:J140,INDIRECT(I69:I140),K69:K140,0), ) -> 46080.708 | M69: OK | N69: IW | O69: Bill | P69: 46064 | V69: 2026/2/9 驗證單配置資料與後台不符，後台無日期設定
A70: =ROW()-2 -> 68 | D70: キャラが右記の通り設定されているか | G70: 角色是否按右側設定 | H70: ='参照_各種特典'!$L$78 -> Yoshimoto | I70: ExtraBounus!A5:AA | J70: 249 | K70: 9 | L70: =IF(ISTEXT(I70:I141), VLOOKUP(J70:J141,INDIRECT(I70:I141),K70:K141,0), ) -> Yoshimoto | M70: OK | N70: IW | O70: Bill | P70: 46062
A71: =ROW()-2 -> 69 | D71: 取得条件の話数 / チケット数が右記の通り設定されているか | G71: 取得條件的故事集數 / 票券數是否按右側設定 | H71: ='参照_各種特典'!$G$78 -> Chapter 13 (10/10) Main Route | I71: ExtraBounus!A5:AA | J71: 249 | K71: 4 | L71: {=IF(ISTEXT(I71), "Chapter "& VLOOKUP(J71,INDIRECT(I71),K71,0)& " ("& VLOOKUP(J71,INDIRECT(I71),K71+1,0)& "/10) Main Route" ,)} -> Chapter 13 (10/10) Main Route | M71: OK | N71: IW | O71: Bill | P71: 46062
A72: =ROW()-2 -> 70 | D72: 取得条件のコレクトアイテム使用数が右記の通り設定されているか | G72: 取得條件的收集特典使用數量是否按右側設定 | H72: ='参照_各種特典'!$K$78 -> 500 | I72: ExtraBounus!A5:AA | J72: 249 | K72: 7 | L72: =IF(ISTEXT(I72:I137), VLOOKUP(J72:J137,INDIRECT(I72:I137),K72:K137,0), ) -> 500 | M72: OK | N72: IW | O72: Bill | P72: 46062
A73: =ROW()-2 -> 71 | C73: 実機 | D73: 特典一覧にてモーダル内の特典内容が右記の通り表示されているか | F73: 實體機台 | G73: 特典一覽中的彈窗內特典內容是否按右側顯示 | H73: ='参照_各種特典'!$M$78&" "&'参照_各種特典'!$F$78 -> Until 02/27 17:00(顯示的時間會因地區而異) ・Finish reading Chapter 13 of Yoshimoto's Main Route ・Use 500 Hearts Nine-Tailed Fox Yoshimoto | L73: =IF(ISTEXT(I73:I138), VLOOKUP(J73:J138,INDIRECT(I73:I138),K73:K138,0), ) | M73: OK | N73: IW | O73: Bill | P73: 46064
A74: =ROW()-2 -> 72 | D74: サムネイル画像が表示されているか | G74: 是否顯示縮圖/預覽圖 | M74: OK | N74: IW | O74: Bill | P74: 46064 | Q74: OK | R74: IW | S74: Bill | T74: 2/12
A75: =ROW()-2 -> 73 | B75: ='参照_各種特典'!C79&" "&'参照_各種特典'!D79 -> 本編・続編連動特典 Extra Bonus | C75: プレゼント登録 | D75: 特典内容が右記の通り設定されているか | E75: ='参照_各種特典'!C79&" "&'参照_各種特典'!D79 -> 本編・続編連動特典 Extra Bonus | F75: 禮物登錄 | G75: 特典內容是否按右側設定 | H75: ='参照_各種特典'!$F$79 -> Nine-Tailed Fox Motonari | I75: Bonus!C5:L | J75: 171920 | K75: 4 | L75: =IF(ISTEXT(I75:I137), VLOOKUP(J75:J137,INDIRECT(I75:I137),K75:K137,0), ) -> Nine-Tailed Fox Motonari | M75: OK | N75: IW | O75: Bill | P75: 46062
A76: =ROW()-2 -> 74 | D76: 個数が右記の通り設定されているか | G76: 個數是否按右側設定 | H76: ='参照_各種特典'!$H$79 -> 1 | I76: Bonus!A5:L | J76: ce_203_bonus_group_025 | K76: 7 | L76: =IF(ISTEXT(I76:I138), VLOOKUP(J76:J138,INDIRECT(I76:I138),K76:K138,0), ) -> 1 | M76: OK | N76: IW | O76: Bill | P76: 46062
A77: =ROW()-2 -> 75 | C77: コレクションイベント＞該当イベント＞本編連動 | D77: 取得開始日時が右記の通り設定されているか | F77: 收集活動＞該活動＞本篇連動 | G77: 取得開始日期時間是否按右側設定 | H77: ='参照_各種特典'!$I$79 -> 46074.708 | I77: ExtraBounus!A5:AA | J77: 250 | K77: 16 | L77: =IF(ISTEXT(I77:I139), VLOOKUP(J77:J139,INDIRECT(I77:I139),K77:K139,0), ) -> 46074.708 | M77: OK | N77: IW | O77: Bill | P77: 46064 | V77: 2026/2/9 驗證單配置資料與後台不符，後台無日期設定
A78: =ROW()-2 -> 76 | D78: 取得終了日時が右記の通り設定されているか | G78: 取得結束日期時間是否按右側設定 | H78: ='参照_各種特典'!$J$79 -> 46080.708 | I78: ExtraBounus!A5:AA | J78: 250 | K78: 17 | L78: =IF(ISTEXT(I78:I140), VLOOKUP(J78:J140,INDIRECT(I78:I140),K78:K140,0), ) -> 46080.708 | M78: OK | N78: IW | O78: Bill | P78: 46064 | V78: 2026/2/9 驗證單配置資料與後台不符，後台無日期設定
A79: =ROW()-2 -> 77 | D79: キャラが右記の通り設定されているか | G79: 角色是否按右側設定 | H79: ='参照_各種特典'!$L$79 -> Motonari | I79: ExtraBounus!A5:AA | J79: 250 | K79: 9 | L79: =IF(ISTEXT(I79:I141), VLOOKUP(J79:J141,INDIRECT(I79:I141),K79:K141,0), ) -> Motonari | M79: OK | N79: IW | O79: Bill | P79: 46065
A80: =ROW()-2 -> 78 | D80: 取得条件の話数 / チケット数が右記の通り設定されているか | G80: 取得條件的故事集數 / 票券數是否按右側設定 | H80: ='参照_各種特典'!$G$79 -> Chapter 13 (10/10) Main Route | I80: ExtraBounus!A5:AA | J80: 250 | K80: 4 | L80: {=IF(ISTEXT(I80), "Chapter "& VLOOKUP(J80,INDIRECT(I80),K80,0)& " ("& VLOOKUP(J80,INDIRECT(I80),K80+1,0)& "/10) Main Route" ,)} -> Chapter 13 (10/10) Main Route | M80: OK | N80: IW | O80: Bill | P80: 46065
A81: =ROW()-2 -> 79 | D81: 取得条件のコレクトアイテム使用数が右記の通り設定されているか | G81: 取得條件的收集特典使用數量是否按右側設定 | H81: ='参照_各種特典'!$K$79 -> 500 | I81: ExtraBounus!A5:AA | J81: 250 | K81: 7 | L81: {=IF(ISTEXT(I81:I137), VLOOKUP(J81:J137,INDIRECT(I81:I137),K81:K137,0), )} -> 500 | M81: OK | N81: IW | O81: Bill | P81: 46065
A82: =ROW()-2 -> 80 | C82: 実機 | D82: 特典一覧にてモーダル内の特典内容が右記の通り表示されているか | F82: 實體機台 | G82: 特典一覽中的彈窗內特典內容是否按右側顯示 | H82: ='参照_各種特典'!$M$79&" "&'参照_各種特典'!$F$79 -> Until 02/27 17:00(顯示的時間會因地區而異) ・Finish reading Chapter 13 of Motonari's Main Route ・Use 500 Hearts Nine-Tailed Fox Motonari | M82: OK | N82: IW | O82: Bill | P82: 46064
A83: =ROW()-2 -> 81 | D83: サムネイル画像が表示されているか | G83: 是否顯示縮圖/預覽圖 | M83: OK | N83: IW | O83: Bill | P83: 46064 | Q83: OK | R83: IW | S83: Bill | T83: 2/12
A84: =ROW()-2 -> 82 | C84: プレゼント登録 | D84: 特典内容が右記の通り設定されているか | E84: ='参照_各種特典'!C80&" "&'参照_各種特典'!D80 -> 本編・続編連動特典 Extra Bonus | F84: 禮物登錄 | G84: 特典內容是否按右側設定 | H84: ='参照_各種特典'!$F$80 -> Nine-Tailed Fox Kanetsugu | I84: Bonus!C5:L | J84: 171921 | K84: 4 | L84: =IF(ISTEXT(I84:I137), VLOOKUP(J84:J137,INDIRECT(I84:I137),K84:K137,0), ) -> Nine-Tailed Fox Kanetsugu | M84: OK | N84: IW | O84: Bill | P84: 46065
A85: =ROW()-2 -> 83 | D85: 個数が右記の通り設定されているか | G85: 個數是否按右側設定 | H85: ='参照_各種特典'!$H$80 -> 1 | I85: Bonus!A5:L | J85: ce_203_bonus_group_025 | K85: 7 | L85: =IF(ISTEXT(I85:I138), VLOOKUP(J85:J138,INDIRECT(I85:I138),K85:K138,0), ) -> 1 | M85: OK | N85: IW | O85: Bill | P85: 46065
A86: =ROW()-2 -> 84 | C86: コレクションイベント＞該当イベント＞本編連動 | D86: 取得開始日時が右記の通り設定されているか | F86: 收集活動＞該活動＞本篇連動 | G86: 取得開始日期時間是否按右側設定 | H86: ='参照_各種特典'!$I$80 -> 46074.708 | I86: ExtraBounus!A5:AA | J86: 251 | K86: 16 | L86: =IF(ISTEXT(I86:I139), VLOOKUP(J86:J139,INDIRECT(I86:I139),K86:K139,0), ) -> 46074.708 | M86: OK | N86: IW | O86: Bill | P86: 46065
A87: =ROW()-2 -> 85 | D87: 取得終了日時が右記の通り設定されているか | G87: 取得結束日期時間是否按右側設定 | H87: ='参照_各種特典'!$J$80 -> 46080.708 | I87: ExtraBounus!A5:AA | J87: 251 | K87: 17 | L87: =IF(ISTEXT(I87:I140), VLOOKUP(J87:J140,INDIRECT(I87:I140),K87:K140,0), ) -> 46080.708 | M87: OK | N87: IW | O87: Bill | P87: 46065
A88: =ROW()-2 -> 86 | D88: キャラが右記の通り設定されているか | G88: 角色是否按右側設定 | H88: ='参照_各種特典'!$L$80 -> Kanetsugu | I88: ExtraBounus!A5:AA | J88: 251 | K88: 9 | L88: =IF(ISTEXT(I88:I141), VLOOKUP(J88:J141,INDIRECT(I88:I141),K88:K141,0), ) -> Kanetsugu | M88: OK | N88: IW | O88: Bill | P88: 46065
A89: =ROW()-2 -> 87 | D89: 取得条件の話数 / チケット数が右記の通り設定されているか | G89: 取得條件的故事集數 / 票券數是否按右側設定 | H89: ='参照_各種特典'!$G$80 -> Chapter 13 (10/10) Main Route | I89: ExtraBounus!A5:AA | J89: 251 | K89: 4 | L89: {=IF(ISTEXT(I89), "Chapter "& VLOOKUP(J89,INDIRECT(I89),K89,0)& " ("& VLOOKUP(J89,INDIRECT(I89),K89+1,0)& "/10) Main Route" ,)} -> Chapter 13 (10/10) Main Route | M89: OK | N89: IW | O89: Bill | P89: 46065
A90: =ROW()-2 -> 88 | D90: 取得条件のコレクトアイテム使用数が右記の通り設定されているか | G90: 取得條件的收集特典使用數量是否按右側設定 | H90: ='参照_各種特典'!$K$80 -> 500 | I90: ExtraBounus!A5:AA | J90: 251 | K90: 7 | L90: {=IF(ISTEXT(I90:I137), VLOOKUP(J90:J137,INDIRECT(I90:I137),K90:K137,0), )} -> 500 | M90: OK | N90: IW | O90: Bill | P90: 46065
A91: =ROW()-2 -> 89 | C91: 実機 | D91: 特典一覧にてモーダル内の特典内容が右記の通り表示されているか | F91: 實體機台 | G91: 特典一覽中的彈窗內特典內容是否按右側顯示 | H91: ='参照_各種特典'!$M$80&" "&'参照_各種特典'!$F$80 -> Until 02/27 17:00(顯示的時間會因地區而異) ・Finish reading Chapter 13 of Kanetsugu's Main Route ・Use 500 Hearts Nine-Tailed Fox Kanetsugu | M91: OK | N91: IW | O91: Bill | P91: 46065
A92: =ROW()-2 -> 90 | D92: サムネイル画像が表示されているか | G92: 是否顯示縮圖/預覽圖 | M92: OK | N92: IW | O92: Bill | P92: 46065 | Q92: OK | R92: IW | S92: Bill | T92: 2/12
A93: =ROW()-2 -> 91 | C93: プレゼント登録 | D93: 特典内容が右記の通り設定されているか | E93: ='参照_各種特典'!C81&" "&'参照_各種特典'!D81 -> 本編・続編連動特典 Extra Bonus | F93: 禮物登錄 | G93: 特典內容是否按右側設定 | H93: ='参照_各種特典'!$F$81 -> Nine-Tailed Fox Kicho | I93: Bonus!C5:L | J93: 171922 | K93: 4 | L93: =IF(ISTEXT(I93:I137), VLOOKUP(J93:J137,INDIRECT(I93:I137),K93:K137,0), ) -> Nine-Tailed Fox Kicho | M93: OK | N93: IW | O93: Bill | P93: 46065
A94: =ROW()-2 -> 92 | D94: 個数が右記の通り設定されているか | G94: 個數是否按右側設定 | H94: ='参照_各種特典'!$H$81 -> 1 | I94: Bonus!A5:L | J94: ce_203_bonus_group_025 | K94: 7 | L94: =IF(ISTEXT(I94:I138), VLOOKUP(J94:J138,INDIRECT(I94:I138),K94:K138,0), ) -> 1 | M94: OK | N94: IW | O94: Bill | P94: 46065
A95: =ROW()-2 -> 93 | C95: コレクションイベント＞該当イベント＞本編連動 | D95: 取得開始日時が右記の通り設定されているか | F95: 收集活動＞該活動＞本篇連動 | G95: 取得開始日期時間是否按右側設定 | H95: ='参照_各種特典'!$I$81 -> 46074.708 | I95: ExtraBounus!A5:AA | J95: 252 | K95: 16 | L95: =IF(ISTEXT(I95:I139), VLOOKUP(J95:J139,INDIRECT(I95:I139),K95:K139,0), ) -> 46074.708 | M95: OK | N95: IW | O95: Bill | P95: 46065
A96: =ROW()-2 -> 94 | D96: 取得終了日時が右記の通り設定されているか | G96: 取得結束日期時間是否按右側設定 | H96: ='参照_各種特典'!$J$81 -> 46080.708 | I96: ExtraBounus!A5:AA | J96: 252 | K96: 17 | L96: =IF(ISTEXT(I96:I140), VLOOKUP(J96:J140,INDIRECT(I96:I140),K96:K140,0), ) -> 46080.708 | M96: OK | N96: IW | O96: Bill | P96: 46065
A97: =ROW()-2 -> 95 | D97: キャラが右記の通り設定されているか | G97: 角色是否按右側設定 | H97: ='参照_各種特典'!$L$81 -> Kicho | I97: ExtraBounus!A5:AA | J97: 252 | K97: 9 | L97: =IF(ISTEXT(I97:I141), VLOOKUP(J97:J141,INDIRECT(I97:I141),K97:K141,0), ) -> Kicho | M97: OK | N97: IW | O97: Bill | P97: 46065
A98: =ROW()-2 -> 96 | D98: 取得条件の話数 / チケット数が右記の通り設定されているか | G98: 取得條件的故事集數 / 票券數是否按右側設定 | H98: ='参照_各種特典'!$G$81 -> Chapter 13 (10/10) Main Route | I98: ExtraBounus!A5:AA | J98: 252 | K98: 4 | L98: {=IF(ISTEXT(I98), "Chapter "& VLOOKUP(J98,INDIRECT(I98),K98,0)& " ("& VLOOKUP(J98,INDIRECT(I98),K98+1,0)& "/10) Main Route" ,)} -> Chapter 13 (10/10) Main Route | M98: OK | N98: IW | O98: Bill | P98: 46065
A99: =ROW()-2 -> 97 | D99: 取得条件のコレクトアイテム使用数が右記の通り設定されているか | G99: 取得條件的收集特典使用數量是否按右側設定 | H99: ='参照_各種特典'!$K$81 -> 500 | I99: ExtraBounus!A5:AA | J99: 252 | K99: 7 | L99: {=IF(ISTEXT(I99:I137), VLOOKUP(J99:J137,INDIRECT(I99:I137),K99:K137,0), )} -> 500 | M99: OK | N99: IW | O99: Bill | P99: 46065
A100: =ROW()-2 -> 98 | C100: 実機 | D100: 特典一覧にてモーダル内の特典内容が右記の通り表示されているか | F100: 實體機台 | G100: 特典一覽中的彈窗內特典內容是否按右側顯示 | H100: ='参照_各種特典'!$M$81&" "&'参照_各種特典'!$F$81 -> Until 02/27 17:00(顯示的時間會因地區而異) ・Finish reading Chapter 13 of Kicho's Main Route ・Use 500 Hearts Nine-Tailed Fox Kicho | M100: OK | N100: IW | O100: Bill | P100: 46065
...

Sheet BonusGroup
B1: https://common-legacy-app-admin.us.ikemen-sengoku.jp/admin/isgame/collection/all_setting/203#Bonus%20Group
B3: {=SEQUENCE(1,COLUMNS(B:M))} -> 1 | C3: 2 | D3: 3 | E3: 4 | F3: 5 | G3: 6 | H3: 7 | I3: 8 | J3: 9 | K3: 10 | L3: 11 | M3: 12
A4: ID | B4: bonus group cd | C4: collect event cd | D4: bonus group type | E4: group name | F4: description | G4: get bonus start | H4: get bonus end | I4: bonus time limit | J4: collect item get count | K4: order | L4: update | M4: resource generated
A5: 5404 | B5: ce_203_bonus_group_001 | C5: collect_203 | D5: early_gold | E5: Early Clear Bonus Gold | F5: Collect 140 Hearts by 2/22 11:00 PM PST for this! | G5: 46074.708 | H5: 46075.958 | J5: 140 | K5: 1 | L5: 46058.267 | M5: 46058.267
A6: 5405 | B6: ce_203_bonus_group_002 | C6: collect_203 | D6: early_silver | E6: Early Clear Bonus Silver | F6: Collect 240 Hearts by 2/23 11:00 PM PST for this! | G6: 46074.708 | H6: 46076.958 | J6: 240 | K6: 2 | L6: 46058.267 | M6: 46058.267
A7: 5406 | B7: ce_203_bonus_group_003 | C7: collect_203 | D7: early_copper | E7: Early Clear Bonus Mystic Matrimony | F7: Collect 400 Hearts by 2/24 11:00 PM PST for this! | G7: 46074.708 | H7: 46077.958 | J7: 400 | K7: 3 | L7: 46058.267 | M7: 46058.267
A8: 5407 | B8: ce_203_bonus_group_004 | C8: collect_203 | D8: early_all_collection | E8: Early Clear Bonus Platinum | F8: Collect 560 Hearts by 2/25 11:00 PM PST for this! | G8: 46074.708 | H8: 46078.958 | J8: 560 | K8: 4 | L8: 46058.267 | M8: 46058.267
A9: 5408 | B9: ce_203_bonus_group_005 | C9: collect_203 | D9: story | E9: Bonus Stories | F9: Collect Hearts to get Bonus Stories! | G9: 0 | H9: 0 | J9: 0 | K9: 5 | L9: 46058.267 | M9: 46058.267
A10: 5409 | B10: ce_203_bonus_group_007 | C10: collect_203 | D10: collection | E10: Collection Bonuses | F10: Collect Hearts & get great Attire & Avatars! | G10: 0 | H10: 0 | J10: 0 | K10: 7 | L10: 46058.267 | M10: 46058.267
A11: 5411 | B11: ce_203_bonus_group_009 | C11: collect_203 | D11: special_collection | E11: Special Collection Bonus | F11: Collect Hearts to get Bonus! | G11: 0 | H11: 0 | J11: 600 | K11: 9 | L11: 46058.267 | M11: 46058.267
A12: 5413 | B12: ce_203_bonus_group_011 | C12: collect_203 | D12: special_collection | E12: Special Collection Bonus | F12: Collect Hearts to get Bonus! | G12: 0 | H12: 0 | J12: 650 | K12: 12 | L12: 46058.267 | M12: 46058.267
A13: 5415 | B13: ce_203_bonus_group_013 | C13: collect_203 | D13: special_collection | E13: Special Collection Bonus | F13: Collect Hearts to get Bonus! | G13: 0 | H13: 0 | J13: 700 | K13: 14 | L13: 46058.267 | M13: 46058.267
A14: 5417 | B14: ce_203_bonus_group_015 | C14: collect_203 | D14: special_collection | E14: Special Collection Bonus | F14: Collect Hearts to get Bonus! | G14: 0 | H14: 0 | J14: 750 | K14: 17 | L14: 46058.267 | M14: 46058.267
A15: 5419 | B15: ce_203_bonus_group_017 | C15: collect_203 | D15: special_collection | E15: Special Collection Bonus | F15: Collect Hearts to get Bonus! | G15: 0 | H15: 0 | J15: 800 | K15: 19 | L15: 46058.267 | M15: 46058.267
A16: 5421 | B16: ce_203_bonus_group_019 | C16: collect_203 | D16: special_collection | E16: Special Collection Bonus | F16: Collect Hearts to get Bonus! | G16: 0 | H16: 0 | J16: 850 | K16: 23 | L16: 46058.267 | M16: 46058.267
... A19: 5426 | B19: ce_203_bonus_group_024 | C19: collect_203 | D19: last_ranking | E19: Final Ranking Bonuses | F19: Rank in for these! | G19: 0 | H19: 0 | J19: 0 | K19: 34 | L19: 46058.267 | M19: 46058.267
A20: 5427 | B20: ce_203_bonus_group_025 | C20: collect_203 | D20: linked | E20: Extra Bonus | G20: 0 | H20: 0 | J20: 500 | K20: 35 | L20: 46058.267 | M20: 46058.267

Sheet Bonus
A1: https://common-legacy-app-admin.us.ikemen-sengoku.jp/admin/isgame/collection/all_setting/203#Bonus
J2: {=SEQUENCE(1,COLUMNS(J:M))} -> 1 | K2: 2 | L2: 3 | M2: 4 | S2: {=SEQUENCE(1,COLUMNS(S:V))} -> 1 | T2: 2 | U2: 3 | V2: 4
A3: {=SEQUENCE(1,COLUMNS(A:V))} -> 1 | B3: 2 | C3: 3 | D3: 4 | E3: 5 | F3: 6 | G3: 7 | H3: 8 | I3: 9 | J3: 10 | K3: 11 | L3: 12 | M3: 13 | N3: 14 | O3: 15 | P3: 16 | Q3: 17 | R3: 18 | S3: 19 | T3: 20 | U3: 21 | V3: 22
A4: bonus group cd | B4: present | C4: present ID | D4: present Name / present descirption | E4: present Item with Count | F4: present Item | G4: present item count | H4: present description | I4: special story | J4: story ID | K4: story Name | L4: voice | M4: still | N4: order | O4: touch chara id | P4: vote group id | Q4: update | R4: All Bonus Combine Info
A5: ce_203_bonus_group_001 | B5: 171901▸Mystic Matrimony Early Clear Bonus Gold 〈Blue Anemone Hair Clip x 1〉 | C5: =IFERROR(__xludf.DUMMYFUNCTION("ARRAYFORMULA(IF(ISTEXT(B5:B47),SPLIT(B5:B47,""▸〈〉""),))"),171901.0) -> 171901 | D5: =IFERROR(__xludf.DUMMYFUNCTION("""COMPUTED_VALUE"""),"Mystic Matrimony Early Clear Bonus Gold ") -> Mystic Matrimony Early Clear Bonus Gold | E5: =IFERROR(__xludf.DUMMYFUNCTION("""COMPUTED_VALUE"""),"Blue Anemone Hair Clip x 1") -> Blue Anemone Hair Clip x 1 | F5: {=if(ISTEXT(E5:E47), LEFT(E5:E47,LEN(E5:E47)-4), )} -> Blue Anemone Hair Clip | G5: 1 | H5: Mystic Matrimony Early Clear Bonus Gold | J5: =IFERROR(__xludf.DUMMYFUNCTION("ARRAYFORMULA(IF(ISTEXT(I5:I47),SPLIT(I5:I47,""▸""),))"),"") | N5: 1 | Q5: 46058.272 | R5: {=LET( _present, B5:B47, _special_story, I5:I47, _voice, L5:L47, _still, M5:M47, IFS( LEN(_present),_present, LEN(_special_story),_special_story, LEN(_voice),_voice, LEN(_still),_still) )} -> 171901▸Mystic Matrimony Early Clear Bonus Gold 〈Blue Anemone Hair Clip x 1〉 | S5: =IFERROR(__xludf.DUMMYFUNCTION("ARRAYFORMULA(IF(ISTEXT(R5:R47),SPLIT(R5:R47,""▸〈〉""),))"),171901.0) -> 171901 | T5: =IFERROR(__xludf.DUMMYFUNCTION("""COMPUTED_VALUE"""),"Mystic Matrimony Early Clear Bonus Gold ") -> Mystic Matrimony Early Clear Bonus Gold | U5: =IFERROR(__xludf.DUMMYFUNCTION("""COMPUTED_VALUE"""),"Blue Anemone Hair Clip x 1") -> Blue Anemone Hair Clip x 1 | V5: {=if(ISTEXT(U5:U47), LEFT(U5:U47,LEN(U5:U47)-4), )} -> Blue Anemone Hair Clip
A6: ce_203_bonus_group_002 | B6: 171902▸Mystic Matrimony Early Clear Bonus Silver 〈Shining Silver Ash Hair x 1〉 | C6: =IFERROR(__xludf.DUMMYFUNCTION("""COMPUTED_VALUE"""),171902.0) -> 171902 | D6: =IFERROR(__xludf.DUMMYFUNCTION("""COMPUTED_VALUE"""),"Mystic Matrimony Early Clear Bonus Silver ") -> Mystic Matrimony Early Clear Bonus Silver | E6: =IFERROR(__xludf.DUMMYFUNCTION("""COMPUTED_VALUE"""),"Shining Silver Ash Hair x 1") -> Shining Silver Ash Hair x 1 | F6: Shining Silver Ash Hair | G6: 1 | H6: Mystic Matrimony Early Clear Bonus Silver | N6: 1 | Q6: 46058.272 | R6: 171902▸Mystic Matrimony Early Clear Bonus Silver 〈Shining Silver Ash Hair x 1〉 | S6: =IFERROR(__xludf.DUMMYFUNCTION("""COMPUTED_VALUE"""),171902.0) -> 171902 | T6: =IFERROR(__xludf.DUMMYFUNCTION("""COMPUTED_VALUE"""),"Mystic Matrimony Early Clear Bonus Silver ") -> Mystic Matrimony Early Clear Bonus Silver | U6: =IFERROR(__xludf.DUMMYFUNCTION("""COMPUTED_VALUE"""),"Shining Silver Ash Hair x 1") -> Shining Silver Ash Hair x 1 | V6: Shining Silver Ash Hair
A7: ce_203_bonus_group_003 | B7: 171903▸Mystic Matrimony Early Clear Bonus Mystic Matrimony 〈Effect: Shiny White Spider Lily x 1〉 | C7: =IFERROR(__xludf.DUMMYFUNCTION("""COMPUTED_VALUE"""),171903.0) -> 171903 | D7: =IFERROR(__xludf.DUMMYFUNCTION("""COMPUTED_VALUE"""),"Mystic Matrimony Early Clear Bonus Mystic Matrimony ") -> Mystic Matrimony Early Clear Bonus Mystic Matrimony | E7: =IFERROR(__xludf.DUMMYFUNCTION("""COMPUTED_VALUE"""),"Effect: Shiny White Spider Lily x 1") -> Effect: Shiny White Spider Lily x 1 | F7: Effect: Shiny White Spider Lily | G7: 1 | H7: Mystic Matrimony Early Clear Bonus Mystic Matrimony | N7: 1 | Q7: 46058.272 | R7: 171903▸Mystic Matrimony Early Clear Bonus Mystic Matrimony 〈Effect: Shiny White Spider Lily x 1〉 | S7: =IFERROR(__xludf.DUMMYFUNCTION("""COMPUTED_VALUE"""),171903.0) -> 171903 | T7: =IFERROR(__xludf.DUMMYFUNCTION("""COMPUTED_VALUE"""),"Mystic Matrimony Early Clear Bonus Mystic Matrimony ") -> Mystic Matrimony Early Clear Bonus Mystic Matrimony | U7: =IFERROR(__xludf.DUMMYFUNCTION("""COMPUTED_VALUE"""),"Effect: Shiny White Spider Lily x 1") -> Effect: Shiny White Spider Lily x 1 | V7: Effect: Shiny White Spider Lily
A8: ce_203_bonus_group_004 | B8: 171904▸Mystic Matrimony Early Clear Bonus Platinum 〈The Forest Where Spirits Dwell x 1〉 | C8: =IFERROR(__xludf.DUMMYFUNCTION("""COMPUTED_VALUE"""),171904.0) -> 171904 | D8: =IFERROR(__xludf.DUMMYFUNCTION("""COMPUTED_VALUE"""),"Mystic Matrimony Early Clear Bonus Platinum ") -> Mystic Matrimony Early Clear Bonus Platinum | E8: =IFERROR(__xludf.DUMMYFUNCTION("""COMPUTED_VALUE"""),"The Forest Where Spirits Dwell x 1") -> The Forest Where Spirits Dwell x 1 | F8: The Forest Where Spirits Dwell | G8: 1 | H8: Mystic Matrimony Early Clear Bonus Platinum | N8: 1 | Q8: 46058.272 | R8: 171904▸Mystic Matrimony Early Clear Bonus Platinum 〈The Forest Where Spirits Dwell x 1〉 | S8: =IFERROR(__xludf.DUMMYFUNCTION("""COMPUTED_VALUE"""),171904.0) -> 171904 | T8: =IFERROR(__xludf.DUMMYFUNCTION("""COMPUTED_VALUE"""),"Mystic Matrimony Early Clear Bonus Platinum ") -> Mystic Matrimony Early Clear Bonus Platinum | U8: =IFERROR(__xludf.DUMMYFUNCTION("""COMPUTED_VALUE"""),"The Forest Where Spirits Dwell x 1") -> The Forest Where Spirits Dwell x 1 | V8: The Forest Where Spirits Dwell
A9: ce_203_bonus_group_005 | I9: 6313▸Demon of My Dreams | J9: =IFERROR(__xludf.DUMMYFUNCTION("""COMPUTED_VALUE"""),6313.0) -> 6313 | K9: =IFERROR(__xludf.DUMMYFUNCTION("""COMPUTED_VALUE"""),"Demon of My Dreams") -> Demon of My Dreams | N9: 1 | Q9: 46058.272 | R9: 6313▸Demon of My Dreams | S9: =IFERROR(__xludf.DUMMYFUNCTION("""COMPUTED_VALUE"""),6313.0) -> 6313 | T9: =IFERROR(__xludf.DUMMYFUNCTION("""COMPUTED_VALUE"""),"Demon of My Dreams") -> Demon of My Dreams
A10: ce_203_bonus_group_005 | I10: 6314▸Mystic Matrimony Bonus Story ～Masamune～ | J10: =IFERROR(__xludf.DUMMYFUNCTION("""COMPUTED_VALUE"""),6314.0) -> 6314 | K10: =IFERROR(__xludf.DUMMYFUNCTION("""COMPUTED_VALUE"""),"Mystic Matrimony Bonus Story ～Masamune～") -> Mystic Matrimony Bonus Story ～Masamune～ | N10: 1 | Q10: 46058.272 | R10: 6314▸Mystic Matrimony Bonus Story ～Masamune～ | S10: =IFERROR(__xludf.DUMMYFUNCTION("""COMPUTED_VALUE"""),6314.0) -> 6314 | T10: =IFERROR(__xludf.DUMMYFUNCTION("""COMPUTED_VALUE"""),"Mystic Matrimony Bonus Story ～Masamune～") -> Mystic Matrimony Bonus Story ～Masamune～
A11: ce_203_bonus_group_005 | I11: 6315▸Mystic Matrimony Bonus Story ～Nobunaga～ | J11: =IFERROR(__xludf.DUMMYFUNCTION("""COMPUTED_VALUE"""),6315.0) -> 6315 | K11: =IFERROR(__xludf.DUMMYFUNCTION("""COMPUTED_VALUE"""),"Mystic Matrimony Bonus Story ～Nobunaga～") -> Mystic Matrimony Bonus Story ～Nobunaga～ | N11: 1 | Q11: 46058.272 | R11: 6315▸Mystic Matrimony Bonus Story ～Nobunaga～ | S11: =IFERROR(__xludf.DUMMYFUNCTION("""COMPUTED_VALUE"""),6315.0) -> 6315 | T11: =IFERROR(__xludf.DUMMYFUNCTION("""COMPUTED_VALUE"""),"Mystic Matrimony Bonus Story ～Nobunaga～") -> Mystic Matrimony Bonus Story ～Nobunaga～
A12: ce_203_bonus_group_005 | I12: 6316▸Mystic Matrimony Bonus Story ～Kanetsugu～ | J12: =IFERROR(__xludf.DUMMYFUNCTION("""COMPUTED_VALUE"""),6316.0) -> 6316 | K12: =IFERROR(__xludf.DUMMYFUNCTION("""COMPUTED_VALUE"""),"Mystic Matrimony Bonus Story ～Kanetsugu～") -> Mystic Matrimony Bonus Story ～Kanetsugu～ | N12: 1 | Q12: 46058.272 | R12: 6316▸Mystic Matrimony Bonus Story ～Kanetsugu～ | S12: =IFERROR(__xludf.DUMMYFUNCTION("""COMPUTED_VALUE"""),6316.0) -> 6316 | T12: =IFERROR(__xludf.DUMMYFUNCTION("""COMPUTED_VALUE"""),"Mystic Matrimony Bonus Story ～Kanetsugu～") -> Mystic Matrimony Bonus Story ～Kanetsugu～
A13: ce_203_bonus_group_005 | I13: 6317▸Mystic Matrimony Bonus Story ～Kicho～ | J13: =IFERROR(__xludf.DUMMYFUNCTION("""COMPUTED_VALUE"""),6317.0) -> 6317 | K13: =IFERROR(__xludf.DUMMYFUNCTION("""COMPUTED_VALUE"""),"Mystic Matrimony Bonus Story ～Kicho～") -> Mystic Matrimony Bonus Story ～Kicho～ | N13: 1 | Q13: 46058.272 | R13: 6317▸Mystic Matrimony Bonus Story ～Kicho～ | S13: =IFERROR(__xludf.DUMMYFUNCTION("""COMPUTED_VALUE"""),6317.0) -> 6317 | T13: =IFERROR(__xludf.DUMMYFUNCTION("""COMPUTED_VALUE"""),"Mystic Matrimony Bonus Story ～Kicho～") -> Mystic Matrimony Bonus Story ～Kicho～
A14: ce_203_bonus_group_005 | I14: 6318▸Mystic Matrimony Bonus Story ～Motonari～ | J14: =IFERROR(__xludf.DUMMYFUNCTION("""COMPUTED_VALUE"""),6318.0) -> 6318 | K14: =IFERROR(__xludf.DUMMYFUNCTION("""COMPUTED_VALUE"""),"Mystic Matrimony Bonus Story ～Motonari～") -> Mystic Matrimony Bonus Story ～Motonari～ | N14: 1 | Q14: 46058.272 | R14: 6318▸Mystic Matrimony Bonus Story ～Motonari～ | S14: =IFERROR(__xludf.DUMMYFUNCTION("""COMPUTED_VALUE"""),6318.0) -> 6318 | T14: =IFERROR(__xludf.DUMMYFUNCTION("""COMPUTED_VALUE"""),"Mystic Matrimony Bonus Story ～Motonari～") -> Mystic Matrimony Bonus Story ～Motonari～
A15: ce_203_bonus_group_005 | I15: 6319▸Mystic Matrimony Bonus Story ～Yoshimoto～ | J15: =IFERROR(__xludf.DUMMYFUNCTION("""COMPUTED_VALUE"""),6319.0) -> 6319 | K15: =IFERROR(__xludf.DUMMYFUNCTION("""COMPUTED_VALUE"""),"Mystic Matrimony Bonus Story ～Yoshimoto～") -> Mystic Matrimony Bonus Story ～Yoshimoto～ | N15: 1 | Q15: 46058.272 | R15: 6319▸Mystic Matrimony Bonus Story ～Yoshimoto～ | S15: =IFERROR(__xludf.DUMMYFUNCTION("""COMPUTED_VALUE"""),6319.0) -> 6319 | T15: =IFERROR(__xludf.DUMMYFUNCTION("""COMPUTED_VALUE"""),"Mystic Matrimony Bonus Story ～Yoshimoto～") -> Mystic Matrimony Bonus Story ～Yoshimoto～
A16: ce_203_bonus_group_007 | M16: 3780▸Mystic Matrimony ~Yoshimoto~ | N16: 1 | Q16: 46058.272 | R16: 3780▸Mystic Matrimony ~Yoshimoto~ | S16: =IFERROR(__xludf.DUMMYFUNCTION("""COMPUTED_VALUE"""),3780.0) -> 3780 | T16: =IFERROR(__xludf.DUMMYFUNCTION("""COMPUTED_VALUE"""),"Mystic Matrimony ~Yoshimoto~") -> Mystic Matrimony ~Yoshimoto~
A17: ce_203_bonus_group_009 | M17: 3779▸Mystic Matrimony ~Motonari~ | N17: 1 | Q17: 46058.272 | R17: 3779▸Mystic Matrimony ~Motonari~ | S17: =IFERROR(__xludf.DUMMYFUNCTION("""COMPUTED_VALUE"""),3779.0) -> 3779 | T17: =IFERROR(__xludf.DUMMYFUNCTION("""COMPUTED_VALUE"""),"Mystic Matrimony ~Motonari~") -> Mystic Matrimony ~Motonari~
A18: ce_203_bonus_group_009 | B18: 171906▸Mystic Matrimony Special Collection Bonus 〈Mystic Matrimony Yoshimoto x 1〉 | C18: =IFERROR(__xludf.DUMMYFUNCTION("""COMPUTED_VALUE"""),171906.0) -> 171906 | D18: =IFERROR(__xludf.DUMMYFUNCTION("""COMPUTED_VALUE"""),"Mystic Matrimony Special Collection Bonus ") -> Mystic Matrimony Special Collection Bonus | E18: =IFERROR(__xludf.DUMMYFUNCTION("""COMPUTED_VALUE"""),"Mystic Matrimony Yoshimoto x 1") -> Mystic Matrimony Yoshimoto x 1 | F18: Mystic Matrimony Yoshimoto | G18: 1 | H18: Mystic Matrimony Special Collection Bonus | N18: 1 | Q18: 46058.272 | R18: 171906▸Mystic Matrimony Special Collection Bonus 〈Mystic Matrimony Yoshimoto x 1〉 | S18: =IFERROR(__xludf.DUMMYFUNCTION("""COMPUTED_VALUE"""),171906.0) -> 171906 | T18: =IFERROR(__xludf.DUMMYFUNCTION("""COMPUTED_VALUE"""),"Mystic Matrimony Special Collection Bonus ") -> Mystic Matrimony Special Collection Bonus | U18: =IFERROR(__xludf.DUMMYFUNCTION("""COMPUTED_VALUE"""),"Mystic Matrimony Yoshimoto x 1") -> Mystic Matrimony Yoshimoto x 1 | V18: Mystic Matrimony Yoshimoto
A19: ce_203_bonus_group_011 | I19: 6325▸Mystic Matrimony After Story ～Yoshimoto～ | J19: =IFERROR(__xludf.DUMMYFUNCTION("""COMPUTED_VALUE"""),6325.0) -> 6325 | K19: =IFERROR(__xludf.DUMMYFUNCTION("""COMPUTED_VALUE"""),"Mystic Matrimony After Story ～Yoshimoto～") -> Mystic Matrimony After Story ～Yoshimoto～ | N19: 1 | Q19: 46058.272 | R19: 6325▸Mystic Matrimony After Story ～Yoshimoto～ | S19: =IFERROR(__xludf.DUMMYFUNCTION("""COMPUTED_VALUE"""),6325.0) -> 6325 | T19: =IFERROR(__xludf.DUMMYFUNCTION("""COMPUTED_VALUE"""),"Mystic Matrimony After Story ～Yoshimoto～") -> Mystic Matrimony After Story ～Yoshimoto～
A20: ce_203_bonus_group_013 | M20: 3778▸Mystic Matrimony ~Kicho~ | N20: 1 | Q20: 46058.272 | R20: 3778▸Mystic Matrimony ~Kicho~ | S20: =IFERROR(__xludf.DUMMYFUNCTION("""COMPUTED_VALUE"""),3778.0) -> 3778 | T20: =IFERROR(__xludf.DUMMYFUNCTION("""COMPUTED_VALUE"""),"Mystic Matrimony ~Kicho~") -> Mystic Matrimony ~Kicho~
A21: ce_203_bonus_group_013 | B21: 171909▸Mystic Matrimony Special Collection Bonus 〈Mystic Matrimony Motonari x 1〉 | C21: =IFERROR(__xludf.DUMMYFUNCTION("""COMPUTED_VALUE"""),171909.0) -> 171909 | D21: =IFERROR(__xludf.DUMMYFUNCTION("""COMPUTED_VALUE"""),"Mystic Matrimony Special Collection Bonus ") -> Mystic Matrimony Special Collection Bonus | E21: =IFERROR(__xludf.DUMMYFUNCTION("""COMPUTED_VALUE"""),"Mystic Matrimony Motonari x 1") -> Mystic Matrimony Motonari x 1 | F21: Mystic Matrimony Motonari | G21: 1 | H21: Mystic Matrimony Special Collection Bonus | N21: 1 | Q21: 46058.272 | R21: 171909▸Mystic Matrimony Special Collection Bonus 〈Mystic Matrimony Motonari x 1〉 | S21: =IFERROR(__xludf.DUMMYFUNCTION("""COMPUTED_VALUE"""),171909.0) -> 171909 | T21: =IFERROR(__xludf.DUMMYFUNCTION("""COMPUTED_VALUE"""),"Mystic Matrimony Special Collection Bonus ") -> Mystic Matrimony Special Collection Bonus | U21: =IFERROR(__xludf.DUMMYFUNCTION("""COMPUTED_VALUE"""),"Mystic Matrimony Motonari x 1") -> Mystic Matrimony Motonari x 1 | V21: Mystic Matrimony Motonari
A22: ce_203_bonus_group_015 | I22: 6324▸Mystic Matrimony After Story ～Motonari～ | J22: =IFERROR(__xludf.DUMMYFUNCTION("""COMPUTED_VALUE"""),6324.0) -> 6324 | K22: =IFERROR(__xludf.DUMMYFUNCTION("""COMPUTED_VALUE"""),"Mystic Matrimony After Story ～Motonari～") -> Mystic Matrimony After Story ～Motonari～ | N22: 1 | Q22: 46058.272 | R22: 6324▸Mystic Matrimony After Story ～Motonari～ | S22: =IFERROR(__xludf.DUMMYFUNCTION("""COMPUTED_VALUE"""),6324.0) -> 6324 | T22: =IFERROR(__xludf.DUMMYFUNCTION("""COMPUTED_VALUE"""),"Mystic Matrimony After Story ～Motonari～") -> Mystic Matrimony After Story ～Motonari～
A23: ce_203_bonus_group_017 | I23: 6323▸Mystic Matrimony After Story ～Kicho～ | J23: =IFERROR(__xludf.DUMMYFUNCTION("""COMPUTED_VALUE"""),6323.0) -> 6323 | K23: =IFERROR(__xludf.DUMMYFUNCTION("""COMPUTED_VALUE"""),"Mystic Matrimony After Story ～Kicho～") -> Mystic Matrimony After Story ～Kicho～ | N23: 1 | Q23: 46058.272 | R23: 6323▸Mystic Matrimony After Story ～Kicho～ | S23: =IFERROR(__xludf.DUMMYFUNCTION("""COMPUTED_VALUE"""),6323.0) -> 6323 | T23: =IFERROR(__xludf.DUMMYFUNCTION("""COMPUTED_VALUE"""),"Mystic Matrimony After Story ～Kicho～") -> Mystic Matrimony After Story ～Kicho～
A24: ce_203_bonus_group_017 | M24: 3777▸Mystic Matrimony ~Kanetsugu~ | N24: 1 | Q24: 46058.272 | R24: 3777▸Mystic Matrimony ~Kanetsugu~ | S24: =IFERROR(__xludf.DUMMYFUNCTION("""COMPUTED_VALUE"""),3777.0) -> 3777 | T24: =IFERROR(__xludf.DUMMYFUNCTION("""COMPUTED_VALUE"""),"Mystic Matrimony ~Kanetsugu~") -> Mystic Matrimony ~Kanetsugu~
A25: ce_203_bonus_group_017 | B25: 171912▸Mystic Matrimony Special Collection Bonus 〈Mystic Matrimony Kicho x 1〉 | C25: =IFERROR(__xludf.DUMMYFUNCTION("""COMPUTED_VALUE"""),171912.0) -> 171912 | D25: =IFERROR(__xludf.DUMMYFUNCTION("""COMPUTED_VALUE"""),"Mystic Matrimony Special Collection Bonus ") -> Mystic Matrimony Special Collection Bonus | E25: =IFERROR(__xludf.DUMMYFUNCTION("""COMPUTED_VALUE"""),"Mystic Matrimony Kicho x 1") -> Mystic Matrimony Kicho x 1 | F25: Mystic Matrimony Kicho | G25: 1 | H25: Mystic Matrimony Special Collection Bonus | N25: 1 | Q25: 46058.272 | R25: 171912▸Mystic Matrimony Special Collection Bonus 〈Mystic Matrimony Kicho x 1〉 | S25: =IFERROR(__xludf.DUMMYFUNCTION("""COMPUTED_VALUE"""),171912.0) -> 171912 | T25: =IFERROR(__xludf.DUMMYFUNCTION("""COMPUTED_VALUE"""),"Mystic Matrimony Special Collection Bonus ") -> Mystic Matrimony Special Collection Bonus | U25: =IFERROR(__xludf.DUMMYFUNCTION("""COMPUTED_VALUE"""),"Mystic Matrimony Kicho x 1") -> Mystic Matrimony Kicho x 1 | V25: Mystic Matrimony Kicho
A26: ce_203_bonus_group_019 | I26: 6322▸Mystic Matrimony After Story ～Kanetsugu～ | J26: =IFERROR(__xludf.DUMMYFUNCTION("""COMPUTED_VALUE"""),6322.0) -> 6322 | K26: =IFERROR(__xludf.DUMMYFUNCTION("""COMPUTED_VALUE"""),"Mystic Matrimony After Story ～Kanetsugu～") -> Mystic Matrimony After Story ～Kanetsugu～ | N26: 1 | Q26: 46058.272 | R26: 6322▸Mystic Matrimony After Story ～Kanetsugu～ | S26: =IFERROR(__xludf.DUMMYFUNCTION("""COMPUTED_VALUE"""),6322.0) -> 6322 | T26: =IFERROR(__xludf.DUMMYFUNCTION("""COMPUTED_VALUE"""),"Mystic Matrimony After Story ～Kanetsugu～") -> Mystic Matrimony After Story ～Kanetsugu～
A27: ce_203_bonus_group_019 | M27: 3776▸Mystic Matrimony ~Nobunaga~ | N27: 1 | Q27: 46058.272 | R27: 3776▸Mystic Matrimony ~Nobunaga~ | S27: =IFERROR(__xludf.DUMMYFUNCTION("""COMPUTED_VALUE"""),3776.0) -> 3776 | T27: =IFERROR(__xludf.DUMMYFUNCTION("""COMPUTED_VALUE"""),"Mystic Matrimony ~Nobunaga~") -> Mystic Matrimony ~Nobunaga~
A28: ce_203_bonus_group_019 | B28: 171914▸Mystic Matrimony Special Collection Bonus 〈Mystic Matrimony Kanetsugu x 1〉 | C28: =IFERROR(__xludf.DUMMYFUNCTION("""COMPUTED_VALUE"""),171914.0) -> 171914 | D28: =IFERROR(__xludf.DUMMYFUNCTION("""COMPUTED_VALUE"""),"Mystic Matrimony Special Collection Bonus ") -> Mystic Matrimony Special Collection Bonus | E28: =IFERROR(__xludf.DUMMYFUNCTION("""COMPUTED_VALUE"""),"Mystic Matrimony Kanetsugu x 1") -> Mystic Matrimony Kanetsugu x 1 | F28: Mystic Matrimony Kanetsugu | G28: 1 | H28: Mystic Matrimony Special Collection Bonus | N28: 1 | Q28: 46058.272 | R28: 171914▸Mystic Matrimony Special Collection Bonus 〈Mystic Matrimony Kanetsugu x 1〉 | S28: =IFERROR(__xludf.DUMMYFUNCTION("""COMPUTED_VALUE"""),171914.0) -> 171914 | T28: =IFERROR(__xludf.DUMMYFUNCTION("""COMPUTED_VALUE"""),"Mystic Matrimony Special Collection Bonus ") -> Mystic Matrimony Special Collection Bonus | U28: =IFERROR(__xludf.DUMMYFUNCTION("""COMPUTED_VALUE"""),"Mystic Matrimony Kanetsugu x 1") -> Mystic Matrimony Kanetsugu x 1 | V28: Mystic Matrimony Kanetsugu
A29: ce_203_bonus_group_021 | I29: 6321▸Mystic Matrimony After Story ～Nobunaga～ | J29: =IFERROR(__xludf.DUMMYFUNCTION("""COMPUTED_VALUE"""),6321.0) -> 6321 | K29: =IFERROR(__xludf.DUMMYFUNCTION("""COMPUTED_VALUE"""),"Mystic Matrimony After Story ～Nobunaga～") -> Mystic Matrimony After Story ～Nobunaga～ | N29: 1 | Q29: 46058.272 | R29: 6321▸Mystic Matrimony After Story ～Nobunaga～ | S29: =IFERROR(__xludf.DUMMYFUNCTION("""COMPUTED_VALUE"""),6321.0) -> 6321 | T29: =IFERROR(__xludf.DUMMYFUNCTION("""COMPUTED_VALUE"""),"Mystic Matrimony After Story ～Nobunaga～") -> Mystic Matrimony After Story ～Nobunaga～
A30: ce_203_bonus_group_021 | M30: 3775▸Mystic Matrimony ~Masamune~ | N30: 1 | Q30: 46059.272 | R30: 3775▸Mystic Matrimony ~Masamune~ | S30: =IFERROR(__xludf.DUMMYFUNCTION("""COMPUTED_VALUE"""),3775.0) -> 3775 | T30: =IFERROR(__xludf.DUMMYFUNCTION("""COMPUTED_VALUE"""),"Mystic Matrimony ~Masamune~") -> Mystic Matrimony ~Masamune~
A31: ce_203_bonus_group_021 | B31: 171916▸Mystic Matrimony Special Collection Bonus 〈Mystic Matrimony Nobunaga x 1〉 | C31: =IFERROR(__xludf.DUMMYFUNCTION("""COMPUTED_VALUE"""),171916.0) -> 171916 | D31: =IFERROR(__xludf.DUMMYFUNCTION("""COMPUTED_VALUE"""),"Mystic Matrimony Special Collection Bonus ") -> Mystic Matrimony Special Collection Bonus | E31: =IFERROR(__xludf.DUMMYFUNCTION("""COMPUTED_VALUE"""),"Mystic Matrimony Nobunaga x 1") -> Mystic Matrimony Nobunaga x 1 | F31: Mystic Matrimony Nobunaga | G31: 1 | H31: Mystic Matrimony Special Collection Bonus | N31: 1 | Q31: 46058.272 | R31: 171916▸Mystic Matrimony Special Collection Bonus 〈Mystic Matrimony Nobunaga x 1〉 | S31: =IFERROR(__xludf.DUMMYFUNCTION("""COMPUTED_VALUE"""),171916.0) -> 171916 | T31: =IFERROR(__xludf.DUMMYFUNCTION("""COMPUTED_VALUE"""),"Mystic Matrimony Special Collection Bonus ") -> Mystic Matrimony Special Collection Bonus | U31: =IFERROR(__xludf.DUMMYFUNCTION("""COMPUTED_VALUE"""),"Mystic Matrimony Nobunaga x 1") -> Mystic Matrimony Nobunaga x 1 | V31: Mystic Matrimony Nobunaga
A32: ce_203_bonus_group_023 | I32: 6320▸Mystic Matrimony After Story ～Masamune～ | J32: =IFERROR(__xludf.DUMMYFUNCTION("""COMPUTED_VALUE"""),6320.0) -> 6320 | K32: =IFERROR(__xludf.DUMMYFUNCTION("""COMPUTED_VALUE"""),"Mystic Matrimony After Story ～Masamune～") -> Mystic Matrimony After Story ～Masamune～ | N32: 1 | Q32: 46058.272 | R32: 6320▸Mystic Matrimony After Story ～Masamune～ | S32: =IFERROR(__xludf.DUMMYFUNCTION("""COMPUTED_VALUE"""),6320.0) -> 6320 | T32: =IFERROR(__xludf.DUMMYFUNCTION("""COMPUTED_VALUE"""),"Mystic Matrimony After Story ～Masamune～") -> Mystic Matrimony After Story ～Masamune～
A33: ce_203_bonus_group_023 | N33: 1 | Q33: 46058.272 | R33: #N/A
A34: ce_203_bonus_group_023 | B34: 171918▸Mystic Matrimony Special Collection Bonus 〈Mystic Matrimony Masamune x 1〉 | C34: =IFERROR(__xludf.DUMMYFUNCTION("""COMPUTED_VALUE"""),171918.0) -> 171918 | D34: =IFERROR(__xludf.DUMMYFUNCTION("""COMPUTED_VALUE"""),"Mystic Matrimony Special Collection Bonus ") -> Mystic Matrimony Special Collection Bonus | E34: =IFERROR(__xludf.DUMMYFUNCTION("""COMPUTED_VALUE"""),"Mystic Matrimony Masamune x 1") -> Mystic Matrimony Masamune x 1 | F34: Mystic Matrimony Masamune | G34: 1 | H34: Mystic Matrimony Special Collection Bonus | N34: 1 | Q34: 46058.272 | R34: 171918▸Mystic Matrimony Special Collection Bonus 〈Mystic Matrimony Masamune x 1〉 | S34: =IFERROR(__xludf.DUMMYFUNCTION("""COMPUTED_VALUE"""),171918.0) -> 171918 | T34: =IFERROR(__xludf.DUMMYFUNCTION("""COMPUTED_VALUE"""),"Mystic Matrimony Special Collection Bonus ") -> Mystic Matrimony Special Collection Bonus | U34: =IFERROR(__xludf.DUMMYFUNCTION("""COMPUTED_VALUE"""),"Mystic Matrimony Masamune x 1") -> Mystic Matrimony Masamune x 1 | V34: Mystic Matrimony Masamune
A35: ce_203_bonus_group_024 | B35: 171923▸Mystic Matrimony Ranking Bonus 〈Mystic Matrimony Top Ranker Placard x 1〉 | C35: =IFERROR(__xludf.DUMMYFUNCTION("""COMPUTED_VALUE"""),171923.0) -> 171923 | D35: =IFERROR(__xludf.DUMMYFUNCTION("""COMPUTED_VALUE"""),"Mystic Matrimony Ranking Bonus ") -> Mystic Matrimony Ranking Bonus | E35: =IFERROR(__xludf.DUMMYFUNCTION("""COMPUTED_VALUE"""),"Mystic Matrimony Top Ranker Placard x 1") -> Mystic Matrimony Top Ranker Placard x 1 | F35: Mystic Matrimony Top Ranker Placard | G35: 1 | H35: Mystic Matrimony Ranking Bonus | N35: 1 | Q35: 46058.272 | R35: 171923▸Mystic Matrimony Ranking Bonus 〈Mystic Matrimony Top Ranker Placard x 1〉 | S35: =IFERROR(__xludf.DUMMYFUNCTION("""COMPUTED_VALUE"""),171923.0) -> 171923 | T35: =IFERROR(__xludf.DUMMYFUNCTION("""COMPUTED_VALUE"""),"Mystic Matrimony Ranking Bonus ") -> Mystic Matrimony Ranking Bonus | U35: =IFERROR(__xludf.DUMMYFUNCTION("""COMPUTED_VALUE"""),"Mystic Matrimony Top Ranker Placard x 1") -> Mystic Matrimony Top Ranker Placard x 1 | V35: Mystic Matrimony Top Ranker Placard
A36: ce_203_bonus_group_024 | B36: 171924▸Mystic Matrimony Ranking Bonus 〈Enchanted Cobalt Green Kimono x 1〉 | C36: =IFERROR(__xludf.DUMMYFUNCTION("""COMPUTED_VALUE"""),171924.0) -> 171924 | D36: =IFERROR(__xludf.DUMMYFUNCTION("""COMPUTED_VALUE"""),"Mystic Matrimony Ranking Bonus ") -> Mystic Matrimony Ranking Bonus | E36: =IFERROR(__xludf.DUMMYFUNCTION("""COMPUTED_VALUE"""),"Enchanted Cobalt Green Kimono x 1") -> Enchanted Cobalt Green Kimono x 1 | F36: Enchanted Cobalt Green Kimono | G36: 1 | H36: Mystic Matrimony Ranking Bonus | N36: 1 | Q36: 46058.272 | R36: 171924▸Mystic Matrimony Ranking Bonus 〈Enchanted Cobalt Green Kimono x 1〉 | S36: =IFERROR(__xludf.DUMMYFUNCTION("""COMPUTED_VALUE"""),171924.0) -> 171924 | T36: =IFERROR(__xludf.DUMMYFUNCTION("""COMPUTED_VALUE"""),"Mystic Matrimony Ranking Bonus ") -> Mystic Matrimony Ranking Bonus | U36: =IFERROR(__xludf.DUMMYFUNCTION("""COMPUTED_VALUE"""),"Enchanted Cobalt Green Kimono x 1") -> Enchanted Cobalt Green Kimono x 1 | V36: Enchanted Cobalt Green Kimono
A37: ce_203_bonus_group_024 | B37: 171925▸Mystic Matrimony Ranking Bonus 〈His Ogre Ensemble x 1〉 | C37: =IFERROR(__xludf.DUMMYFUNCTION("""COMPUTED_VALUE"""),171925.0) -> 171925 | D37: =IFERROR(__xludf.DUMMYFUNCTION("""COMPUTED_VALUE"""),"Mystic Matrimony Ranking Bonus ") -> Mystic Matrimony Ranking Bonus | E37: =IFERROR(__xludf.DUMMYFUNCTION("""COMPUTED_VALUE"""),"His Ogre Ensemble x 1") -> His Ogre Ensemble x 1 | F37: His Ogre Ensemble | G37: 1 | H37: Mystic Matrimony Ranking Bonus | N37: 1 | Q37: 46058.272 | R37: 171925▸Mystic Matrimony Ranking Bonus 〈His Ogre Ensemble x 1〉 | S37: =IFERROR(__xludf.DUMMYFUNCTION("""COMPUTED_VALUE"""),171925.0) -> 171925 | T37: =IFERROR(__xludf.DUMMYFUNCTION("""COMPUTED_VALUE"""),"Mystic Matrimony Ranking Bonus ") -> Mystic Matrimony Ranking Bonus | U37: =IFERROR(__xludf.DUMMYFUNCTION("""COMPUTED_VALUE"""),"His Ogre Ensemble x 1") -> His Ogre Ensemble x 1 | V37: His Ogre Ensemble
A38: ce_203_bonus_group_024 | B38: 171926▸Mystic Matrimony Ranking Bonus 〈His Draconic Dressrobes x 1〉 | C38: =IFERROR(__xludf.DUMMYFUNCTION("""COMPUTED_VALUE"""),171926.0) -> 171926 | D38: =IFERROR(__xludf.DUMMYFUNCTION("""COMPUTED_VALUE"""),"Mystic Matrimony Ranking Bonus ") -> Mystic Matrimony Ranking Bonus | E38: =IFERROR(__xludf.DUMMYFUNCTION("""COMPUTED_VALUE"""),"His Draconic Dressrobes x 1") -> His Draconic Dressrobes x 1 | F38: His Draconic Dressrobes | G38: 1 | H38: Mystic Matrimony Ranking Bonus | N38: 1 | Q38: 46058.272 | R38: 171926▸Mystic Matrimony Ranking Bonus 〈His Draconic Dressrobes x 1〉 | S38: =IFERROR(__xludf.DUMMYFUNCTION("""COMPUTED_VALUE"""),171926.0) -> 171926 | T38: =IFERROR(__xludf.DUMMYFUNCTION("""COMPUTED_VALUE"""),"Mystic Matrimony Ranking Bonus ") -> Mystic Matrimony Ranking Bonus | U38: =IFERROR(__xludf.DUMMYFUNCTION("""COMPUTED_VALUE"""),"His Draconic Dressrobes x 1") -> His Draconic Dressrobes x 1 | V38: His Draconic Dressrobes
A39: ce_203_bonus_group_024 | B39: 171927▸Mystic Matrimony Ranking Bonus 〈His Vampiric Vestments x 1〉 | C39: =IFERROR(__xludf.DUMMYFUNCTION("""COMPUTED_VALUE"""),171927.0) -> 171927 | D39: =IFERROR(__xludf.DUMMYFUNCTION("""COMPUTED_VALUE"""),"Mystic Matrimony Ranking Bonus ") -> Mystic Matrimony Ranking Bonus | E39: =IFERROR(__xludf.DUMMYFUNCTION("""COMPUTED_VALUE"""),"His Vampiric Vestments x 1") -> His Vampiric Vestments x 1 | F39: His Vampiric Vestments | G39: 1 | H39: Mystic Matrimony Ranking Bonus | N39: 1 | Q39: 46058.272 | R39: 171927▸Mystic Matrimony Ranking Bonus 〈His Vampiric Vestments x 1〉 | S39: =IFERROR(__xludf.DUMMYFUNCTION("""COMPUTED_VALUE"""),171927.0) -> 171927 | T39: =IFERROR(__xludf.DUMMYFUNCTION("""COMPUTED_VALUE"""),"Mystic Matrimony Ranking Bonus ") -> Mystic Matrimony Ranking Bonus | U39: =IFERROR(__xludf.DUMMYFUNCTION("""COMPUTED_VALUE"""),"His Vampiric Vestments x 1") -> His Vampiric Vestments x 1 | V39: His Vampiric Vestments
A40: ce_203_bonus_group_024 | B40: 171928▸Mystic Matrimony Ranking Bonus 〈Nine-Tailed Fox Warlords 1 x 1〉 | C40: =IFERROR(__xludf.DUMMYFUNCTION("""COMPUTED_VALUE"""),171928.0) -> 171928 | D40: =IFERROR(__xludf.DUMMYFUNCTION("""COMPUTED_VALUE"""),"Mystic Matrimony Ranking Bonus ") -> Mystic Matrimony Ranking Bonus | E40: =IFERROR(__xludf.DUMMYFUNCTION("""COMPUTED_VALUE"""),"Nine-Tailed Fox Warlords 1 x 1") -> Nine-Tailed Fox Warlords 1 x 1 | F40: Nine-Tailed Fox Warlords 1 | G40: 1 | H40: Mystic Matrimony Ranking Bonus | N40: 1 | Q40: 46058.272 | R40: 171928▸Mystic Matrimony Ranking Bonus 〈Nine-Tailed Fox Warlords 1 x 1〉 | S40: =IFERROR(__xludf.DUMMYFUNCTION("""COMPUTED_VALUE"""),171928.0) -> 171928 | T40: =IFERROR(__xludf.DUMMYFUNCTION("""COMPUTED_VALUE"""),"Mystic Matrimony Ranking Bonus ") -> Mystic Matrimony Ranking Bonus | U40: =IFERROR(__xludf.DUMMYFUNCTION("""COMPUTED_VALUE"""),"Nine-Tailed Fox Warlords 1 x 1") -> Nine-Tailed Fox Warlords 1 x 1 | V40: Nine-Tailed Fox Warlords 1
A41: ce_203_bonus_group_024 | B41: 171929▸Mystic Matrimony Ranking Bonus 〈Nine-Tailed Fox Warlords 2 x 1〉 | C41: =IFERROR(__xludf.DUMMYFUNCTION("""COMPUTED_VALUE"""),171929.0) -> 171929 | D41: =IFERROR(__xludf.DUMMYFUNCTION("""COMPUTED_VALUE"""),"Mystic Matrimony Ranking Bonus ") -> Mystic Matrimony Ranking Bonus | E41: =IFERROR(__xludf.DUMMYFUNCTION("""COMPUTED_VALUE"""),"Nine-Tailed Fox Warlords 2 x 1") -> Nine-Tailed Fox Warlords 2 x 1 | F41: Nine-Tailed Fox Warlords 2 | G41: 1 | H41: Mystic Matrimony Ranking Bonus | N41: 1 | Q41: 46058.272 | R41: 171929▸Mystic Matrimony Ranking Bonus 〈Nine-Tailed Fox Warlords 2 x 1〉 | S41: =IFERROR(__xludf.DUMMYFUNCTION("""COMPUTED_VALUE"""),171929.0) -> 171929 | T41: =IFERROR(__xludf.DUMMYFUNCTION("""COMPUTED_VALUE"""),"Mystic Matrimony Ranking Bonus ") -> Mystic Matrimony Ranking Bonus | U41: =IFERROR(__xludf.DUMMYFUNCTION("""COMPUTED_VALUE"""),"Nine-Tailed Fox Warlords 2 x 1") -> Nine-Tailed Fox Warlords 2 x 1 | V41: Nine-Tailed Fox Warlords 2
A42: ce_203_bonus_group_024 | B42: 171930▸Mystic Matrimony Ranking Bonus 〈Chapter Ticket x 1〉 | C42: =IFERROR(__xludf.DUMMYFUNCTION("""COMPUTED_VALUE"""),171930.0) -> 171930 | D42: =IFERROR(__xludf.DUMMYFUNCTION("""COMPUTED_VALUE"""),"Mystic Matrimony Ranking Bonus ") -> Mystic Matrimony Ranking Bonus | E42: =IFERROR(__xludf.DUMMYFUNCTION("""COMPUTED_VALUE"""),"Chapter Ticket x 1") -> Chapter Ticket x 1 | F42: Chapter Ticket | G42: 1 | H42: Mystic Matrimony Ranking Bonus | N42: 1 | Q42: 46058.272 | R42: 171930▸Mystic Matrimony Ranking Bonus 〈Chapter Ticket x 1〉 | S42: =IFERROR(__xludf.DUMMYFUNCTION("""COMPUTED_VALUE"""),171930.0) -> 171930 | T42: =IFERROR(__xludf.DUMMYFUNCTION("""COMPUTED_VALUE"""),"Mystic Matrimony Ranking Bonus ") -> Mystic Matrimony Ranking Bonus | U42: =IFERROR(__xludf.DUMMYFUNCTION("""COMPUTED_VALUE"""),"Chapter Ticket x 1") -> Chapter Ticket x 1 | V42: Chapter Ticket
A43: ce_203_bonus_group_024 | B43: 171931▸Mystic Matrimony Ranking Bonus 〈1500 Gold x 1〉 | C43: =IFERROR(__xludf.DUMMYFUNCTION("""COMPUTED_VALUE"""),171931.0) -> 171931 | D43: =IFERROR(__xludf.DUMMYFUNCTION("""COMPUTED_VALUE"""),"Mystic Matrimony Ranking Bonus ") -> Mystic Matrimony Ranking Bonus | E43: =IFERROR(__xludf.DUMMYFUNCTION("""COMPUTED_VALUE"""),"1500 Gold x 1") -> 1500 Gold x 1 | F43: 1500 Gold | G43: 1 | H43: Mystic Matrimony Ranking Bonus | N43: 1 | Q43: 46058.272 | R43: 171931▸Mystic Matrimony Ranking Bonus 〈1500 Gold x 1〉 | S43: =IFERROR(__xludf.DUMMYFUNCTION("""COMPUTED_VALUE"""),171931.0) -> 171931 | T43: =IFERROR(__xludf.DUMMYFUNCTION("""COMPUTED_VALUE"""),"Mystic Matrimony Ranking Bonus ") -> Mystic Matrimony Ranking Bonus | U43: =IFERROR(__xludf.DUMMYFUNCTION("""COMPUTED_VALUE"""),"1500 Gold x 1") -> 1500 Gold x 1 | V43: 1500 Gold
A44: ce_203_bonus_group_025 | B44: 171919▸Mystic Matrimony Extra Bonus 〈Nine-Tailed Fox Yoshimoto x 1〉 | C44: =IFERROR(__xludf.DUMMYFUNCTION("""COMPUTED_VALUE"""),171919.0) -> 171919 | D44: =IFERROR(__xludf.DUMMYFUNCTION("""COMPUTED_VALUE"""),"Mystic Matrimony Extra Bonus ") -> Mystic Matrimony Extra Bonus | E44: =IFERROR(__xludf.DUMMYFUNCTION("""COMPUTED_VALUE"""),"Nine-Tailed Fox Yoshimoto x 1") -> Nine-Tailed Fox Yoshimoto x 1 | F44: Nine-Tailed Fox Yoshimoto | G44: 1 | H44: Mystic Matrimony Extra Bonus | N44: 1 | Q44: 46058.272 | R44: 171919▸Mystic Matrimony Extra Bonus 〈Nine-Tailed Fox Yoshimoto x 1〉 | S44: =IFERROR(__xludf.DUMMYFUNCTION("""COMPUTED_VALUE"""),171919.0) -> 171919 | T44: =IFERROR(__xludf.DUMMYFUNCTION("""COMPUTED_VALUE"""),"Mystic Matrimony Extra Bonus ") -> Mystic Matrimony Extra Bonus | U44: =IFERROR(__xludf.DUMMYFUNCTION("""COMPUTED_VALUE"""),"Nine-Tailed Fox Yoshimoto x 1") -> Nine-Tailed Fox Yoshimoto x 1 | V44: Nine-Tailed Fox Yoshimoto
A45: ce_203_bonus_group_025 | B45: 171920▸Mystic Matrimony Extra Bonus 〈Nine-Tailed Fox Motonari x 1〉 | C45: =IFERROR(__xludf.DUMMYFUNCTION("""COMPUTED_VALUE"""),171920.0) -> 171920 | D45: =IFERROR(__xludf.DUMMYFUNCTION("""COMPUTED_VALUE"""),"Mystic Matrimony Extra Bonus ") -> Mystic Matrimony Extra Bonus | E45: =IFERROR(__xludf.DUMMYFUNCTION("""COMPUTED_VALUE"""),"Nine-Tailed Fox Motonari x 1") -> Nine-Tailed Fox Motonari x 1 | F45: Nine-Tailed Fox Motonari | G45: 1 | H45: Mystic Matrimony Extra Bonus | N45: 1 | Q45: 46058.272 | R45: 171920▸Mystic Matrimony Extra Bonus 〈Nine-Tailed Fox Motonari x 1〉 | S45: =IFERROR(__xludf.DUMMYFUNCTION("""COMPUTED_VALUE"""),171920.0) -> 171920 | T45: =IFERROR(__xludf.DUMMYFUNCTION("""COMPUTED_VALUE"""),"Mystic Matrimony Extra Bonus ") -> Mystic Matrimony Extra Bonus | U45: =IFERROR(__xludf.DUMMYFUNCTION("""COMPUTED_VALUE"""),"Nine-Tailed Fox Motonari x 1") -> Nine-Tailed Fox Motonari x 1 | V45: Nine-Tailed Fox Motonari
A46: ce_203_bonus_group_025 | B46: 171921▸Mystic Matrimony Extra Bonus 〈Nine-Tailed Fox Kanetsugu x 1〉 | C46: =IFERROR(__xludf.DUMMYFUNCTION("""COMPUTED_VALUE"""),171921.0) -> 171921 | D46: =IFERROR(__xludf.DUMMYFUNCTION("""COMPUTED_VALUE"""),"Mystic Matrimony Extra Bonus ") -> Mystic Matrimony Extra Bonus | E46: =IFERROR(__xludf.DUMMYFUNCTION("""COMPUTED_VALUE"""),"Nine-Tailed Fox Kanetsugu x 1") -> Nine-Tailed Fox Kanetsugu x 1 | F46: Nine-Tailed Fox Kanetsugu | G46: 1 | H46: Mystic Matrimony Extra Bonus | N46: 1 | Q46: 46058.272 | R46: 171921▸Mystic Matrimony Extra Bonus 〈Nine-Tailed Fox Kanetsugu x 1〉 | S46: =IFERROR(__xludf.DUMMYFUNCTION("""COMPUTED_VALUE"""),171921.0) -> 171921 | T46: =IFERROR(__xludf.DUMMYFUNCTION("""COMPUTED_VALUE"""),"Mystic Matrimony Extra Bonus ") -> Mystic Matrimony Extra Bonus | U46: =IFERROR(__xludf.DUMMYFUNCTION("""COMPUTED_VALUE"""),"Nine-Tailed Fox Kanetsugu x 1") -> Nine-Tailed Fox Kanetsugu x 1 | V46: Nine-Tailed Fox Kanetsugu
A47: ce_203_bonus_group_025 | B47: 171922▸Mystic Matrimony Extra Bonus 〈Nine-Tailed Fox Kicho x 1〉 | C47: =IFERROR(__xludf.DUMMYFUNCTION("""COMPUTED_VALUE"""),171922.0) -> 171922 | D47: =IFERROR(__xludf.DUMMYFUNCTION("""COMPUTED_VALUE"""),"Mystic Matrimony Extra Bonus ") -> Mystic Matrimony Extra Bonus | E47: =IFERROR(__xludf.DUMMYFUNCTION("""COMPUTED_VALUE"""),"Nine-Tailed Fox Kicho x 1") -> Nine-Tailed Fox Kicho x 1 | F47: Nine-Tailed Fox Kicho | G47: 1 | H47: Mystic Matrimony Extra Bonus | N47: 1 | Q47: 46058.272 | R47: 171922▸Mystic Matrimony Extra Bonus 〈Nine-Tailed Fox Kicho x 1〉 | S47: =IFERROR(__xludf.DUMMYFUNCTION("""COMPUTED_VALUE"""),171922.0) -> 171922 | T47: =IFERROR(__xludf.DUMMYFUNCTION("""COMPUTED_VALUE"""),"Mystic Matrimony Extra Bonus ") -> Mystic Matrimony Extra Bonus | U47: =IFERROR(__xludf.DUMMYFUNCTION("""COMPUTED_VALUE"""),"Nine-Tailed Fox Kicho x 1") -> Nine-Tailed Fox Kicho x 1 | V47: Nine-Tailed Fox Kicho

Sheet ExtraBounus
A1: https://common-legacy-app-admin.us.ikemen-sengoku.jp/admin/isgame/collection/all_setting/203#event_linked_bonus_mst
A3: {=SEQUENCE(1,COLUMNS(A5:AA8))} -> 1 | B3: 2 | C3: 3 | D3: 4 | E3: 5 | F3: 6 | G3: 7 | H3: 8 | I3: 9 | J3: 10 | K3: 11 | L3: 12 | M3: 13 | N3: 14 | O3: 15 | P3: 16 | Q3: 17 | R3: 18 | S3: 19 | T3: 20 | U3: 21 | V3: 22 | W3: 23 | X3: 24 | Y3: 25 | Z3: 26 | AA3: 27
A4: ID | B4: order | C4: chapter / ticket | D4: chapter | E4: ticket | F4: route | G4: collect item quantity | H4: chara | I4: character first name | J4: last name | K4: type | L4: receive title | M4: attention | N4: thumbnail | O4: frame | P4: start | Q4: end | R4: present | S4: present ID | T4: present Name | U4: present Item | V4: present Item Name | W4: present Item count | X4: special story | Y4: voice | Z4: still | AA4: update
A5: 249 | B5: 1 | C5: 13 / 10 | D5: =IFERROR(__xludf.DUMMYFUNCTION("ARRAYFORMULA(IF(ISTEXT(C5:C8),VALUE(SPLIT(C5:C8,""▸〈〉/"")),))"),13.0) -> 13 | E5: =IFERROR(__xludf.DUMMYFUNCTION("""COMPUTED_VALUE"""),10.0) -> 10 | F5: 全ルート | G5: 500 | H5: Yoshimoto Imagawa | I5: =IFERROR(__xludf.DUMMYFUNCTION("ARRAYFORMULA(IF(ISTEXT(H5:H8),SPLIT(H5:H8,""▸〈〉/ ""),))"),"Yoshimoto") -> Yoshimoto | J5: =IFERROR(__xludf.DUMMYFUNCTION("""COMPUTED_VALUE"""),"Imagawa") -> Imagawa | K5: avatar | L5: You got the reward! | N5: 692_084.png | O5: thumb_2.png | P5: 46074.708 | Q5: 46080.708 | R5: 171919▸Mystic Matrimony Extra Bonus 〈Nine-Tailed Fox Yoshimoto x 1〉 | S5: =IFERROR(__xludf.DUMMYFUNCTION("ARRAYFORMULA(IF(ISTEXT(R5:R8),TRIM(SPLIT(R5:R8,""▸〈〉/"")),))"),"171919") -> 171919 | T5: =IFERROR(__xludf.DUMMYFUNCTION("""COMPUTED_VALUE"""),"Mystic Matrimony Extra Bonus") -> Mystic Matrimony Extra Bonus | U5: =IFERROR(__xludf.DUMMYFUNCTION("""COMPUTED_VALUE"""),"Nine-Tailed Fox Yoshimoto x 1") -> Nine-Tailed Fox Yoshimoto x 1 | V5: {=TRIM(LEFT(U5:U8,LEN(U5:U8)-4))} -> Nine-Tailed Fox Yoshimoto | W5: {=VALUE(RIGHT(U5:U8,1))} -> 1 | AA5: 46058.274
A6: 250 | B6: 1 | C6: 13 / 10 | D6: =IFERROR(__xludf.DUMMYFUNCTION("""COMPUTED_VALUE"""),13.0) -> 13 | E6: =IFERROR(__xludf.DUMMYFUNCTION("""COMPUTED_VALUE"""),10.0) -> 10 | F6: 全ルート | G6: 500 | H6: Motonari Mouri | I6: =IFERROR(__xludf.DUMMYFUNCTION("""COMPUTED_VALUE"""),"Motonari") -> Motonari | J6: =IFERROR(__xludf.DUMMYFUNCTION("""COMPUTED_VALUE"""),"Mouri") -> Mouri | K6: avatar | L6: You got the reward! | N6: 651_068.png | O6: thumb_2.png | P6: 46074.708 | Q6: 46080.708 | R6: 171920▸Mystic Matrimony Extra Bonus 〈Nine-Tailed Fox Motonari x 1〉 | S6: =IFERROR(__xludf.DUMMYFUNCTION("""COMPUTED_VALUE"""),"171920") -> 171920 | T6: =IFERROR(__xludf.DUMMYFUNCTION("""COMPUTED_VALUE"""),"Mystic Matrimony Extra Bonus") -> Mystic Matrimony Extra Bonus | U6: =IFERROR(__xludf.DUMMYFUNCTION("""COMPUTED_VALUE"""),"Nine-Tailed Fox Motonari x 1") -> Nine-Tailed Fox Motonari x 1 | V6: Nine-Tailed Fox Motonari | W6: 1 | AA6: 46058.274
A7: 251 | B7: 1 | C7: 13 / 10 | D7: =IFERROR(__xludf.DUMMYFUNCTION("""COMPUTED_VALUE"""),13.0) -> 13 | E7: =IFERROR(__xludf.DUMMYFUNCTION("""COMPUTED_VALUE"""),10.0) -> 10 | F7: 全ルート | G7: 500 | H7: Kanetsugu Naoe | I7: =IFERROR(__xludf.DUMMYFUNCTION("""COMPUTED_VALUE"""),"Kanetsugu") -> Kanetsugu | J7: =IFERROR(__xludf.DUMMYFUNCTION("""COMPUTED_VALUE"""),"Naoe") -> Naoe | K7: avatar | L7: You got the reward! | N7: 647_121.png | O7: thumb_2.png | P7: 46074.708 | Q7: 46080.708 | R7: 171921▸Mystic Matrimony Extra Bonus 〈Nine-Tailed Fox Kanetsugu x 1〉 | S7: =IFERROR(__xludf.DUMMYFUNCTION("""COMPUTED_VALUE"""),"171921") -> 171921 | T7: =IFERROR(__xludf.DUMMYFUNCTION("""COMPUTED_VALUE"""),"Mystic Matrimony Extra Bonus") -> Mystic Matrimony Extra Bonus | U7: =IFERROR(__xludf.DUMMYFUNCTION("""COMPUTED_VALUE"""),"Nine-Tailed Fox Kanetsugu x 1") -> Nine-Tailed Fox Kanetsugu x 1 | V7: Nine-Tailed Fox Kanetsugu | W7: 1 | AA7: 46058.274
A8: 252 | B8: 1 | C8: 13 / 10 | D8: =IFERROR(__xludf.DUMMYFUNCTION("""COMPUTED_VALUE"""),13.0) -> 13 | E8: =IFERROR(__xludf.DUMMYFUNCTION("""COMPUTED_VALUE"""),10.0) -> 10 | F8: 全ルート | G8: 500 | H8: Kicho | I8: =IFERROR(__xludf.DUMMYFUNCTION("""COMPUTED_VALUE"""),"Kicho") -> Kicho | K8: avatar | L8: You got the reward! | N8: 656_066.png | O8: thumb_2.png | P8: 46074.708 | Q8: 46080.708 | R8: 171922▸Mystic Matrimony Extra Bonus 〈Nine-Tailed Fox Kicho x 1〉 | S8: =IFERROR(__xludf.DUMMYFUNCTION("""COMPUTED_VALUE"""),"171922") -> 171922 | T8: =IFERROR(__xludf.DUMMYFUNCTION("""COMPUTED_VALUE"""),"Mystic Matrimony Extra Bonus") -> Mystic Matrimony Extra Bonus | U8: =IFERROR(__xludf.DUMMYFUNCTION("""COMPUTED_VALUE"""),"Nine-Tailed Fox Kicho x 1") -> Nine-Tailed Fox Kicho x 1 | V8: Nine-Tailed Fox Kicho | W8: 1 | AA8: 46058.274

Sheet RankingBonus
A1: https://common-legacy-app-admin.us.ikemen-sengoku.jp/admin/isgame/collection/all_setting/203#Ranking%20Bonus
A3: {=SEQUENCE(1,COLUMNS(A:M))} -> 1 | B3: 2 | C3: 3 | D3: 4 | E3: 5 | F3: 6 | G3: 7 | H3: 8 | I3: 9 | J3: 10 | K3: 11 | L3: 12 | M3: 13
A4: ID | B4: present | C4: present ID | D4: present Name | E4: present Item with count | F4: present Item | G4: present item count | H4: present description | I4: still | J4: from | K4: to | L4: order | M4: update
A5: 5779 | B5: 171923▸Mystic Matrimony Ranking Bonus〈Mystic Matrimony Top Ranker Placard x 1〉 | C5: =IFERROR(__xludf.DUMMYFUNCTION("ARRAYFORMULA(IF(ISTEXT(B5:B36),SPLIT(B5:B36,""▸〈〉""),))"),171923.0) -> 171923 | D5: =IFERROR(__xludf.DUMMYFUNCTION("""COMPUTED_VALUE"""),"Mystic Matrimony Ranking Bonus") -> Mystic Matrimony Ranking Bonus | E5: =IFERROR(__xludf.DUMMYFUNCTION("""COMPUTED_VALUE"""),"Mystic Matrimony Top Ranker Placard x 1") -> Mystic Matrimony Top Ranker Placard x 1 | F5: {=if(ISTEXT(E5:E36), LEFT(E5:E36,LEN(E5:E36)-4), )} -> Mystic Matrimony Top Ranker Placard | G5: 1 | H5: Mystic Matrimony Ranking Bonus | J5: 1 | K5: 100 | L5: 1 | M5: 46058.27
A6: 5780 | B6: 171924▸Mystic Matrimony Ranking Bonus〈Enchanted Cobalt Green Kimono x 1〉 | C6: =IFERROR(__xludf.DUMMYFUNCTION("""COMPUTED_VALUE"""),171924.0) -> 171924 | D6: =IFERROR(__xludf.DUMMYFUNCTION("""COMPUTED_VALUE"""),"Mystic Matrimony Ranking Bonus") -> Mystic Matrimony Ranking Bonus | E6: =IFERROR(__xludf.DUMMYFUNCTION("""COMPUTED_VALUE"""),"Enchanted Cobalt Green Kimono x 1") -> Enchanted Cobalt Green Kimono x 1 | F6: Enchanted Cobalt Green Kimono | G6: 1 | H6: Mystic Matrimony Ranking Bonus | J6: 1 | K6: 100 | L6: 2 | M6: 46058.27
A7: 5781 | B7: 171925▸Mystic Matrimony Ranking Bonus〈His Ogre Ensemble x 1〉 | C7: =IFERROR(__xludf.DUMMYFUNCTION("""COMPUTED_VALUE"""),171925.0) -> 171925 | D7: =IFERROR(__xludf.DUMMYFUNCTION("""COMPUTED_VALUE"""),"Mystic Matrimony Ranking Bonus") -> Mystic Matrimony Ranking Bonus | E7: =IFERROR(__xludf.DUMMYFUNCTION("""COMPUTED_VALUE"""),"His Ogre Ensemble x 1") -> His Ogre Ensemble x 1 | F7: His Ogre Ensemble | G7: 1 | H7: Mystic Matrimony Ranking Bonus | J7: 1 | K7: 100 | L7: 3 | M7: 46058.27
A8: 5782 | B8: 171926▸Mystic Matrimony Ranking Bonus〈His Draconic Dressrobes x 1〉 | C8: =IFERROR(__xludf.DUMMYFUNCTION("""COMPUTED_VALUE"""),171926.0) -> 171926 | D8: =IFERROR(__xludf.DUMMYFUNCTION("""COMPUTED_VALUE"""),"Mystic Matrimony Ranking Bonus") -> Mystic Matrimony Ranking Bonus | E8: =IFERROR(__xludf.DUMMYFUNCTION("""COMPUTED_VALUE"""),"His Draconic Dressrobes x 1") -> His Draconic Dressrobes x 1 | F8: His Draconic Dressrobes | G8: 1 | H8: Mystic Matrimony Ranking Bonus | J8: 1 | K8: 100 | L8: 4 | M8: 46058.27
A9: 5783 | B9: 171927▸Mystic Matrimony Ranking Bonus〈His Vampiric Vestments x 1〉 | C9: =IFERROR(__xludf.DUMMYFUNCTION("""COMPUTED_VALUE"""),171927.0) -> 171927 | D9: =IFERROR(__xludf.DUMMYFUNCTION("""COMPUTED_VALUE"""),"Mystic Matrimony Ranking Bonus") -> Mystic Matrimony Ranking Bonus | E9: =IFERROR(__xludf.DUMMYFUNCTION("""COMPUTED_VALUE"""),"His Vampiric Vestments x 1") -> His Vampiric Vestments x 1 | F9: His Vampiric Vestments | G9: 1 | H9: Mystic Matrimony Ranking Bonus | J9: 1 | K9: 100 | L9: 5 | M9: 46058.27
A10: 5784 | B10: 171928▸Mystic Matrimony Ranking Bonus〈Nine-Tailed Fox Warlords 1 x 1〉 | C10: =IFERROR(__xludf.DUMMYFUNCTION("""COMPUTED_VALUE"""),171928.0) -> 171928 | D10: =IFERROR(__xludf.DUMMYFUNCTION("""COMPUTED_VALUE"""),"Mystic Matrimony Ranking Bonus") -> Mystic Matrimony Ranking Bonus | E10: =IFERROR(__xludf.DUMMYFUNCTION("""COMPUTED_VALUE"""),"Nine-Tailed Fox Warlords 1 x 1") -> Nine-Tailed Fox Warlords 1 x 1 | F10: Nine-Tailed Fox Warlords 1 | G10: 1 | H10: Mystic Matrimony Ranking Bonus | J10: 1 | K10: 100 | L10: 6 | M10: 46058.27
A11: 5785 | B11: 171929▸Mystic Matrimony Ranking Bonus〈Nine-Tailed Fox Warlords 2 x 1〉 | C11: =IFERROR(__xludf.DUMMYFUNCTION("""COMPUTED_VALUE"""),171929.0) -> 171929 | D11: =IFERROR(__xludf.DUMMYFUNCTION("""COMPUTED_VALUE"""),"Mystic Matrimony Ranking Bonus") -> Mystic Matrimony Ranking Bonus | E11: =IFERROR(__xludf.DUMMYFUNCTION("""COMPUTED_VALUE"""),"Nine-Tailed Fox Warlords 2 x 1") -> Nine-Tailed Fox Warlords 2 x 1 | F11: Nine-Tailed Fox Warlords 2 | G11: 1 | H11: Mystic Matrimony Ranking Bonus | J11: 1 | K11: 100 | L11: 7 | M11: 46058.27
A12: 5786 | B12: 171930▸Mystic Matrimony Ranking Bonus〈Chapter Ticket x 1〉 | C12: =IFERROR(__xludf.DUMMYFUNCTION("""COMPUTED_VALUE"""),171930.0) -> 171930 | D12: =IFERROR(__xludf.DUMMYFUNCTION("""COMPUTED_VALUE"""),"Mystic Matrimony Ranking Bonus") -> Mystic Matrimony Ranking Bonus | E12: =IFERROR(__xludf.DUMMYFUNCTION("""COMPUTED_VALUE"""),"Chapter Ticket x 1") -> Chapter Ticket x 1 | F12: Chapter Ticket | G12: 1 | H12: Mystic Matrimony Ranking Bonus | J12: 1 | K12: 100 | L12: 8 | M12: 46058.27
A13: 5787 | B13: 171931▸Mystic Matrimony Ranking Bonus〈1500 Gold x 1〉 | C13: =IFERROR(__xludf.DUMMYFUNCTION("""COMPUTED_VALUE"""),171931.0) -> 171931 | D13: =IFERROR(__xludf.DUMMYFUNCTION("""COMPUTED_VALUE"""),"Mystic Matrimony Ranking Bonus") -> Mystic Matrimony Ranking Bonus | E13: =IFERROR(__xludf.DUMMYFUNCTION("""COMPUTED_VALUE"""),"1500 Gold x 1") -> 1500 Gold x 1 | F13: 1500 Gold | G13: 1 | H13: Mystic Matrimony Ranking Bonus | J13: 1 | K13: 100 | L13: 9 | M13: 46058.27
A14: 5788 | B14: 171924▸Mystic Matrimony Ranking Bonus〈Enchanted Cobalt Green Kimono x 1〉 | C14: =IFERROR(__xludf.DUMMYFUNCTION("""COMPUTED_VALUE"""),171924.0) -> 171924 | D14: =IFERROR(__xludf.DUMMYFUNCTION("""COMPUTED_VALUE"""),"Mystic Matrimony Ranking Bonus") -> Mystic Matrimony Ranking Bonus | E14: =IFERROR(__xludf.DUMMYFUNCTION("""COMPUTED_VALUE"""),"Enchanted Cobalt Green Kimono x 1") -> Enchanted Cobalt Green Kimono x 1 | F14: Enchanted Cobalt Green Kimono | G14: 1 | H14: Mystic Matrimony Ranking Bonus | J14: 101 | K14: 150 | L14: 1 | M14: 46058.27
A15: 5789 | B15: 171925▸Mystic Matrimony Ranking Bonus〈His Ogre Ensemble x 1〉 | C15: =IFERROR(__xludf.DUMMYFUNCTION("""COMPUTED_VALUE"""),171925.0) -> 171925 | D15: =IFERROR(__xludf.DUMMYFUNCTION("""COMPUTED_VALUE"""),"Mystic Matrimony Ranking Bonus") -> Mystic Matrimony Ranking Bonus | E15: =IFERROR(__xludf.DUMMYFUNCTION("""COMPUTED_VALUE"""),"His Ogre Ensemble x 1") -> His Ogre Ensemble x 1 | F15: His Ogre Ensemble | G15: 1 | H15: Mystic Matrimony Ranking Bonus | J15: 101 | K15: 150 | L15: 2 | M15: 46058.27
A16: 5790 | B16: 171926▸Mystic Matrimony Ranking Bonus〈His Draconic Dressrobes x 1〉 | C16: =IFERROR(__xludf.DUMMYFUNCTION("""COMPUTED_VALUE"""),171926.0) -> 171926 | D16: =IFERROR(__xludf.DUMMYFUNCTION("""COMPUTED_VALUE"""),"Mystic Matrimony Ranking Bonus") -> Mystic Matrimony Ranking Bonus | E16: =IFERROR(__xludf.DUMMYFUNCTION("""COMPUTED_VALUE"""),"His Draconic Dressrobes x 1") -> His Draconic Dressrobes x 1 | F16: His Draconic Dressrobes | G16: 1 | H16: Mystic Matrimony Ranking Bonus | J16: 101 | K16: 150 | L16: 3 | M16: 46058.27
A17: 5791 | B17: 171927▸Mystic Matrimony Ranking Bonus〈His Vampiric Vestments x 1〉 | C17: =IFERROR(__xludf.DUMMYFUNCTION("""COMPUTED_VALUE"""),171927.0) -> 171927 | D17: =IFERROR(__xludf.DUMMYFUNCTION("""COMPUTED_VALUE"""),"Mystic Matrimony Ranking Bonus") -> Mystic Matrimony Ranking Bonus | E17: =IFERROR(__xludf.DUMMYFUNCTION("""COMPUTED_VALUE"""),"His Vampiric Vestments x 1") -> His Vampiric Vestments x 1 | F17: His Vampiric Vestments | G17: 1 | H17: Mystic Matrimony Ranking Bonus | J17: 101 | K17: 150 | L17: 4 | M17: 46058.27
A18: 5792 | B18: 171928▸Mystic Matrimony Ranking Bonus〈Nine-Tailed Fox Warlords 1 x 1〉 | C18: =IFERROR(__xludf.DUMMYFUNCTION("""COMPUTED_VALUE"""),171928.0) -> 171928 | D18: =IFERROR(__xludf.DUMMYFUNCTION("""COMPUTED_VALUE"""),"Mystic Matrimony Ranking Bonus") -> Mystic Matrimony Ranking Bonus | E18: =IFERROR(__xludf.DUMMYFUNCTION("""COMPUTED_VALUE"""),"Nine-Tailed Fox Warlords 1 x 1") -> Nine-Tailed Fox Warlords 1 x 1 | F18: Nine-Tailed Fox Warlords 1 | G18: 1 | H18: Mystic Matrimony Ranking Bonus | J18: 101 | K18: 150 | L18: 5 | M18: 46058.27
A19: 5793 | B19: 171929▸Mystic Matrimony Ranking Bonus〈Nine-Tailed Fox Warlords 2 x 1〉 | C19: =IFERROR(__xludf.DUMMYFUNCTION("""COMPUTED_VALUE"""),171929.0) -> 171929 | D19: =IFERROR(__xludf.DUMMYFUNCTION("""COMPUTED_VALUE"""),"Mystic Matrimony Ranking Bonus") -> Mystic Matrimony Ranking Bonus | E19: =IFERROR(__xludf.DUMMYFUNCTION("""COMPUTED_VALUE"""),"Nine-Tailed Fox Warlords 2 x 1") -> Nine-Tailed Fox Warlords 2 x 1 | F19: Nine-Tailed Fox Warlords 2 | G19: 1 | H19: Mystic Matrimony Ranking Bonus | J19: 101 | K19: 150 | L19: 6 | M19: 46058.27
A20: 5794 | B20: 171930▸Mystic Matrimony Ranking Bonus〈Chapter Ticket x 1〉 | C20: =IFERROR(__xludf.DUMMYFUNCTION("""COMPUTED_VALUE"""),171930.0) -> 171930 | D20: =IFERROR(__xludf.DUMMYFUNCTION("""COMPUTED_VALUE"""),"Mystic Matrimony Ranking Bonus") -> Mystic Matrimony Ranking Bonus | E20: =IFERROR(__xludf.DUMMYFUNCTION("""COMPUTED_VALUE"""),"Chapter Ticket x 1") -> Chapter Ticket x 1 | F20: Chapter Ticket | G20: 1 | H20: Mystic Matrimony Ranking Bonus | J20: 101 | K20: 150 | L20: 7 | M20: 46058.27
A21: 5795 | B21: 171931▸Mystic Matrimony Ranking Bonus〈1500 Gold x 1〉 | C21: =IFERROR(__xludf.DUMMYFUNCTION("""COMPUTED_VALUE"""),171931.0) -> 171931 | D21: =IFERROR(__xludf.DUMMYFUNCTION("""COMPUTED_VALUE"""),"Mystic Matrimony Ranking Bonus") -> Mystic Matrimony Ranking Bonus | E21: =IFERROR(__xludf.DUMMYFUNCTION("""COMPUTED_VALUE"""),"1500 Gold x 1") -> 1500 Gold x 1 | F21: 1500 Gold | G21: 1 | H21: Mystic Matrimony Ranking Bonus | J21: 101 | K21: 150 | L21: 8 | M21: 46058.27
A22: 5796 | B22: 171925▸Mystic Matrimony Ranking Bonus〈His Ogre Ensemble x 1〉 | C22: =IFERROR(__xludf.DUMMYFUNCTION("""COMPUTED_VALUE"""),171925.0) -> 171925 | D22: =IFERROR(__xludf.DUMMYFUNCTION("""COMPUTED_VALUE"""),"Mystic Matrimony Ranking Bonus") -> Mystic Matrimony Ranking Bonus | E22: =IFERROR(__xludf.DUMMYFUNCTION("""COMPUTED_VALUE"""),"His Ogre Ensemble x 1") -> His Ogre Ensemble x 1 | F22: His Ogre Ensemble | G22: 1 | H22: Mystic Matrimony Ranking Bonus | J22: 151 | K22: 300 | L22: 1 | M22: 46058.27
A23: 5797 | B23: 171926▸Mystic Matrimony Ranking Bonus〈His Draconic Dressrobes x 1〉 | C23: =IFERROR(__xludf.DUMMYFUNCTION("""COMPUTED_VALUE"""),171926.0) -> 171926 | D23: =IFERROR(__xludf.DUMMYFUNCTION("""COMPUTED_VALUE"""),"Mystic Matrimony Ranking Bonus") -> Mystic Matrimony Ranking Bonus | E23: =IFERROR(__xludf.DUMMYFUNCTION("""COMPUTED_VALUE"""),"His Draconic Dressrobes x 1") -> His Draconic Dressrobes x 1 | F23: His Draconic Dressrobes | G23: 1 | H23: Mystic Matrimony Ranking Bonus | J23: 151 | K23: 300 | L23: 2 | M23: 46058.27
A24: 5798 | B24: 171927▸Mystic Matrimony Ranking Bonus〈His Vampiric Vestments x 1〉 | C24: =IFERROR(__xludf.DUMMYFUNCTION("""COMPUTED_VALUE"""),171927.0) -> 171927 | D24: =IFERROR(__xludf.DUMMYFUNCTION("""COMPUTED_VALUE"""),"Mystic Matrimony Ranking Bonus") -> Mystic Matrimony Ranking Bonus | E24: =IFERROR(__xludf.DUMMYFUNCTION("""COMPUTED_VALUE"""),"His Vampiric Vestments x 1") -> His Vampiric Vestments x 1 | F24: His Vampiric Vestments | G24: 1 | H24: Mystic Matrimony Ranking Bonus | J24: 151 | K24: 300 | L24: 3 | M24: 46058.27
A25: 5799 | B25: 171928▸Mystic Matrimony Ranking Bonus〈Nine-Tailed Fox Warlords 1 x 1〉 | C25: =IFERROR(__xludf.DUMMYFUNCTION("""COMPUTED_VALUE"""),171928.0) -> 171928 | D25: =IFERROR(__xludf.DUMMYFUNCTION("""COMPUTED_VALUE"""),"Mystic Matrimony Ranking Bonus") -> Mystic Matrimony Ranking Bonus | E25: =IFERROR(__xludf.DUMMYFUNCTION("""COMPUTED_VALUE"""),"Nine-Tailed Fox Warlords 1 x 1") -> Nine-Tailed Fox Warlords 1 x 1 | F25: Nine-Tailed Fox Warlords 1 | G25: 1 | H25: Mystic Matrimony Ranking Bonus | J25: 151 | K25: 300 | L25: 4 | M25: 46058.27
A26: 5800 | B26: 171929▸Mystic Matrimony Ranking Bonus〈Nine-Tailed Fox Warlords 2 x 1〉 | C26: =IFERROR(__xludf.DUMMYFUNCTION("""COMPUTED_VALUE"""),171929.0) -> 171929 | D26: =IFERROR(__xludf.DUMMYFUNCTION("""COMPUTED_VALUE"""),"Mystic Matrimony Ranking Bonus") -> Mystic Matrimony Ranking Bonus | E26: =IFERROR(__xludf.DUMMYFUNCTION("""COMPUTED_VALUE"""),"Nine-Tailed Fox Warlords 2 x 1") -> Nine-Tailed Fox Warlords 2 x 1 | F26: Nine-Tailed Fox Warlords 2 | G26: 1 | H26: Mystic Matrimony Ranking Bonus | J26: 151 | K26: 300 | L26: 5 | M26: 46058.27
A27: 5801 | B27: 171930▸Mystic Matrimony Ranking Bonus〈Chapter Ticket x 1〉 | C27: =IFERROR(__xludf.DUMMYFUNCTION("""COMPUTED_VALUE"""),171930.0) -> 171930 | D27: =IFERROR(__xludf.DUMMYFUNCTION("""COMPUTED_VALUE"""),"Mystic Matrimony Ranking Bonus") -> Mystic Matrimony Ranking Bonus | E27: =IFERROR(__xludf.DUMMYFUNCTION("""COMPUTED_VALUE"""),"Chapter Ticket x 1") -> Chapter Ticket x 1 | F27: Chapter Ticket | G27: 1 | H27: Mystic Matrimony Ranking Bonus | J27: 151 | K27: 300 | L27: 6 | M27: 46058.27
A28: 5802 | B28: 171931▸Mystic Matrimony Ranking Bonus〈1500 Gold x 1〉 | C28: =IFERROR(__xludf.DUMMYFUNCTION("""COMPUTED_VALUE"""),171931.0) -> 171931 | D28: =IFERROR(__xludf.DUMMYFUNCTION("""COMPUTED_VALUE"""),"Mystic Matrimony Ranking Bonus") -> Mystic Matrimony Ranking Bonus | E28: =IFERROR(__xludf.DUMMYFUNCTION("""COMPUTED_VALUE"""),"1500 Gold x 1") -> 1500 Gold x 1 | F28: 1500 Gold | G28: 1 | H28: Mystic Matrimony Ranking Bonus | J28: 151 | K28: 300 | L28: 7 | M28: 46058.27
A29: 5803 | B29: 171928▸Mystic Matrimony Ranking Bonus〈Nine-Tailed Fox Warlords 1 x 1〉 | C29: =IFERROR(__xludf.DUMMYFUNCTION("""COMPUTED_VALUE"""),171928.0) -> 171928 | D29: =IFERROR(__xludf.DUMMYFUNCTION("""COMPUTED_VALUE"""),"Mystic Matrimony Ranking Bonus") -> Mystic Matrimony Ranking Bonus | E29: =IFERROR(__xludf.DUMMYFUNCTION("""COMPUTED_VALUE"""),"Nine-Tailed Fox Warlords 1 x 1") -> Nine-Tailed Fox Warlords 1 x 1 | F29: Nine-Tailed Fox Warlords 1 | G29: 1 | H29: Mystic Matrimony Ranking Bonus | J29: 301 | K29: 500 | L29: 1 | M29: 46058.27
A30: 5804 | B30: 171929▸Mystic Matrimony Ranking Bonus〈Nine-Tailed Fox Warlords 2 x 1〉 | C30: =IFERROR(__xludf.DUMMYFUNCTION("""COMPUTED_VALUE"""),171929.0) -> 171929 | D30: =IFERROR(__xludf.DUMMYFUNCTION("""COMPUTED_VALUE"""),"Mystic Matrimony Ranking Bonus") -> Mystic Matrimony Ranking Bonus | E30: =IFERROR(__xludf.DUMMYFUNCTION("""COMPUTED_VALUE"""),"Nine-Tailed Fox Warlords 2 x 1") -> Nine-Tailed Fox Warlords 2 x 1 | F30: Nine-Tailed Fox Warlords 2 | G30: 1 | H30: Mystic Matrimony Ranking Bonus | J30: 301 | K30: 500 | L30: 2 | M30: 46058.27
A31: 5805 | B31: 171930▸Mystic Matrimony Ranking Bonus〈Chapter Ticket x 1〉 | C31: =IFERROR(__xludf.DUMMYFUNCTION("""COMPUTED_VALUE"""),171930.0) -> 171930 | D31: =IFERROR(__xludf.DUMMYFUNCTION("""COMPUTED_VALUE"""),"Mystic Matrimony Ranking Bonus") -> Mystic Matrimony Ranking Bonus | E31: =IFERROR(__xludf.DUMMYFUNCTION("""COMPUTED_VALUE"""),"Chapter Ticket x 1") -> Chapter Ticket x 1 | F31: Chapter Ticket | G31: 1 | H31: Mystic Matrimony Ranking Bonus | J31: 301 | K31: 500 | L31: 3 | M31: 46058.27
A32: 5806 | B32: 171931▸Mystic Matrimony Ranking Bonus〈1500 Gold x 1〉 | C32: =IFERROR(__xludf.DUMMYFUNCTION("""COMPUTED_VALUE"""),171931.0) -> 171931 | D32: =IFERROR(__xludf.DUMMYFUNCTION("""COMPUTED_VALUE"""),"Mystic Matrimony Ranking Bonus") -> Mystic Matrimony Ranking Bonus | E32: =IFERROR(__xludf.DUMMYFUNCTION("""COMPUTED_VALUE"""),"1500 Gold x 1") -> 1500 Gold x 1 | F32: 1500 Gold | G32: 1 | H32: Mystic Matrimony Ranking Bonus | J32: 301 | K32: 500 | L32: 4 | M32: 46058.27
A33: 5807 | B33: 171930▸Mystic Matrimony Ranking Bonus〈Chapter Ticket x 1〉 | C33: =IFERROR(__xludf.DUMMYFUNCTION("""COMPUTED_VALUE"""),171930.0) -> 171930 | D33: =IFERROR(__xludf.DUMMYFUNCTION("""COMPUTED_VALUE"""),"Mystic Matrimony Ranking Bonus") -> Mystic Matrimony Ranking Bonus | E33: =IFERROR(__xludf.DUMMYFUNCTION("""COMPUTED_VALUE"""),"Chapter Ticket x 1") -> Chapter Ticket x 1 | F33: Chapter Ticket | G33: 1 | H33: Mystic Matrimony Ranking Bonus | J33: 501 | K33: 1000 | L33: 1 | M33: 46058.27
A34: 5808 | B34: 171931▸Mystic Matrimony Ranking Bonus〈1500 Gold x 1〉 | C34: =IFERROR(__xludf.DUMMYFUNCTION("""COMPUTED_VALUE"""),171931.0) -> 171931 | D34: =IFERROR(__xludf.DUMMYFUNCTION("""COMPUTED_VALUE"""),"Mystic Matrimony Ranking Bonus") -> Mystic Matrimony Ranking Bonus | E34: =IFERROR(__xludf.DUMMYFUNCTION("""COMPUTED_VALUE"""),"1500 Gold x 1") -> 1500 Gold x 1 | F34: 1500 Gold | G34: 1 | H34: Mystic Matrimony Ranking Bonus | J34: 501 | K34: 1000 | L34: 2 | M34: 46058.27
A35: 5809 | B35: 171931▸Mystic Matrimony Ranking Bonus〈1500 Gold x 1〉 | C35: =IFERROR(__xludf.DUMMYFUNCTION("""COMPUTED_VALUE"""),171931.0) -> 171931 | D35: =IFERROR(__xludf.DUMMYFUNCTION("""COMPUTED_VALUE"""),"Mystic Matrimony Ranking Bonus") -> Mystic Matrimony Ranking Bonus | E35: =IFERROR(__xludf.DUMMYFUNCTION("""COMPUTED_VALUE"""),"1500 Gold x 1") -> 1500 Gold x 1 | F35: 1500 Gold | G35: 1 | H35: Mystic Matrimony Ranking Bonus | J35: 1001 | K35: 1500 | L35: 1 | M35: 46058.27

Sheet special_story
A1: https://common-legacy-app-admin.us.ikemen-sengoku.jp/admin/specialstory?search_title=Demon+of+My+Dreams
A2: https://common-legacy-app-admin.us.ikemen-sengoku.jp/admin/specialstory?search_title=Let%27s+Meet+in+a+Dream
A4: ID | B4: ストーリータイプ | C4: 特別ストーリータイトル | D4: キャラ名 | E4: チケットID | F4: 公開開始 | G4: 公開終了 | H4: 編集ボタン | I4: 本番反映 | J4: 他PF反映
A5: 4040 | B5: イベント *** | C5: Demon of My Dreams (Nobunaga) | D5: Nobunaga | E5: 22519 | F5: 2023-11-06 17:00:00 | G5: 無期限
A6: 4041 | B6: イベント *** | C6: Demon of My Dreams (Masamune) | D6: Masamune | E6: 22520 | F6: 2023-11-06 17:00:00 | G6: 無期限
A7: 4042 | B7: イベント *** | C7: Demon of My Dreams (Hideyoshi) | D7: Hideyoshi | E7: 22521 | F7: 2023-11-06 17:00:00 | G7: 無期限
A8: 4043 | B8: イベント *** | C8: Demon of My Dreams (Ieyasu) | D8: Ieyasu | E8: 22522 | F8: 2023-11-06 17:00:00 | G8: 無期限
A9: 4044 | B9: イベント *** | C9: Demon of My Dreams (Mitsuhide) | D9: Mitsuhide | E9: 22523 | F9: 2023-11-06 17:00:00 | G9: 無期限
A10: 4045 | B10: イベント *** | C10: Demon of My Dreams (Mitsunari) | D10: Mitsunari | E10: 22524 | F10: 2023-11-06 17:00:00 | G10: 無期限
A11: 4046 | B11: イベント *** | C11: Demon of My Dreams (Yukimura) | D11: Yukimura | E11: 22525 | F11: 2023-11-06 17:00:00 | G11: 無期限
A12: 4047 | B12: イベント *** | C12: Demon of My Dreams (Shingen) | D12: Shingen | E12: 22526 | F12: 2023-11-06 17:00:00 | G12: 無期限
A13: 4048 | B13: イベント *** | C13: Demon of My Dreams (Kenshin) | D13: Kenshin | E13: 22527 | F13: 2023-11-06 17:00:00 | G13: 無期限
A14: 4049 | B14: イベント *** | C14: Demon of My Dreams (Sasuke) | D14: Sasuke | E14: 22528 | F14: 2023-11-06 17:00:00 | G14: 無期限
A15: 4050 | B15: イベント *** | C15: Demon of My Dreams (Kennyo) | D15: Kennyo | E15: 22529 | F15: 2023-11-06 17:00:00 | G15: 無期限
A16: 4051 | B16: イベント *** | C16: Demon of My Dreams (Ranmaru) | D16: Ranmaru | E16: 22530 | F16: 2023-11-06 17:00:00 | G16: 無期限
... A22: 4036 | B22: イベント *** | C22: Let's Meet in a Dream Part2 | D22: All | E22: 22515 | F22: 2023-11-06 17:00:00 | G22: 無期限

Sheet コレクション特典
A1: No | B1: 累計投票数 | C1: 確認方法 | D1: 確認内容 | E1: 確認項目 | F1: 累計投票数 | G1: 確認方法 | H1: 確認内容 | I1: 確認項目 | J1: 特典情報 | K1: table | L1: ID | M1: Column | N1: Result | O1: テスト環境 | S1: 本番環境 | W1: 備考 | X1: テスターコメント | Y1: チケットURL
O2: 確認 | P2: 担当 | Q2: 担当者 | R2: 日付 | S2: 確認 | T2: 担当 | U2: 担当者 | V2: 日付
A3: =ROW()-2 -> 1 | C3: 実機 | E3: 特典サムネイル画像が表示されているか | G3: 實體機台 | I3: 是否顯示特典縮圖 | O3: OK | P3: IW | Q3: Bill | R3: 46062 | S3: OK | T3: {=IF(S3:S393="OK",{"IW","Bill","2/12"},)} -> IW | U3: Bill | V3: 2/12
A4: =ROW()-2 -> 2 | B4: 10 | C4: 管理ツール コレクションイベント＞該当イベント＞コレクション＞全特典の確認 | D4: 特典一覧 ＞コレクション一覧 | E4: 特典アイテムが右記の通り設定されているか | F4: 10 | G4: 管理工具 收集活動＞該活動＞收集＞確認所有特典 | H4: 特典一覽 ＞收集一覽 | I4: 特典道具是否按右側設定 | J4: ='参照_各種特典'!$F$20 -> Demon of My Dreams | K4: CollectionBonus!B5:N | L4: =IFERROR(__xludf.DUMMYFUNCTION("ARRAYFORMULA( LET( _range, F4:F326, IFNA(VLOOKUP(ROW(_range),FILTER({ROW(_range),_range},LEN(_range)),2,1),)) )"),10.0) -> 10 | M4: 11 | N4: {=IF(LEN(J4:J326),VLOOKUP(VALUE(L4:L326),INDIRECT(K4:K326),M4:M326,0),)} -> Demon of My Dreams | O4: OK | P4: IW | Q4: Bill | R4: 46062
A5: =ROW()-2 -> 3 | C5: 実機 | E5: 特典サムネイル画像が表示されているか | G5: 實體機台 | I5: 是否顯示特典縮圖 | K5: CollectionBonus!B5:N | L5: =IFERROR(__xludf.DUMMYFUNCTION("""COMPUTED_VALUE"""),10.0) -> 10 | O5: OK | P5: IW | Q5: Bill | R5: 46062 | S5: OK | T5: IW | U5: Bill | V5: 2/12
A6: =ROW()-2 -> 4 | D6: コレクトアイテム使用 | E6: コレクトアイテム使用後に特典が取得できるか | H6: 使用收集道具 | I6: 使用收集道具後是否能取得特典 | K6: CollectionBonus!B5:N | L6: =IFERROR(__xludf.DUMMYFUNCTION("""COMPUTED_VALUE"""),10.0) -> 10 | S6: OK | T6: IW | U6: Bill | V6: 2/12
A7: =ROW()-2 -> 5 | B7: 20 | C7: コレクションイベント＞該当イベント＞コレクション＞全特典の確認 | D7: 特典一覧 ＞コレクション一覧 | E7: 受け取り文言が右記の通り設定されているか ※受取箱に入れるもののみ確認する | F7: 20 | G7: 收集活動＞該活動＞收集＞確認所有特典 | H7: 特典一覽 ＞收集一覽 | I7: 是否已按照右列內容設定領取文案※僅確認放入領取箱中的項目 | J7: ='参照_各種特典'!D21 -> Mystic Matrimony◆Collection Bonus | K7: CollectionBonus!B5:N | L7: =IFERROR(__xludf.DUMMYFUNCTION("""COMPUTED_VALUE"""),20.0) -> 20 | M7: 4 | N7: Mystic Matrimony◆Collection Bonus | O7: OK | P7: IW | Q7: Bill | R7: 46062
A8: =ROW()-2 -> 6 | E8: 特典アイテムが右記の通り設定されているか | I8: 特典道具是否按右側設定 | J8: ='参照_各種特典'!F21 -> Shaved Ice (+50 Stamina) | K8: CollectionBonus!B5:N | L8: =IFERROR(__xludf.DUMMYFUNCTION("""COMPUTED_VALUE"""),20.0) -> 20 | M8: 11 | N8: Shaved Ice (+50 Stamina) | O8: OK | P8: IW | Q8: Bill | R8: 46062
A9: =ROW()-2 -> 7 | E9: 個数が左記の通り設定されているか | I9: 個數是否按右側設定 | J9: ='参照_各種特典'!H21 -> 1 | K9: CollectionBonus!B5:N | L9: =IFERROR(__xludf.DUMMYFUNCTION("""COMPUTED_VALUE"""),20.0) -> 20 | M9: 7 | N9: 1 | O9: OK | P9: IW | Q9: Bill | R9: 46062
A10: =ROW()-2 -> 8 | C10: 実機 | E10: 特典サムネイル画像が表示されているか | G10: 實體機台 | I10: 是否顯示特典縮圖 | K10: CollectionBonus!B5:N | L10: =IFERROR(__xludf.DUMMYFUNCTION("""COMPUTED_VALUE"""),20.0) -> 20 | O10: OK | P10: IW | Q10: Bill | R10: 46062 | S10: OK | T10: IW | U10: Bill | V10: 2/12
A11: =ROW()-2 -> 9 | D11: コレクトアイテム使用 | E11: コレクトアイテム使用後に特典が取得できるか | H11: 使用收集道具 | I11: 使用收集道具後是否能取得特典 | K11: CollectionBonus!B5:N | L11: =IFERROR(__xludf.DUMMYFUNCTION("""COMPUTED_VALUE"""),20.0) -> 20 | S11: OK | T11: IW | U11: Bill | V11: 2/12
A12: =ROW()-2 -> 10 | E12: イベント限定アイテムの受取期限がイベント終了日時になっているか | I12: 活動限定道具的領取期限是否為活動結束日期和時間 | J12: 通常は2週間（活動限定：活動結束時間／其餘2週） | K12: CollectionBonus!B5:N | L12: =IFERROR(__xludf.DUMMYFUNCTION("""COMPUTED_VALUE"""),20.0) -> 20 | N12: #VALUE! | S12: OK | T12: IW | U12: Bill | V12: 2/12
A13: =ROW()-2 -> 11 | B13: 30 | C13: コレクションイベント＞該当イベント＞コレクション＞全特典の確認 | D13: 特典一覧 ＞コレクション一覧 | E13: 受け取り文言が右記の通り設定されているか ※受取箱に入れるもののみ確認する | F13: 30 | G13: 收集活動＞該活動＞收集＞確認所有特典 | H13: 特典一覽 ＞收集一覽 | I13: 是否已按照右列內容設定領取文案※僅確認放入領取箱中的項目 | J13: ='参照_各種特典'!D22 -> Mystic Matrimony◆Collection Bonus | K13: CollectionBonus!B5:N | L13: =IFERROR(__xludf.DUMMYFUNCTION("""COMPUTED_VALUE"""),30.0) -> 30 | M13: 4 | N13: Mystic Matrimony◆Collection Bonus | O13: OK | P13: IW | Q13: Bill | R13: 46062
A14: =ROW()-2 -> 12 | E14: 特典アイテムが右記の通り設定されているか | I14: 特典道具是否按右側設定 | J14: ='参照_各種特典'!F22 -> 500 Gold | K14: CollectionBonus!B5:N | L14: =IFERROR(__xludf.DUMMYFUNCTION("""COMPUTED_VALUE"""),30.0) -> 30 | M14: 11 | N14: 500 Gold | O14: OK | P14: IW | Q14: Bill | R14: 46062
A15: =ROW()-2 -> 13 | E15: 個数が左記の通り設定されているか | I15: 個數是否按右側設定 | J15: ='参照_各種特典'!H22 -> 1 | K15: CollectionBonus!B5:N | L15: =IFERROR(__xludf.DUMMYFUNCTION("""COMPUTED_VALUE"""),30.0) -> 30 | M15: 7 | N15: 1 | O15: OK | P15: IW | Q15: Bill | R15: 46062
A16: =ROW()-2 -> 14 | C16: 実機 | E16: 特典サムネイル画像が表示されているか | G16: 實體機台 | I16: 是否顯示特典縮圖 | K16: CollectionBonus!B5:N | L16: =IFERROR(__xludf.DUMMYFUNCTION("""COMPUTED_VALUE"""),30.0) -> 30 | O16: OK | P16: IW | Q16: Bill | R16: 46062 | S16: OK | T16: IW | U16: Bill | V16: 2/12
A17: =ROW()-2 -> 15 | D17: コレクトアイテム使用 | E17: コレクトアイテム使用後に特典が取得できるか | H17: 使用收集道具 | I17: 使用收集道具後是否能取得特典 | K17: CollectionBonus!B5:N | L17: =IFERROR(__xludf.DUMMYFUNCTION("""COMPUTED_VALUE"""),30.0) -> 30 | S17: OK | T17: IW | U17: Bill | V17: 2/12
A18: =ROW()-2 -> 16 | E18: イベント限定アイテムの受取期限がイベント終了日時になっているか | I18: 活動限定道具的領取期限是否為活動結束日期和時間 | J18: 通常は2週間（活動限定：活動結束時間／其餘2週） | K18: CollectionBonus!B5:N | L18: =IFERROR(__xludf.DUMMYFUNCTION("""COMPUTED_VALUE"""),30.0) -> 30 | N18: #VALUE! | S18: OK | T18: IW | U18: Bill | V18: 2/12
A19: =ROW()-2 -> 17 | B19: 40 | C19: コレクションイベント＞該当イベント＞コレクション＞全特典の確認 | D19: 特典一覧 ＞コレクション一覧 | E19: 受け取り文言が右記の通り設定されているか ※受取箱に入れるもののみ確認する | F19: 40 | G19: 收集活動＞該活動＞收集＞確認所有特典 | H19: 特典一覽 ＞收集一覽 | I19: 是否已按照右列內容設定領取文案※僅確認放入領取箱中的項目 | J19: ='参照_各種特典'!D23 -> Mystic Matrimony◆Collection Bonus | K19: CollectionBonus!B5:N | L19: =IFERROR(__xludf.DUMMYFUNCTION("""COMPUTED_VALUE"""),40.0) -> 40 | M19: 4 | N19: Mystic Matrimony◆Collection Bonus | O19: OK | P19: IW | Q19: Bill | R19: 46062
A20: =ROW()-2 -> 18 | E20: 特典アイテムが右記の通り設定されているか | I20: 特典道具是否按右側設定 | J20: ='参照_各種特典'!F23 -> Closet Storage | K20: CollectionBonus!B5:N | L20: =IFERROR(__xludf.DUMMYFUNCTION("""COMPUTED_VALUE"""),40.0) -> 40 | M20: 11 | N20: Closet Storage | O20: OK | P20: IW | Q20: Bill | R20: 46062
A21: =ROW()-2 -> 19 | E21: 個数が左記の通り設定されているか | I21: 個數是否按右側設定 | J21: ='参照_各種特典'!H23 -> 1 | K21: CollectionBonus!B5:N | L21: =IFERROR(__xludf.DUMMYFUNCTION("""COMPUTED_VALUE"""),40.0) -> 40 | M21: 7 | N21: 1 | O21: OK | P21: IW | Q21: Bill | R21: 46062
A22: =ROW()-2 -> 20 | C22: 実機 | E22: 特典サムネイル画像が表示されているか | G22: 實體機台 | I22: 是否顯示特典縮圖 | K22: CollectionBonus!B5:N | L22: =IFERROR(__xludf.DUMMYFUNCTION("""COMPUTED_VALUE"""),40.0) -> 40 | O22: OK | P22: IW | Q22: Bill | R22: 46062 | S22: OK | T22: IW | U22: Bill | V22: 2/12
A23: =ROW()-2 -> 21 | D23: コレクトアイテム使用 | E23: コレクトアイテム使用後に特典が取得できるか | H23: 使用收集道具 | I23: 使用收集道具後是否能取得特典 | K23: CollectionBonus!B5:N | L23: =IFERROR(__xludf.DUMMYFUNCTION("""COMPUTED_VALUE"""),40.0) -> 40 | S23: OK | T23: IW | U23: Bill | V23: 2/12
A24: =ROW()-2 -> 22 | E24: イベント限定アイテムの受取期限がイベント終了日時になっているか | I24: 活動限定道具的領取期限是否為活動結束日期和時間 | J24: 通常は2週間（活動限定：活動結束時間／其餘2週） | K24: CollectionBonus!B5:N | L24: =IFERROR(__xludf.DUMMYFUNCTION("""COMPUTED_VALUE"""),40.0) -> 40 | N24: #VALUE! | S24: OK | T24: IW | U24: Bill | V24: 2/12
A25: =ROW()-2 -> 23 | B25: 50 | C25: コレクションイベント＞該当イベント＞コレクション＞全特典の確認 | D25: 特典一覧 ＞コレクション一覧 | E25: 受け取り文言が右記の通り設定されているか ※受取箱に入れるもののみ確認する | F25: 50 | G25: 收集活動＞該活動＞收集＞確認所有特典 | H25: 特典一覽 ＞收集一覽 | I25: 是否已按照右列內容設定領取文案※僅確認放入領取箱中的項目 | J25: ='参照_各種特典'!D24 -> Mystic Matrimony◆Collection Bonus | K25: CollectionBonus!B5:N | L25: =IFERROR(__xludf.DUMMYFUNCTION("""COMPUTED_VALUE"""),50.0) -> 50 | M25: 4 | N25: Mystic Matrimony◆Collection Bonus | O25: OK | P25: IW | Q25: Bill | R25: 46062
A26: =ROW()-2 -> 24 | E26: 特典アイテムが右記の通り設定されているか | I26: 特典道具是否按右側設定 | J26: ='参照_各種特典'!F24 -> Shaved Ice (+50 Stamina) | K26: CollectionBonus!B5:N | L26: =IFERROR(__xludf.DUMMYFUNCTION("""COMPUTED_VALUE"""),50.0) -> 50 | M26: 11 | N26: Shaved Ice (+50 Stamina) | O26: OK | P26: IW | Q26: Bill | R26: 46062
A27: =ROW()-2 -> 25 | E27: 個数が左記の通り設定されているか | I27: 個數是否按右側設定 | J27: ='参照_各種特典'!H24 -> 1 | K27: CollectionBonus!B5:N | L27: =IFERROR(__xludf.DUMMYFUNCTION("""COMPUTED_VALUE"""),50.0) -> 50 | M27: 7 | N27: 1 | O27: OK | P27: IW | Q27: Bill | R27: 46062
A28: =ROW()-2 -> 26 | C28: 実機 | E28: 特典サムネイル画像が表示されているか | G28: 實體機台 | I28: 是否顯示特典縮圖 | K28: CollectionBonus!B5:N | L28: =IFERROR(__xludf.DUMMYFUNCTION("""COMPUTED_VALUE"""),50.0) -> 50 | O28: OK | P28: IW | Q28: Bill | R28: 46062 | S28: OK | T28: IW | U28: Bill | V28: 2/12
A29: =ROW()-2 -> 27 | D29: コレクトアイテム使用 | E29: コレクトアイテム使用後に特典が取得できるか | H29: 使用收集道具 | I29: 使用收集道具後是否能取得特典 | K29: CollectionBonus!B5:N | L29: =IFERROR(__xludf.DUMMYFUNCTION("""COMPUTED_VALUE"""),50.0) -> 50 | S29: OK | T29: IW | U29: Bill | V29: 2/12
A30: =ROW()-2 -> 28 | E30: イベント限定アイテムの受取期限がイベント終了日時になっているか | I30: 活動限定道具的領取期限是否為活動結束日期和時間 | J30: 通常は2週間（活動限定：活動結束時間／其餘2週） | K30: CollectionBonus!B5:N | L30: =IFERROR(__xludf.DUMMYFUNCTION("""COMPUTED_VALUE"""),50.0) -> 50 | N30: #VALUE! | S30: OK | T30: IW | U30: Bill | V30: 2/12
A31: =ROW()-2 -> 29 | B31: 60 | C31: コレクションイベント＞該当イベント＞コレクション＞全特典の確認 | D31: 特典一覧 ＞コレクション一覧 | E31: 受け取り文言が右記の通り設定されているか ※受取箱に入れるもののみ確認する | F31: 60 | G31: 收集活動＞該活動＞收集＞確認所有特典 | H31: 特典一覽 ＞收集一覽 | I31: 是否已按照右列內容設定領取文案※僅確認放入領取箱中的項目 | J31: ='参照_各種特典'!D25 -> Mystic Matrimony◆Collection Bonus | K31: CollectionBonus!B5:N | L31: =IFERROR(__xludf.DUMMYFUNCTION("""COMPUTED_VALUE"""),60.0) -> 60 | M31: 4 | N31: Mystic Matrimony◆Collection Bonus | O31: OK | P31: IW | Q31: Bill | R31: 46062
A32: =ROW()-2 -> 30 | E32: 特典アイテムが右記の通り設定されているか | I32: 特典道具是否按右側設定 | J32: ='参照_各種特典'!F25 -> Yoshimoto with a Lantern | K32: CollectionBonus!B5:N | L32: =IFERROR(__xludf.DUMMYFUNCTION("""COMPUTED_VALUE"""),60.0) -> 60 | M32: 11 | N32: Yoshimoto with a Lantern | O32: OK | P32: IW | Q32: Bill | R32: 46063
A33: =ROW()-2 -> 31 | E33: 個数が左記の通り設定されているか | G33: 實體機台 | I33: 個數是否按右側設定 | J33: ='参照_各種特典'!H25 -> 1 | K33: CollectionBonus!B5:N | L33: =IFERROR(__xludf.DUMMYFUNCTION("""COMPUTED_VALUE"""),60.0) -> 60 | M33: 7 | N33: 1 | O33: OK | P33: IW | Q33: Bill | R33: 46063
A34: =ROW()-2 -> 32 | C34: 実機 | E34: 特典サムネイル画像が表示されているか | I34: 是否顯示特典縮圖 | K34: CollectionBonus!B5:N | L34: =IFERROR(__xludf.DUMMYFUNCTION("""COMPUTED_VALUE"""),60.0) -> 60 | O34: OK | P34: IW | Q34: Bill | R34: 46062 | S34: OK | T34: IW | U34: Bill | V34: 2/12
A35: =ROW()-2 -> 33 | D35: コレクトアイテム使用 | E35: コレクトアイテム使用後に特典が取得できるか | H35: 使用收集道具 | I35: 使用收集道具後是否能取得特典 | K35: CollectionBonus!B5:N | L35: =IFERROR(__xludf.DUMMYFUNCTION("""COMPUTED_VALUE"""),60.0) -> 60 | S35: OK | T35: IW | U35: Bill | V35: 2/12
A36: =ROW()-2 -> 34 | E36: イベント限定アイテムの受取期限がイベント終了日時になっているか | I36: 活動限定道具的領取期限是否為活動結束日期和時間 | J36: 通常は2週間（活動限定：活動結束時間／其餘2週） | K36: CollectionBonus!B5:N | L36: =IFERROR(__xludf.DUMMYFUNCTION("""COMPUTED_VALUE"""),60.0) -> 60 | N36: #VALUE! | S36: OK | T36: IW | U36: Bill | V36: 2/12
A37: =ROW()-2 -> 35 | B37: 70 | C37: コレクションイベント＞該当イベント＞コレクション＞全特典の確認 | D37: 特典一覧 ＞コレクション一覧 | E37: 受け取り文言が右記の通り設定されているか ※受取箱に入れるもののみ確認する | F37: 70 | G37: 收集活動＞該活動＞收集＞確認所有特典 | H37: 特典一覽 ＞收集一覽 | I37: 是否已按照右列內容設定領取文案※僅確認放入領取箱中的項目 | J37: ='参照_各種特典'!D26 -> Mystic Matrimony◆Collection Bonus | K37: CollectionBonus!B5:N | L37: =IFERROR(__xludf.DUMMYFUNCTION("""COMPUTED_VALUE"""),70.0) -> 70 | M37: 4 | N37: Mystic Matrimony◆Collection Bonus | O37: OK | P37: IW | Q37: Bill | R37: 46062
A38: =ROW()-2 -> 36 | E38: 特典アイテムが右記の通り設定されているか | I38: 特典道具是否按右側設定 | J38: ='参照_各種特典'!F26 -> Shaved Ice (+50 Stamina) | K38: CollectionBonus!B5:N | L38: =IFERROR(__xludf.DUMMYFUNCTION("""COMPUTED_VALUE"""),70.0) -> 70 | M38: 11 | N38: Shaved Ice (+50 Stamina) | O38: OK | P38: IW | Q38: Bill | R38: 46062
A39: =ROW()-2 -> 37 | E39: 個数が左記の通り設定されているか | I39: 個數是否按右側設定 | J39: ='参照_各種特典'!H26 -> 1 | K39: CollectionBonus!B5:N | L39: =IFERROR(__xludf.DUMMYFUNCTION("""COMPUTED_VALUE"""),70.0) -> 70 | M39: 7 | N39: 1 | O39: OK | P39: IW | Q39: Bill | R39: 46062
A40: =ROW()-2 -> 38 | C40: 実機 | E40: 特典サムネイル画像が表示されているか | G40: 實體機台 | I40: 是否顯示特典縮圖 | K40: CollectionBonus!B5:N | L40: =IFERROR(__xludf.DUMMYFUNCTION("""COMPUTED_VALUE"""),70.0) -> 70 | O40: OK | P40: IW | Q40: Bill | R40: 46062 | S40: OK | T40: IW | U40: Bill | V40: 2/12
A41: =ROW()-2 -> 39 | D41: コレクトアイテム使用 | E41: コレクトアイテム使用後に特典が取得できるか | H41: 使用收集道具 | I41: 使用收集道具後是否能取得特典 | K41: CollectionBonus!B5:N | L41: =IFERROR(__xludf.DUMMYFUNCTION("""COMPUTED_VALUE"""),70.0) -> 70 | S41: OK | T41: IW | U41: Bill | V41: 2/12
A42: =ROW()-2 -> 40 | E42: イベント限定アイテムの受取期限がイベント終了日時になっているか | I42: 活動限定道具的領取期限是否為活動結束日期和時間 | J42: 通常は2週間（活動限定：活動結束時間／其餘2週） | K42: CollectionBonus!B5:N | L42: =IFERROR(__xludf.DUMMYFUNCTION("""COMPUTED_VALUE"""),70.0) -> 70 | N42: #VALUE! | S42: OK | T42: IW | U42: Bill | V42: 2/12
A43: =ROW()-2 -> 41 | B43: 80 | C43: コレクションイベント＞該当イベント＞コレクション＞全特典の確認 | D43: 特典一覧 ＞コレクション一覧 | E43: 受け取り文言が右記の通り設定されているか ※受取箱に入れるもののみ確認する | F43: 80 | G43: 收集活動＞該活動＞收集＞確認所有特典 | H43: 特典一覽 ＞收集一覽 | I43: 是否已按照右列內容設定領取文案※僅確認放入領取箱中的項目 | J43: ='参照_各種特典'!D27 -> Mystic Matrimony◆Collection Bonus | K43: CollectionBonus!B5:N | L43: =IFERROR(__xludf.DUMMYFUNCTION("""COMPUTED_VALUE"""),80.0) -> 80 | M43: 4 | N43: Mystic Matrimony◆Collection Bonus | O43: OK | P43: IW | Q43: Bill | R43: 46062
A44: =ROW()-2 -> 42 | E44: 特典アイテムが右記の通り設定されているか | I44: 特典道具是否按右側設定 | J44: ='参照_各種特典'!F27 -> 500 Gold | K44: CollectionBonus!B5:N | L44: =IFERROR(__xludf.DUMMYFUNCTION("""COMPUTED_VALUE"""),80.0) -> 80 | M44: 11 | N44: 500 Gold | O44: OK | P44: IW | Q44: Bill | R44: 46062
A45: =ROW()-2 -> 43 | E45: 個数が左記の通り設定されているか | I45: 個數是否按右側設定 | J45: ='参照_各種特典'!H27 -> 1 | K45: CollectionBonus!B5:N | L45: =IFERROR(__xludf.DUMMYFUNCTION("""COMPUTED_VALUE"""),80.0) -> 80 | M45: 7 | N45: 1 | O45: OK | P45: IW | Q45: Bill | R45: 46062
A46: =ROW()-2 -> 44 | C46: 実機 | E46: 特典サムネイル画像が表示されているか | G46: 實體機台 | I46: 是否顯示特典縮圖 | K46: CollectionBonus!B5:N | L46: =IFERROR(__xludf.DUMMYFUNCTION("""COMPUTED_VALUE"""),80.0) -> 80 | O46: OK | P46: IW | Q46: Bill | R46: 46062 | S46: OK | T46: IW | U46: Bill | V46: 2/12
A47: =ROW()-2 -> 45 | D47: コレクトアイテム使用 | E47: コレクトアイテム使用後に特典が取得できるか | H47: 使用收集道具 | I47: 使用收集道具後是否能取得特典 | K47: CollectionBonus!B5:N | L47: =IFERROR(__xludf.DUMMYFUNCTION("""COMPUTED_VALUE"""),80.0) -> 80 | S47: OK | T47: IW | U47: Bill | V47: 2/12
A48: =ROW()-2 -> 46 | E48: イベント限定アイテムの受取期限がイベント終了日時になっているか | I48: 活動限定道具的領取期限是否為活動結束日期和時間 | J48: 通常は2週間（活動限定：活動結束時間／其餘2週） | K48: CollectionBonus!B5:N | L48: =IFERROR(__xludf.DUMMYFUNCTION("""COMPUTED_VALUE"""),80.0) -> 80 | N48: #VALUE! | S48: OK | T48: IW | U48: Bill | V48: 2/12
A49: =ROW()-2 -> 47 | B49: 90 | C49: コレクションイベント＞該当イベント＞コレクション＞全特典の確認 | D49: 特典一覧 ＞コレクション一覧 | E49: 受け取り文言が右記の通り設定されているか ※受取箱に入れるもののみ確認する | F49: 90 | G49: 收集活動＞該活動＞收集＞確認所有特典 | H49: 特典一覽 ＞收集一覽 | I49: 是否已按照右列內容設定領取文案※僅確認放入領取箱中的項目 | J49: ='参照_各種特典'!D28 -> Mystic Matrimony◆Collection Bonus | K49: CollectionBonus!B5:N | L49: =IFERROR(__xludf.DUMMYFUNCTION("""COMPUTED_VALUE"""),90.0) -> 90 | M49: 4 | N49: Mystic Matrimony◆Collection Bonus | O49: OK | P49: IW | Q49: Bill | R49: 46062
A50: =ROW()-2 -> 48 | E50: 特典アイテムが右記の通り設定されているか | I50: 特典道具是否按右側設定 | J50: ='参照_各種特典'!F28 -> Shaved Ice (+50 Stamina) | K50: CollectionBonus!B5:N | L50: =IFERROR(__xludf.DUMMYFUNCTION("""COMPUTED_VALUE"""),90.0) -> 90 | M50: 11 | N50: Shaved Ice (+50 Stamina) | O50: OK | P50: IW | Q50: Bill | R50: 46062
A51: =ROW()-2 -> 49 | E51: 個数が左記の通り設定されているか | I51: 個數是否按右側設定 | J51: ='参照_各種特典'!H28 -> 1 | K51: CollectionBonus!B5:N | L51: =IFERROR(__xludf.DUMMYFUNCTION("""COMPUTED_VALUE"""),90.0) -> 90 | M51: 7 | N51: 1 | O51: OK | P51: IW | Q51: Bill | R51: 46062
A52: =ROW()-2 -> 50 | C52: 実機 | E52: 特典サムネイル画像が表示されているか | G52: 實體機台 | I52: 是否顯示特典縮圖 | K52: CollectionBonus!B5:N | L52: =IFERROR(__xludf.DUMMYFUNCTION("""COMPUTED_VALUE"""),90.0) -> 90 | O52: OK | P52: IW | Q52: Bill | R52: 46062 | S52: OK | T52: IW | U52: Bill | V52: 2/12
A53: =ROW()-2 -> 51 | D53: コレクトアイテム使用 | E53: コレクトアイテム使用後に特典が取得できるか | H53: 使用收集道具 | I53: 使用收集道具後是否能取得特典 | K53: CollectionBonus!B5:N | L53: =IFERROR(__xludf.DUMMYFUNCTION("""COMPUTED_VALUE"""),90.0) -> 90 | S53: OK | T53: IW | U53: Bill | V53: 2/12
A54: =ROW()-2 -> 52 | E54: イベント限定アイテムの受取期限がイベント終了日時になっているか | I54: 活動限定道具的領取期限是否為活動結束日期和時間 | J54: 通常は2週間（活動限定：活動結束時間／其餘2週） | K54: CollectionBonus!B5:N | L54: =IFERROR(__xludf.DUMMYFUNCTION("""COMPUTED_VALUE"""),90.0) -> 90 | N54: #VALUE! | S54: OK | T54: IW | U54: Bill | V54: 2/12
A55: =ROW()-2 -> 53 | B55: 100 | C55: コレクションイベント＞該当イベント＞コレクション＞全特典の確認 | D55: 特典一覧 ＞コレクション一覧 | E55: 特典アイテムが右記の通り設定されているか | F55: 100 | G55: 收集活動＞該活動＞收集＞確認所有特典 | H55: 特典一覽 ＞收集一覽 | I55: 特典道具是否按右側設定 | J55: ='参照_各種特典'!F29 -> Mystic Matrimony Bonus Story ～Yoshimoto～ | K55: CollectionBonus!B5:N | L55: =IFERROR(__xludf.DUMMYFUNCTION("""COMPUTED_VALUE"""),100.0) -> 100 | M55: 11 | N55: Mystic Matrimony Bonus Story ～Yoshimoto～ | O55: OK | P55: IW | Q55: Bill | R55: 46062
A56: =ROW()-2 -> 54 | C56: 実機 | E56: 特典サムネイル画像が表示されているか | G56: 實體機台 | I56: 是否顯示特典縮圖 | K56: CollectionBonus!B5:N | L56: =IFERROR(__xludf.DUMMYFUNCTION("""COMPUTED_VALUE"""),100.0) -> 100 | O56: OK | P56: IW | Q56: Bill | R56: 46062 | S56: OK | T56: IW | U56: Bill | V56: 2/12
A57: =ROW()-2 -> 55 | D57: コレクトアイテム使用 | E57: コレクトアイテム使用後に特典が取得できるか | H57: 使用收集道具 | I57: 使用收集道具後是否能取得特典 | J57: 通常は2週間（活動限定：活動結束時間／其餘2週） | K57: CollectionBonus!B5:N | L57: =IFERROR(__xludf.DUMMYFUNCTION("""COMPUTED_VALUE"""),100.0) -> 100 | N57: #VALUE! | S57: OK | T57: IW | U57: Bill | V57: 2/12
A58: =ROW()-2 -> 56 | B58: 110 | C58: コレクションイベント＞該当イベント＞コレクション＞全特典の確認 | D58: 特典一覧 ＞コレクション一覧 | E58: 受け取り文言が右記の通り設定されているか ※受取箱に入れるもののみ確認する | F58: 110 | G58: 收集活動＞該活動＞收集＞確認所有特典 | H58: 特典一覽 ＞收集一覽 | I58: 是否已按照右列內容設定領取文案※僅確認放入領取箱中的項目 | J58: ='参照_各種特典'!D30 -> Mystic Matrimony◆Collection Bonus | K58: CollectionBonus!B5:N | L58: =IFERROR(__xludf.DUMMYFUNCTION("""COMPUTED_VALUE"""),110.0) -> 110 | M58: 4 | N58: Mystic Matrimony◆Collection Bonus | O58: OK | P58: IW | Q58: Bill | R58: 46062
E59: 特典アイテムが右記の通り設定されているか | I59: 特典道具是否按右側設定 | J59: ='参照_各種特典'!F30 -> Makeup (+100 Glamour) | K59: CollectionBonus!B5:N | L59: =IFERROR(__xludf.DUMMYFUNCTION("""COMPUTED_VALUE"""),110.0) -> 110 | M59: 11 | N59: Makeup (+100 Glamour) | O59: OK | P59: IW | Q59: Bill | R59: 46062
E60: 個数が左記の通り設定されているか | I60: 個數是否按右側設定 | J60: ='参照_各種特典'!H30 -> 1 | K60: CollectionBonus!B5:N | L60: =IFERROR(__xludf.DUMMYFUNCTION("""COMPUTED_VALUE"""),110.0) -> 110 | M60: 7 | N60: 1 | O60: OK | P60: IW | Q60: Bill | R60: 46062
A61: =ROW()-2 -> 59 | C61: 実機 | E61: 特典サムネイル画像が表示されているか | G61: 實體機台 | I61: 是否顯示特典縮圖 | K61: CollectionBonus!B5:N | L61: =IFERROR(__xludf.DUMMYFUNCTION("""COMPUTED_VALUE"""),110.0) -> 110 | O61: OK | P61: IW | Q61: Bill | R61: 46062 | S61: OK | T61: IW | U61: Bill | V61: 2/12
D62: コレクトアイテム使用 | E62: コレクトアイテム使用後に特典が取得できるか | H62: 使用收集道具 | I62: 使用收集道具後是否能取得特典 | K62: CollectionBonus!B5:N | L62: =IFERROR(__xludf.DUMMYFUNCTION("""COMPUTED_VALUE"""),110.0) -> 110 | S62: OK | T62: IW | U62: Bill | V62: 2/12
A63: =ROW()-2 -> 61 | E63: イベント限定アイテムの受取期限がイベント終了日時になっているか | I63: 活動限定道具的領取期限是否為活動結束日期和時間 | J63: 通常は2週間（活動限定：活動結束時間／其餘2週） | K63: CollectionBonus!B5:N | L63: =IFERROR(__xludf.DUMMYFUNCTION("""COMPUTED_VALUE"""),110.0) -> 110 | N63: #VALUE! | S63: OK | T63: IW | U63: Bill | V63: 2/12
A64: =ROW()-2 -> 62 | B64: 120 | C64: コレクションイベント＞該当イベント＞コレクション＞全特典の確認 | D64: 特典一覧 ＞コレクション一覧 | E64: 受け取り文言が右記の通り設定されているか ※受取箱に入れるもののみ確認する | F64: 120 | G64: 收集活動＞該活動＞收集＞確認所有特典 | H64: 特典一覽 ＞收集一覽 | I64: 是否已按照右列內容設定領取文案※僅確認放入領取箱中的項目 | J64: ='参照_各種特典'!D31 -> Mystic Matrimony◆Collection Bonus | K64: CollectionBonus!B5:N | L64: =IFERROR(__xludf.DUMMYFUNCTION("""COMPUTED_VALUE"""),120.0) -> 120 | M64: 4 | N64: Mystic Matrimony◆Collection Bonus | O64: OK | P64: IW | Q64: Bill | R64: 46062
A65: =ROW()-2 -> 63 | E65: 特典アイテムが右記の通り設定されているか | I65: 特典道具是否按右側設定 | J65: ='参照_各種特典'!F31 -> Castle Storage | K65: CollectionBonus!B5:N | L65: =IFERROR(__xludf.DUMMYFUNCTION("""COMPUTED_VALUE"""),120.0) -> 120 | M65: 11 | N65: Castle Storage | O65: OK | P65: IW | Q65: Bill | R65: 46062
A66: =ROW()-2 -> 64 | E66: 個数が左記の通り設定されているか | I66: 個數是否按右側設定 | J66: ='参照_各種特典'!H31 -> 1 | K66: CollectionBonus!B5:N | L66: =IFERROR(__xludf.DUMMYFUNCTION("""COMPUTED_VALUE"""),120.0) -> 120 | M66: 7 | N66: 1 | O66: OK | P66: IW | Q66: Bill | R66: 46062
A67: =ROW()-2 -> 65 | C67: 実機 | E67: 特典サムネイル画像が表示されているか | G67: 實體機台 | I67: 是否顯示特典縮圖 | K67: CollectionBonus!B5:N | L67: =IFERROR(__xludf.DUMMYFUNCTION("""COMPUTED_VALUE"""),120.0) -> 120 | O67: OK | P67: IW | Q67: Bill | R67: 46062 | S67: OK | T67: IW | U67: Bill | V67: 2/12
A68: =ROW()-2 -> 66 | D68: コレクトアイテム使用 | E68: コレクトアイテム使用後に特典が取得できるか | H68: 使用收集道具 | I68: 使用收集道具後是否能取得特典 | K68: CollectionBonus!B5:N | L68: =IFERROR(__xludf.DUMMYFUNCTION("""COMPUTED_VALUE"""),120.0) -> 120 | S68: OK | T68: IW | U68: Bill | V68: 2/12
A69: =ROW()-2 -> 67 | E69: イベント限定アイテムの受取期限がイベント終了日時になっているか | I69: 活動限定道具的領取期限是否為活動結束日期和時間 | J69: 通常は2週間（活動限定：活動結束時間／其餘2週） | K69: CollectionBonus!B5:N | L69: =IFERROR(__xludf.DUMMYFUNCTION("""COMPUTED_VALUE"""),120.0) -> 120 | N69: #VALUE! | S69: OK | T69: IW | U69: Bill | V69: 2/12
B70: 130 | C70: コレクションイベント＞該当イベント＞コレクション＞全特典の確認 | D70: 特典一覧 ＞コレクション一覧 | E70: 受け取り文言が右記の通り設定されているか ※受取箱に入れるもののみ確認する | F70: 130 | G70: 收集活動＞該活動＞收集＞確認所有特典 | H70: 特典一覽 ＞收集一覽 | I70: 是否已按照右列內容設定領取文案※僅確認放入領取箱中的項目 | J70: ='参照_各種特典'!D32 -> Mystic Matrimony◆Collection Bonus | K70: CollectionBonus!B5:N | L70: =IFERROR(__xludf.DUMMYFUNCTION("""COMPUTED_VALUE"""),130.0) -> 130 | M70: 4 | N70: Mystic Matrimony◆Collection Bonus | O70: OK | P70: IW | Q70: Bill | R70: 46062
A71: =ROW()-2 -> 69 | E71: 特典アイテムが右記の通り設定されているか | I71: 特典道具是否按右側設定 | J71: ='参照_各種特典'!F32 -> Shaved Ice (+50 Stamina) | K71: CollectionBonus!B5:N | L71: =IFERROR(__xludf.DUMMYFUNCTION("""COMPUTED_VALUE"""),130.0) -> 130 | M71: 11 | N71: Shaved Ice (+50 Stamina) | O71: OK | P71: IW | Q71: Bill | R71: 46062
E72: 個数が左記の通り設定されているか | I72: 個數是否按右側設定 | J72: ='参照_各種特典'!H32 -> 1 | K72: CollectionBonus!B5:N | L72: =IFERROR(__xludf.DUMMYFUNCTION("""COMPUTED_VALUE"""),130.0) -> 130 | M72: 7 | N72: 1 | O72: OK | P72: IW | Q72: Bill | R72: 46062
A73: =ROW()-2 -> 71 | C73: 実機 | E73: 特典サムネイル画像が表示されているか | G73: 實體機台 | I73: 是否顯示特典縮圖 | K73: CollectionBonus!B5:N | L73: =IFERROR(__xludf.DUMMYFUNCTION("""COMPUTED_VALUE"""),130.0) -> 130 | O73: OK | P73: IW | Q73: Bill | R73: 46062 | S73: OK | T73: IW | U73: Bill | V73: 2/12
A74: =ROW()-2 -> 72 | D74: コレクトアイテム使用 | E74: コレクトアイテム使用後に特典が取得できるか | H74: 使用收集道具 | I74: 使用收集道具後是否能取得特典 | K74: CollectionBonus!B5:N | L74: =IFERROR(__xludf.DUMMYFUNCTION("""COMPUTED_VALUE"""),130.0) -> 130 | S74: OK | T74: IW | U74: Bill | V74: 2/12
E75: イベント限定アイテムの受取期限がイベント終了日時になっているか | I75: 活動限定道具的領取期限是否為活動結束日期和時間 | J75: 通常は2週間（活動限定：活動結束時間／其餘2週） | K75: CollectionBonus!B5:N | L75: =IFERROR(__xludf.DUMMYFUNCTION("""COMPUTED_VALUE"""),130.0) -> 130 | N75: #VALUE! | S75: OK | T75: IW | U75: Bill | V75: 2/12
A76: =ROW()-2 -> 74 | B76: 140 | C76: コレクションイベント＞該当イベント＞コレクション＞全特典の確認 | D76: 特典一覧 ＞コレクション一覧 | E76: 受け取り文言が右記の通り設定されているか ※受取箱に入れるもののみ確認する | F76: 140 | G76: 收集活動＞該活動＞收集＞確認所有特典 | H76: 特典一覽 ＞收集一覽 | I76: 是否已按照右列內容設定領取文案※僅確認放入領取箱中的項目 | J76: ='参照_各種特典'!D33 -> Mystic Matrimony◆Collection Bonus | K76: CollectionBonus!B5:N | L76: =IFERROR(__xludf.DUMMYFUNCTION("""COMPUTED_VALUE"""),140.0) -> 140 | M76: 4 | N76: Mystic Matrimony◆Collection Bonus | O76: OK | P76: IW | Q76: Bill | R76: 46062
A77: =ROW()-2 -> 75 | E77: 特典アイテムが右記の通り設定されているか | I77: 特典道具是否按右側設定 | J77: ='参照_各種特典'!F33 -> Motonari with a Lantern | K77: CollectionBonus!B5:N | L77: =IFERROR(__xludf.DUMMYFUNCTION("""COMPUTED_VALUE"""),140.0) -> 140 | M77: 11 | N77: Motonari with a Lantern | O77: OK | P77: IW | Q77: Bill | R77: 46062
A78: =ROW()-2 -> 76 | E78: 個数が左記の通り設定されているか | I78: 個數是否按右側設定 | J78: ='参照_各種特典'!H33 -> 1 | K78: CollectionBonus!B5:N | L78: =IFERROR(__xludf.DUMMYFUNCTION("""COMPUTED_VALUE"""),140.0) -> 140 | M78: 7 | N78: 1 | O78: OK | P78: IW | Q78: Bill | R78: 46062
A79: =ROW()-2 -> 77 | C79: 実機 | E79: 特典サムネイル画像が表示されているか | G79: 實體機台 | I79: 是否顯示特典縮圖 | K79: CollectionBonus!B5:N | L79: =IFERROR(__xludf.DUMMYFUNCTION("""COMPUTED_VALUE"""),140.0) -> 140 | O79: OK | P79: IW | Q79: Bill | R79: 46062 | S79: OK | T79: IW | U79: Bill | V79: 2/12
A80: =ROW()-2 -> 78 | D80: コレクトアイテム使用 | E80: コレクトアイテム使用後に特典が取得できるか | H80: 使用收集道具 | I80: 使用收集道具後是否能取得特典 | K80: CollectionBonus!B5:N | L80: =IFERROR(__xludf.DUMMYFUNCTION("""COMPUTED_VALUE"""),140.0) -> 140 | S80: OK | T80: IW | U80: Bill | V80: 2/12
A81: =ROW()-2 -> 79 | E81: イベント限定アイテムの受取期限がイベント終了日時になっているか | I81: 活動限定道具的領取期限是否為活動結束日期和時間 | J81: 通常は2週間（活動限定：活動結束時間／其餘2週） | K81: CollectionBonus!B5:N | L81: =IFERROR(__xludf.DUMMYFUNCTION("""COMPUTED_VALUE"""),140.0) -> 140 | N81: #VALUE! | S81: OK | T81: IW | U81: Bill | V81: 2/12
A82: =ROW()-2 -> 80 | E82: コレクトアイテム使用後に特典が取得できるか | I82: 使用收集道具後是否能取得特典 | J82: ='参照_各種特典'!F12 -> Blue Anemone Hair Clip | K82: CollectionBonus!B5:N | L82: =IFERROR(__xludf.DUMMYFUNCTION("""COMPUTED_VALUE"""),140.0) -> 140 | N82: #VALUE! | S82: OK | T82: IW | U82: Bill | V82: 2/12
A83: =ROW()-2 -> 81 | B83: 150 | C83: コレクションイベント＞該当イベント＞コレクション＞全特典の確認 | D83: 特典一覧 ＞コレクション一覧 | E83: 受け取り文言が右記の通り設定されているか ※受取箱に入れるもののみ確認する | F83: 150 | G83: 收集活動＞該活動＞收集＞確認所有特典 | H83: 特典一覽 ＞收集一覽 | I83: 是否已按照右列內容設定領取文案※僅確認放入領取箱中的項目 | J83: ='参照_各種特典'!D34 -> Mystic Matrimony◆Collection Bonus | K83: CollectionBonus!B5:N | L83: =IFERROR(__xludf.DUMMYFUNCTION("""COMPUTED_VALUE"""),150.0) -> 150 | M83: 4 | N83: Mystic Matrimony◆Collection Bonus | O83: OK | P83: IW | Q83: Bill | R83: 46062
E84: 特典アイテムが右記の通り設定されているか | I84: 特典道具是否按右側設定 | J84: ='参照_各種特典'!F34 -> 500 Gold | K84: CollectionBonus!B5:N | L84: =IFERROR(__xludf.DUMMYFUNCTION("""COMPUTED_VALUE"""),150.0) -> 150 | M84: 11 | N84: 500 Gold | O84: OK | P84: IW | Q84: Bill | R84: 46062
E85: 個数が左記の通り設定されているか | I85: 個數是否按右側設定 | J85: ='参照_各種特典'!H34 -> 1 | K85: CollectionBonus!B5:N | L85: =IFERROR(__xludf.DUMMYFUNCTION("""COMPUTED_VALUE"""),150.0) -> 150 | M85: 7 | N85: 1 | O85: OK | P85: IW | Q85: Bill | R85: 46062
A86: =ROW()-2 -> 84 | C86: 実機 | E86: 特典サムネイル画像が表示されているか | G86: 實體機台 | I86: 是否顯示特典縮圖 | K86: CollectionBonus!B5:N | L86: =IFERROR(__xludf.DUMMYFUNCTION("""COMPUTED_VALUE"""),150.0) -> 150 | O86: OK | P86: IW | Q86: Bill | R86: 46062 | S86: OK | T86: IW | U86: Bill | V86: 2/12
D87: コレクトアイテム使用 | E87: コレクトアイテム使用後に特典が取得できるか | H87: 使用收集道具 | I87: 使用收集道具後是否能取得特典 | K87: CollectionBonus!B5:N | L87: =IFERROR(__xludf.DUMMYFUNCTION("""COMPUTED_VALUE"""),150.0) -> 150 | S87: OK | T87: IW | U87: Bill | V87: 2/12
A88: =ROW()-2 -> 86 | E88: イベント限定アイテムの受取期限がイベント終了日時になっているか | I88: 活動限定道具的領取期限是否為活動結束日期和時間 | J88: 通常は2週間（活動限定：活動結束時間／其餘2週） | K88: CollectionBonus!B5:N | L88: =IFERROR(__xludf.DUMMYFUNCTION("""COMPUTED_VALUE"""),150.0) -> 150 | N88: #VALUE! | S88: OK | T88: IW | U88: Bill | V88: 2/12
A89: =ROW()-2 -> 87 | B89: 160 | C89: コレクションイベント＞該当イベント＞コレクション＞全特典の確認 | D89: 特典一覧 ＞コレクション一覧 | E89: 受け取り文言が右記の通り設定されているか ※受取箱に入れるもののみ確認する | F89: 160 | G89: 收集活動＞該活動＞收集＞確認所有特典 | H89: 特典一覽 ＞收集一覽 | I89: 是否已按照右列內容設定領取文案※僅確認放入領取箱中的項目 | J89: ='参照_各種特典'!D35 -> Mystic Matrimony◆Collection Bonus | K89: CollectionBonus!B5:N | L89: =IFERROR(__xludf.DUMMYFUNCTION("""COMPUTED_VALUE"""),160.0) -> 160 | M89: 4 | N89: Mystic Matrimony◆Collection Bonus | O89: OK | P89: IW | Q89: Bill | R89: 46062
A90: =ROW()-2 -> 88 | E90: 特典アイテムが右記の通り設定されているか | I90: 特典道具是否按右側設定 | J90: ='参照_各種特典'!F35 -> Closet Storage | K90: CollectionBonus!B5:N | L90: =IFERROR(__xludf.DUMMYFUNCTION("""COMPUTED_VALUE"""),160.0) -> 160 | M90: 11 | N90: Closet Storage | O90: OK | P90: IW | Q90: Bill | R90: 46062
A91: =ROW()-2 -> 89 | E91: 個数が左記の通り設定されているか | I91: 個數是否按右側設定 | J91: ='参照_各種特典'!H35 -> 1 | K91: CollectionBonus!B5:N | L91: =IFERROR(__xludf.DUMMYFUNCTION("""COMPUTED_VALUE"""),160.0) -> 160 | M91: 7 | N91: 1 | O91: OK | P91: IW | Q91: Bill | R91: 46062
A92: =ROW()-2 -> 90 | C92: 実機 | E92: 特典サムネイル画像が表示されているか | G92: 實體機台 | I92: 是否顯示特典縮圖 | K92: CollectionBonus!B5:N | L92: =IFERROR(__xludf.DUMMYFUNCTION("""COMPUTED_VALUE"""),160.0) -> 160 | O92: OK | P92: IW | Q92: Bill | R92: 46062 | S92: OK | T92: IW | U92: Bill | V92: 2/12
A93: =ROW()-2 -> 91 | D93: コレクトアイテム使用 | E93: コレクトアイテム使用後に特典が取得できるか | H93: 使用收集道具 | I93: 使用收集道具後是否能取得特典 | K93: CollectionBonus!B5:N | L93: =IFERROR(__xludf.DUMMYFUNCTION("""COMPUTED_VALUE"""),160.0) -> 160 | S93: OK | T93: IW | U93: Bill | V93: 2/12
A94: =ROW()-2 -> 92 | E94: イベント限定アイテムの受取期限がイベント終了日時になっているか | I94: 活動限定道具的領取期限是否為活動結束日期和時間 | J94: 通常は2週間（活動限定：活動結束時間／其餘2週） | K94: CollectionBonus!B5:N | L94: =IFERROR(__xludf.DUMMYFUNCTION("""COMPUTED_VALUE"""),160.0) -> 160 | N94: #VALUE! | S94: OK | T94: IW | U94: Bill | V94: 2/12
A95: =ROW()-2 -> 93 | B95: 170 | C95: コレクションイベント＞該当イベント＞コレクション＞全特典の確認 | D95: 特典一覧 ＞コレクション一覧 | E95: 受け取り文言が右記の通り設定されているか ※受取箱に入れるもののみ確認する | F95: 170 | G95: 收集活動＞該活動＞收集＞確認所有特典 | H95: 特典一覽 ＞收集一覽 | I95: 是否已按照右列內容設定領取文案※僅確認放入領取箱中的項目 | J95: ='参照_各種特典'!D36 -> Mystic Matrimony◆Collection Bonus | K95: CollectionBonus!B5:N | L95: =IFERROR(__xludf.DUMMYFUNCTION("""COMPUTED_VALUE"""),170.0) -> 170 | M95: 4 | N95: Mystic Matrimony◆Collection Bonus | O95: OK | P95: IW | Q95: Bill | R95: 46062
A96: =ROW()-2 -> 94 | E96: 特典アイテムが右記の通り設定されているか | I96: 特典道具是否按右側設定 | J96: ='参照_各種特典'!F36 -> Shaved Ice (+50 Stamina) | K96: CollectionBonus!B5:N | L96: =IFERROR(__xludf.DUMMYFUNCTION("""COMPUTED_VALUE"""),170.0) -> 170 | M96: 11 | N96: Shaved Ice (+50 Stamina) | O96: OK | P96: IW | Q96: Bill | R96: 46062
A97: =ROW()-2 -> 95 | E97: 個数が左記の通り設定されているか | I97: 個數是否按右側設定 | J97: ='参照_各種特典'!H36 -> 1 | K97: CollectionBonus!B5:N | L97: =IFERROR(__xludf.DUMMYFUNCTION("""COMPUTED_VALUE"""),170.0) -> 170 | M97: 7 | N97: 1 | O97: OK | P97: IW | Q97: Bill | R97: 46062
A98: =ROW()-2 -> 96 | C98: 実機 | E98: 特典サムネイル画像が表示されているか | G98: 實體機台 | I98: 是否顯示特典縮圖 | K98: CollectionBonus!B5:N | L98: =IFERROR(__xludf.DUMMYFUNCTION("""COMPUTED_VALUE"""),170.0) -> 170 | O98: OK | P98: IW | Q98: Bill | R98: 46062 | S98: OK | T98: IW | U98: Bill | V98: 2/12
A99: =ROW()-2 -> 97 | D99: コレクトアイテム使用 | E99: コレクトアイテム使用後に特典が取得できるか | H99: 使用收集道具 | I99: 使用收集道具後是否能取得特典 | K99: CollectionBonus!B5:N | L99: =IFERROR(__xludf.DUMMYFUNCTION("""COMPUTED_VALUE"""),170.0) -> 170 | S99: OK | T99: IW | U99: Bill | V99: 2/12
A100: =ROW()-2 -> 98 | E100: イベント限定アイテムの受取期限がイベント終了日時になっているか | I100: 活動限定道具的領取期限是否為活動結束日期和時間 | J100: 通常は2週間（活動限定：活動結束時間／其餘2週） | K100: CollectionBonus!B5:N | L100: =IFERROR(__xludf.DUMMYFUNCTION("""COMPUTED_VALUE"""),170.0) -> 170 | N100: #VALUE! | S100: OK | T100: IW | U100: Bill | V100: 2/12
...

Sheet collect_event_story
A1: https://common-legacy-app-admin.us.ikemen-sengoku.jp/admin/collection/collect_event_story/collect_203
A5: ID | B5: タイトル | C5: 画像 | D5: チケット | E5: ストーリー 請求画像 | F5: 説明 | G5: 編集 | H5: 本番反映
A6: 2064 | B6: Mystic Matrimony ~My Fated Bride~ | D6: 恋遊戯『戦国妖絵巻』
A7: 2065 | B7: Mystic Matrimony ~My Fated Bride~ | D7: 恋遊戯『特別ストーリー』
A8: 2066 | B8: Mystic Matrimony ~My Fated Bride~ | D8: 恋遊戯『特別ストーリー』
A9: 2067 | B9: Mystic Matrimony ~My Fated Bride~ | D9: 恋遊戯『特別ストーリー』
A10: 2068 | B10: Mystic Matrimony ~My Fated Bride~ | D10: 恋遊戯『特別ストーリー』
A11: 2069 | B11: Mystic Matrimony ~My Fated Bride~ | D11: 恋遊戯『特別ストーリー』
A12: 2070 | B12: Mystic Matrimony ~My Fated Bride~ | D12: 恋遊戯『特別ストーリー』
A13: 2071 | B13: Mystic Matrimony ~My Fated Bride~ | D13: 恋遊戯『アフターストーリー』
A14: 2072 | B14: Mystic Matrimony ~My Fated Bride~ | D14: 恋遊戯『アフターストーリー』
A15: 2073 | B15: Mystic Matrimony ~My Fated Bride~ | D15: 恋遊戯『アフターストーリー』
A16: 2074 | B16: Mystic Matrimony ~My Fated Bride~ | D16: 恋遊戯『アフターストーリー』
A17: 2075 | B17: Mystic Matrimony ~My Fated Bride~ | D17: 恋遊戯『アフターストーリー』
A18: 2076 | B18: Mystic Matrimony ~My Fated Bride~ | D18: 恋遊戯『アフターストーリー』

Sheet present
A1: https://common-legacy-app-admin.us.ikemen-sengoku.jp/admin/present/list?item_name=Mystic+Matrimony
A4: {=SEQUENCE(1,COLUMNS(A:J))} -> 1 | B4: 2 | C4: 3 | D4: 4 | E4: 5 | F4: 6 | G4: 7 | H4: 8 | I4: 9 | J4: 10
A5: ID | B5: アイテム | C5: 個数 | D5: 説明 | E5: イベント名 | F5: 開始 | G5: 終了 | H5: 本番反映 | I5: 他PF反映 | J5: 削除
A6: 171906 | B6: Mystic Matrimony Yoshimoto | C6: 1 | D6: Mystic Matrimony Special Collection Bonus | E6: *** | F6: 46074.708 | G6: 無期限
A7: 171909 | B7: Mystic Matrimony Motonari | C7: 1 | D7: Mystic Matrimony Special Collection Bonus | E7: *** | F7: 46074.708 | G7: 無期限
A8: 171912 | B8: Mystic Matrimony Kicho | C8: 1 | D8: Mystic Matrimony Special Collection Bonus | E8: *** | F8: 46074.708 | G8: 無期限
A9: 171914 | B9: Mystic Matrimony Kanetsugu | C9: 1 | D9: Mystic Matrimony Special Collection Bonus | E9: *** | F9: 46074.708 | G9: 無期限
A10: 171916 | B10: Mystic Matrimony Nobunaga | C10: 1 | D10: Mystic Matrimony Special Collection Bonus | E10: *** | F10: 46074.708 | G10: 無期限
A11: 171918 | B11: Mystic Matrimony Masamune | C11: 1 | D11: Mystic Matrimony Special Collection Bonus | E11: *** | F11: 46074.708 | G11: 無期限
A12: 171923 | B12: Mystic Matrimony Top Ranker Placard | C12: 1 | D12: Mystic Matrimony Ranking Bonus | E12: *** | F12: 46074.708 | G12: 無期限
A13: 171980 | B13: Mystic Matrimony Trophy | C13: 1 | D13: Mystic Matrimony◆Collection Bonus | E13: *** | F13: 46074.708 | G13: 無期限

Sheet CollectionBonus
B1: https://common-legacy-app-admin.us.ikemen-sengoku.jp/admin/isgame/collection/all_setting/203#event_collection_bonus_mst
B2: https://common-legacy-app-admin.us.ikemen-sengoku.jp/admin/collection/collect_event_collection_bonus/ce_214_collect_bonus_group
B3: {=SEQUENCE(1,COLUMNS(B:N))} -> 1 | C3: 2 | D3: 3 | E3: 4 | F3: 5 | G3: 6 | H3: 7 | I3: 8 | J3: 9 | K3: 10 | L3: 11 | M3: 12 | N3: 13
A4: ID | B4: collect item get count | C4: present | D4: present ID | E4: present Name | F4: present Item with Count | G4: present Item | H4: present Item Count | I4: special story | J4: special story ID | K4: special story Name | L4: Combine Present Name with Story Name | M4: still | N4: update
A5: 11221 | B5: 10 | D5: =IFERROR(__xludf.DUMMYFUNCTION("ARRAYFORMULA(IF(ISTEXT(C5:C61),SPLIT(C5:C61,""▸〈〉""),))"),"") | G5: {=if(ISTEXT(F5:F61), LEFT(F5:F61,LEN(F5:F61)-4), )} | H5: {=if(ISTEXT(F5:F61), RIGHT(F5:F61,1), )} | I5: 6313▸Demon of My Dreams | J5: =IFERROR(__xludf.DUMMYFUNCTION("ARRAYFORMULA(IF(ISTEXT(I5:I61),SPLIT(I5:I61,""▸〈〉""),))"),6313.0) -> 6313 | K5: =IFERROR(__xludf.DUMMYFUNCTION("""COMPUTED_VALUE"""),"Demon of My Dreams") -> Demon of My Dreams | L5: {=IF(ISBLANK(G5:G61),K5:K61,G5:G61)} -> Demon of My Dreams | N5: 46058.274
A6: 11222 | B6: 20 | C6: 171932▸Mystic Matrimony◆Collection Bonus〈Shaved Ice (+50 Stamina) x 1〉 | D6: =IFERROR(__xludf.DUMMYFUNCTION("""COMPUTED_VALUE"""),171932.0) -> 171932 | E6: =IFERROR(__xludf.DUMMYFUNCTION("""COMPUTED_VALUE"""),"Mystic Matrimony◆Collection Bonus") -> Mystic Matrimony◆Collection Bonus | F6: =IFERROR(__xludf.DUMMYFUNCTION("""COMPUTED_VALUE"""),"Shaved Ice (+50 Stamina) x 1") -> Shaved Ice (+50 Stamina) x 1 | G6: Shaved Ice (+50 Stamina) | H6: 1 | L6: Shaved Ice (+50 Stamina) | N6: 46058.274
A7: 11223 | B7: 30 | C7: 171933▸Mystic Matrimony◆Collection Bonus〈500 Gold x 1〉 | D7: =IFERROR(__xludf.DUMMYFUNCTION("""COMPUTED_VALUE"""),171933.0) -> 171933 | E7: =IFERROR(__xludf.DUMMYFUNCTION("""COMPUTED_VALUE"""),"Mystic Matrimony◆Collection Bonus") -> Mystic Matrimony◆Collection Bonus | F7: =IFERROR(__xludf.DUMMYFUNCTION("""COMPUTED_VALUE"""),"500 Gold x 1") -> 500 Gold x 1 | G7: 500 Gold | H7: 1 | L7: 500 Gold | N7: 46058.274
A8: 11224 | B8: 40 | C8: 171934▸Mystic Matrimony◆Collection Bonus〈Closet Storage x 1〉 | D8: =IFERROR(__xludf.DUMMYFUNCTION("""COMPUTED_VALUE"""),171934.0) -> 171934 | E8: =IFERROR(__xludf.DUMMYFUNCTION("""COMPUTED_VALUE"""),"Mystic Matrimony◆Collection Bonus") -> Mystic Matrimony◆Collection Bonus | F8: =IFERROR(__xludf.DUMMYFUNCTION("""COMPUTED_VALUE"""),"Closet Storage x 1") -> Closet Storage x 1 | G8: Closet Storage | H8: 1 | L8: Closet Storage | N8: 46058.274
A9: 11225 | B9: 50 | C9: 171935▸Mystic Matrimony◆Collection Bonus〈Shaved Ice (+50 Stamina) x 1〉 | D9: =IFERROR(__xludf.DUMMYFUNCTION("""COMPUTED_VALUE"""),171935.0) -> 171935 | E9: =IFERROR(__xludf.DUMMYFUNCTION("""COMPUTED_VALUE"""),"Mystic Matrimony◆Collection Bonus") -> Mystic Matrimony◆Collection Bonus | F9: =IFERROR(__xludf.DUMMYFUNCTION("""COMPUTED_VALUE"""),"Shaved Ice (+50 Stamina) x 1") -> Shaved Ice (+50 Stamina) x 1 | G9: Shaved Ice (+50 Stamina) | H9: 1 | L9: Shaved Ice (+50 Stamina) | N9: 46058.274
A10: 11226 | B10: 60 | C10: 171936▸Mystic Matrimony◆Collection Bonus〈Yoshimoto with a Lantern x 1〉 | D10: =IFERROR(__xludf.DUMMYFUNCTION("""COMPUTED_VALUE"""),171936.0) -> 171936 | E10: =IFERROR(__xludf.DUMMYFUNCTION("""COMPUTED_VALUE"""),"Mystic Matrimony◆Collection Bonus") -> Mystic Matrimony◆Collection Bonus | F10: =IFERROR(__xludf.DUMMYFUNCTION("""COMPUTED_VALUE"""),"Yoshimoto with a Lantern x 1") -> Yoshimoto with a Lantern x 1 | G10: Yoshimoto with a Lantern | H10: 1 | L10: Yoshimoto with a Lantern | N10: 46058.274
A11: 11227 | B11: 70 | C11: 171937▸Mystic Matrimony◆Collection Bonus〈Shaved Ice (+50 Stamina) x 1〉 | D11: =IFERROR(__xludf.DUMMYFUNCTION("""COMPUTED_VALUE"""),171937.0) -> 171937 | E11: =IFERROR(__xludf.DUMMYFUNCTION("""COMPUTED_VALUE"""),"Mystic Matrimony◆Collection Bonus") -> Mystic Matrimony◆Collection Bonus | F11: =IFERROR(__xludf.DUMMYFUNCTION("""COMPUTED_VALUE"""),"Shaved Ice (+50 Stamina) x 1") -> Shaved Ice (+50 Stamina) x 1 | G11: Shaved Ice (+50 Stamina) | H11: 1 | L11: Shaved Ice (+50 Stamina) | N11: 46058.274
A12: 11228 | B12: 80 | C12: 171938▸Mystic Matrimony◆Collection Bonus〈500 Gold x 1〉 | D12: =IFERROR(__xludf.DUMMYFUNCTION("""COMPUTED_VALUE"""),171938.0) -> 171938 | E12: =IFERROR(__xludf.DUMMYFUNCTION("""COMPUTED_VALUE"""),"Mystic Matrimony◆Collection Bonus") -> Mystic Matrimony◆Collection Bonus | F12: =IFERROR(__xludf.DUMMYFUNCTION("""COMPUTED_VALUE"""),"500 Gold x 1") -> 500 Gold x 1 | G12: 500 Gold | H12: 1 | L12: 500 Gold | N12: 46058.274
A13: 11229 | B13: 90 | C13: 171939▸Mystic Matrimony◆Collection Bonus〈Shaved Ice (+50 Stamina) x 1〉 | D13: =IFERROR(__xludf.DUMMYFUNCTION("""COMPUTED_VALUE"""),171939.0) -> 171939 | E13: =IFERROR(__xludf.DUMMYFUNCTION("""COMPUTED_VALUE"""),"Mystic Matrimony◆Collection Bonus") -> Mystic Matrimony◆Collection Bonus | F13: =IFERROR(__xludf.DUMMYFUNCTION("""COMPUTED_VALUE"""),"Shaved Ice (+50 Stamina) x 1") -> Shaved Ice (+50 Stamina) x 1 | G13: Shaved Ice (+50 Stamina) | H13: 1 | L13: Shaved Ice (+50 Stamina) | N13: 46058.274
A14: 11230 | B14: 100 | I14: 6319▸Mystic Matrimony Bonus Story ～Yoshimoto～ | J14: =IFERROR(__xludf.DUMMYFUNCTION("""COMPUTED_VALUE"""),6319.0) -> 6319 | K14: =IFERROR(__xludf.DUMMYFUNCTION("""COMPUTED_VALUE"""),"Mystic Matrimony Bonus Story ～Yoshimoto～") -> Mystic Matrimony Bonus Story ～Yoshimoto～ | L14: Mystic Matrimony Bonus Story ～Yoshimoto～ | N14: 46058.274
A15: 11231 | B15: 110 | C15: 171940▸Mystic Matrimony◆Collection Bonus〈Makeup (+100 Glamour) x 1〉 | D15: =IFERROR(__xludf.DUMMYFUNCTION("""COMPUTED_VALUE"""),171940.0) -> 171940 | E15: =IFERROR(__xludf.DUMMYFUNCTION("""COMPUTED_VALUE"""),"Mystic Matrimony◆Collection Bonus") -> Mystic Matrimony◆Collection Bonus | F15: =IFERROR(__xludf.DUMMYFUNCTION("""COMPUTED_VALUE"""),"Makeup (+100 Glamour) x 1") -> Makeup (+100 Glamour) x 1 | G15: Makeup (+100 Glamour) | H15: 1 | L15: Makeup (+100 Glamour) | N15: 46058.274
A16: 11232 | B16: 120 | C16: 171941▸Mystic Matrimony◆Collection Bonus〈Castle Storage x 1〉 | D16: =IFERROR(__xludf.DUMMYFUNCTION("""COMPUTED_VALUE"""),171941.0) -> 171941 | E16: =IFERROR(__xludf.DUMMYFUNCTION("""COMPUTED_VALUE"""),"Mystic Matrimony◆Collection Bonus") -> Mystic Matrimony◆Collection Bonus | F16: =IFERROR(__xludf.DUMMYFUNCTION("""COMPUTED_VALUE"""),"Castle Storage x 1") -> Castle Storage x 1 | G16: Castle Storage | H16: 1 | L16: Castle Storage | N16: 46058.274
A17: 11233 | B17: 130 | C17: 171942▸Mystic Matrimony◆Collection Bonus〈Shaved Ice (+50 Stamina) x 1〉 | D17: =IFERROR(__xludf.DUMMYFUNCTION("""COMPUTED_VALUE"""),171942.0) -> 171942 | E17: =IFERROR(__xludf.DUMMYFUNCTION("""COMPUTED_VALUE"""),"Mystic Matrimony◆Collection Bonus") -> Mystic Matrimony◆Collection Bonus | F17: =IFERROR(__xludf.DUMMYFUNCTION("""COMPUTED_VALUE"""),"Shaved Ice (+50 Stamina) x 1") -> Shaved Ice (+50 Stamina) x 1 | G17: Shaved Ice (+50 Stamina) | H17: 1 | L17: Shaved Ice (+50 Stamina) | N17: 46058.274
A18: 11234 | B18: 140 | C18: 171943▸Mystic Matrimony◆Collection Bonus〈Motonari with a Lantern x 1〉 | D18: =IFERROR(__xludf.DUMMYFUNCTION("""COMPUTED_VALUE"""),171943.0) -> 171943 | E18: =IFERROR(__xludf.DUMMYFUNCTION("""COMPUTED_VALUE"""),"Mystic Matrimony◆Collection Bonus") -> Mystic Matrimony◆Collection Bonus | F18: =IFERROR(__xludf.DUMMYFUNCTION("""COMPUTED_VALUE"""),"Motonari with a Lantern x 1") -> Motonari with a Lantern x 1 | G18: Motonari with a Lantern | H18: 1 | L18: Motonari with a Lantern | N18: 46058.274
A19: 11235 | B19: 150 | C19: 171944▸Mystic Matrimony◆Collection Bonus〈500 Gold x 1〉 | D19: =IFERROR(__xludf.DUMMYFUNCTION("""COMPUTED_VALUE"""),171944.0) -> 171944 | E19: =IFERROR(__xludf.DUMMYFUNCTION("""COMPUTED_VALUE"""),"Mystic Matrimony◆Collection Bonus") -> Mystic Matrimony◆Collection Bonus | F19: =IFERROR(__xludf.DUMMYFUNCTION("""COMPUTED_VALUE"""),"500 Gold x 1") -> 500 Gold x 1 | G19: 500 Gold | H19: 1 | L19: 500 Gold | N19: 46058.274
A20: 11236 | B20: 160 | C20: 171945▸Mystic Matrimony◆Collection Bonus〈Closet Storage x 1〉 | D20: =IFERROR(__xludf.DUMMYFUNCTION("""COMPUTED_VALUE"""),171945.0) -> 171945 | E20: =IFERROR(__xludf.DUMMYFUNCTION("""COMPUTED_VALUE"""),"Mystic Matrimony◆Collection Bonus") -> Mystic Matrimony◆Collection Bonus | F20: =IFERROR(__xludf.DUMMYFUNCTION("""COMPUTED_VALUE"""),"Closet Storage x 1") -> Closet Storage x 1 | G20: Closet Storage | H20: 1 | L20: Closet Storage | N20: 46058.274
A21: 11237 | B21: 170 | C21: 171946▸Mystic Matrimony◆Collection Bonus〈Shaved Ice (+50 Stamina) x 1〉 | D21: =IFERROR(__xludf.DUMMYFUNCTION("""COMPUTED_VALUE"""),171946.0) -> 171946 | E21: =IFERROR(__xludf.DUMMYFUNCTION("""COMPUTED_VALUE"""),"Mystic Matrimony◆Collection Bonus") -> Mystic Matrimony◆Collection Bonus | F21: =IFERROR(__xludf.DUMMYFUNCTION("""COMPUTED_VALUE"""),"Shaved Ice (+50 Stamina) x 1") -> Shaved Ice (+50 Stamina) x 1 | G21: Shaved Ice (+50 Stamina) | H21: 1 | L21: Shaved Ice (+50 Stamina) | N21: 46058.274
A22: 11238 | B22: 180 | C22: 171947▸Mystic Matrimony◆Collection Bonus〈Perfume (+100 Grace) x 1〉 | D22: =IFERROR(__xludf.DUMMYFUNCTION("""COMPUTED_VALUE"""),171947.0) -> 171947 | E22: =IFERROR(__xludf.DUMMYFUNCTION("""COMPUTED_VALUE"""),"Mystic Matrimony◆Collection Bonus") -> Mystic Matrimony◆Collection Bonus | F22: =IFERROR(__xludf.DUMMYFUNCTION("""COMPUTED_VALUE"""),"Perfume (+100 Grace) x 1") -> Perfume (+100 Grace) x 1 | G22: Perfume (+100 Grace) | H22: 1 | L22: Perfume (+100 Grace) | N22: 46058.274
A23: 11239 | B23: 190 | I23: 6318▸Mystic Matrimony Bonus Story ～Motonari～ | J23: =IFERROR(__xludf.DUMMYFUNCTION("""COMPUTED_VALUE"""),6318.0) -> 6318 | K23: =IFERROR(__xludf.DUMMYFUNCTION("""COMPUTED_VALUE"""),"Mystic Matrimony Bonus Story ～Motonari～") -> Mystic Matrimony Bonus Story ～Motonari～ | L23: Mystic Matrimony Bonus Story ～Motonari～ | N23: 46058.274
A24: 11240 | B24: 200 | C24: 171948▸Mystic Matrimony◆Collection Bonus〈Limited Chapter Ticket x 1〉 | D24: =IFERROR(__xludf.DUMMYFUNCTION("""COMPUTED_VALUE"""),171948.0) -> 171948 | E24: =IFERROR(__xludf.DUMMYFUNCTION("""COMPUTED_VALUE"""),"Mystic Matrimony◆Collection Bonus") -> Mystic Matrimony◆Collection Bonus | F24: =IFERROR(__xludf.DUMMYFUNCTION("""COMPUTED_VALUE"""),"Limited Chapter Ticket x 1") -> Limited Chapter Ticket x 1 | G24: Limited Chapter Ticket | H24: 1 | L24: Limited Chapter Ticket | N24: 46058.274
A25: 11241 | B25: 210 | C25: 171949▸Mystic Matrimony◆Collection Bonus〈500 Gold x 1〉 | D25: =IFERROR(__xludf.DUMMYFUNCTION("""COMPUTED_VALUE"""),171949.0) -> 171949 | E25: =IFERROR(__xludf.DUMMYFUNCTION("""COMPUTED_VALUE"""),"Mystic Matrimony◆Collection Bonus") -> Mystic Matrimony◆Collection Bonus | F25: =IFERROR(__xludf.DUMMYFUNCTION("""COMPUTED_VALUE"""),"500 Gold x 1") -> 500 Gold x 1 | G25: 500 Gold | H25: 1 | L25: 500 Gold | N25: 46058.274
A26: 11242 | B26: 220 | C26: 171950▸Mystic Matrimony◆Collection Bonus〈Castle Storage x 1〉 | D26: =IFERROR(__xludf.DUMMYFUNCTION("""COMPUTED_VALUE"""),171950.0) -> 171950 | E26: =IFERROR(__xludf.DUMMYFUNCTION("""COMPUTED_VALUE"""),"Mystic Matrimony◆Collection Bonus") -> Mystic Matrimony◆Collection Bonus | F26: =IFERROR(__xludf.DUMMYFUNCTION("""COMPUTED_VALUE"""),"Castle Storage x 1") -> Castle Storage x 1 | G26: Castle Storage | H26: 1 | L26: Castle Storage | N26: 46058.274
A27: 11243 | B27: 230 | C27: 171951▸Mystic Matrimony◆Collection Bonus〈Kicho with a Lantern x 1〉 | D27: =IFERROR(__xludf.DUMMYFUNCTION("""COMPUTED_VALUE"""),171951.0) -> 171951 | E27: =IFERROR(__xludf.DUMMYFUNCTION("""COMPUTED_VALUE"""),"Mystic Matrimony◆Collection Bonus") -> Mystic Matrimony◆Collection Bonus | F27: =IFERROR(__xludf.DUMMYFUNCTION("""COMPUTED_VALUE"""),"Kicho with a Lantern x 1") -> Kicho with a Lantern x 1 | G27: Kicho with a Lantern | H27: 1 | L27: Kicho with a Lantern | N27: 46058.274
A28: 11244 | B28: 240 | C28: 171952▸Mystic Matrimony◆Collection Bonus〈Perfume (+100 Grace) x 1〉 | D28: =IFERROR(__xludf.DUMMYFUNCTION("""COMPUTED_VALUE"""),171952.0) -> 171952 | E28: =IFERROR(__xludf.DUMMYFUNCTION("""COMPUTED_VALUE"""),"Mystic Matrimony◆Collection Bonus") -> Mystic Matrimony◆Collection Bonus | F28: =IFERROR(__xludf.DUMMYFUNCTION("""COMPUTED_VALUE"""),"Perfume (+100 Grace) x 1") -> Perfume (+100 Grace) x 1 | G28: Perfume (+100 Grace) | H28: 1 | L28: Perfume (+100 Grace) | N28: 46058.274
A29: 11245 | B29: 250 | C29: 171953▸Mystic Matrimony◆Collection Bonus〈500 Gold x 1〉 | D29: =IFERROR(__xludf.DUMMYFUNCTION("""COMPUTED_VALUE"""),171953.0) -> 171953 | E29: =IFERROR(__xludf.DUMMYFUNCTION("""COMPUTED_VALUE"""),"Mystic Matrimony◆Collection Bonus") -> Mystic Matrimony◆Collection Bonus | F29: =IFERROR(__xludf.DUMMYFUNCTION("""COMPUTED_VALUE"""),"500 Gold x 1") -> 500 Gold x 1 | G29: 500 Gold | H29: 1 | L29: 500 Gold | N29: 46058.274
A30: 11246 | B30: 260 | C30: 171954▸Mystic Matrimony◆Collection Bonus〈Kanetsugu with a Lantern x 1〉 | D30: =IFERROR(__xludf.DUMMYFUNCTION("""COMPUTED_VALUE"""),171954.0) -> 171954 | E30: =IFERROR(__xludf.DUMMYFUNCTION("""COMPUTED_VALUE"""),"Mystic Matrimony◆Collection Bonus") -> Mystic Matrimony◆Collection Bonus | F30: =IFERROR(__xludf.DUMMYFUNCTION("""COMPUTED_VALUE"""),"Kanetsugu with a Lantern x 1") -> Kanetsugu with a Lantern x 1 | G30: Kanetsugu with a Lantern | H30: 1 | L30: Kanetsugu with a Lantern | N30: 46058.274
A31: 11247 | B31: 270 | C31: 171955▸Mystic Matrimony◆Collection Bonus〈Castle Storage x 1〉 | D31: =IFERROR(__xludf.DUMMYFUNCTION("""COMPUTED_VALUE"""),171955.0) -> 171955 | E31: =IFERROR(__xludf.DUMMYFUNCTION("""COMPUTED_VALUE"""),"Mystic Matrimony◆Collection Bonus") -> Mystic Matrimony◆Collection Bonus | F31: =IFERROR(__xludf.DUMMYFUNCTION("""COMPUTED_VALUE"""),"Castle Storage x 1") -> Castle Storage x 1 | G31: Castle Storage | H31: 1 | L31: Castle Storage | N31: 46058.274
A32: 11248 | B32: 280 | C32: 171956▸Mystic Matrimony◆Collection Bonus〈Makeup (+100 Glamour) x 1〉 | D32: =IFERROR(__xludf.DUMMYFUNCTION("""COMPUTED_VALUE"""),171956.0) -> 171956 | E32: =IFERROR(__xludf.DUMMYFUNCTION("""COMPUTED_VALUE"""),"Mystic Matrimony◆Collection Bonus") -> Mystic Matrimony◆Collection Bonus | F32: =IFERROR(__xludf.DUMMYFUNCTION("""COMPUTED_VALUE"""),"Makeup (+100 Glamour) x 1") -> Makeup (+100 Glamour) x 1 | G32: Makeup (+100 Glamour) | H32: 1 | L32: Makeup (+100 Glamour) | N32: 46058.274
A33: 11249 | B33: 290 | C33: 171957▸Mystic Matrimony◆Collection Bonus〈Shaved Ice (+100 Stamina) x 1〉 | D33: =IFERROR(__xludf.DUMMYFUNCTION("""COMPUTED_VALUE"""),171957.0) -> 171957 | E33: =IFERROR(__xludf.DUMMYFUNCTION("""COMPUTED_VALUE"""),"Mystic Matrimony◆Collection Bonus") -> Mystic Matrimony◆Collection Bonus | F33: =IFERROR(__xludf.DUMMYFUNCTION("""COMPUTED_VALUE"""),"Shaved Ice (+100 Stamina) x 1") -> Shaved Ice (+100 Stamina) x 1 | G33: Shaved Ice (+100 Stamina) | H33: 1 | L33: Shaved Ice (+100 Stamina) | N33: 46058.274
A34: 11250 | B34: 300 | I34: 6317▸Mystic Matrimony Bonus Story ～Kicho～ | J34: =IFERROR(__xludf.DUMMYFUNCTION("""COMPUTED_VALUE"""),6317.0) -> 6317 | K34: =IFERROR(__xludf.DUMMYFUNCTION("""COMPUTED_VALUE"""),"Mystic Matrimony Bonus Story ～Kicho～") -> Mystic Matrimony Bonus Story ～Kicho～ | L34: Mystic Matrimony Bonus Story ～Kicho～ | N34: 46058.274
A35: 11251 | B35: 310 | C35: 171958▸Mystic Matrimony◆Collection Bonus〈Closet Storage x 1〉 | D35: =IFERROR(__xludf.DUMMYFUNCTION("""COMPUTED_VALUE"""),171958.0) -> 171958 | E35: =IFERROR(__xludf.DUMMYFUNCTION("""COMPUTED_VALUE"""),"Mystic Matrimony◆Collection Bonus") -> Mystic Matrimony◆Collection Bonus | F35: =IFERROR(__xludf.DUMMYFUNCTION("""COMPUTED_VALUE"""),"Closet Storage x 1") -> Closet Storage x 1 | G35: Closet Storage | H35: 1 | L35: Closet Storage | N35: 46058.274
A36: 11252 | B36: 320 | C36: 171959▸Mystic Matrimony◆Collection Bonus〈1500 Gold x 1〉 | D36: =IFERROR(__xludf.DUMMYFUNCTION("""COMPUTED_VALUE"""),171959.0) -> 171959 | E36: =IFERROR(__xludf.DUMMYFUNCTION("""COMPUTED_VALUE"""),"Mystic Matrimony◆Collection Bonus") -> Mystic Matrimony◆Collection Bonus | F36: =IFERROR(__xludf.DUMMYFUNCTION("""COMPUTED_VALUE"""),"1500 Gold x 1") -> 1500 Gold x 1 | G36: 1500 Gold | H36: 1 | L36: 1500 Gold | N36: 46058.274
A37: 11253 | B37: 330 | C37: 171960▸Mystic Matrimony◆Collection Bonus〈(Main) Dramatic Elixir (+1) x 1〉 | D37: =IFERROR(__xludf.DUMMYFUNCTION("""COMPUTED_VALUE"""),171960.0) -> 171960 | E37: =IFERROR(__xludf.DUMMYFUNCTION("""COMPUTED_VALUE"""),"Mystic Matrimony◆Collection Bonus") -> Mystic Matrimony◆Collection Bonus | F37: =IFERROR(__xludf.DUMMYFUNCTION("""COMPUTED_VALUE"""),"(Main) Dramatic Elixir (+1) x 1") -> (Main) Dramatic Elixir (+1) x 1 | G37: (Main) Dramatic Elixir (+1) | H37: 1 | L37: (Main) Dramatic Elixir (+1) | N37: 46058.274
A38: 11254 | B38: 340 | C38: 171961▸Mystic Matrimony◆Collection Bonus〈Nobunaga with a Lantern x 1〉 | D38: =IFERROR(__xludf.DUMMYFUNCTION("""COMPUTED_VALUE"""),171961.0) -> 171961 | E38: =IFERROR(__xludf.DUMMYFUNCTION("""COMPUTED_VALUE"""),"Mystic Matrimony◆Collection Bonus") -> Mystic Matrimony◆Collection Bonus | F38: =IFERROR(__xludf.DUMMYFUNCTION("""COMPUTED_VALUE"""),"Nobunaga with a Lantern x 1") -> Nobunaga with a Lantern x 1 | G38: Nobunaga with a Lantern | H38: 1 | L38: Nobunaga with a Lantern | N38: 46058.274
A39: 11255 | B39: 350 | C39: 171962▸Mystic Matrimony◆Collection Bonus〈Castle Storage x 1〉 | D39: =IFERROR(__xludf.DUMMYFUNCTION("""COMPUTED_VALUE"""),171962.0) -> 171962 | E39: =IFERROR(__xludf.DUMMYFUNCTION("""COMPUTED_VALUE"""),"Mystic Matrimony◆Collection Bonus") -> Mystic Matrimony◆Collection Bonus | F39: =IFERROR(__xludf.DUMMYFUNCTION("""COMPUTED_VALUE"""),"Castle Storage x 1") -> Castle Storage x 1 | G39: Castle Storage | H39: 1 | L39: Castle Storage | N39: 46058.274
A40: 11256 | B40: 360 | C40: 171963▸Mystic Matrimony◆Collection Bonus〈Limited Chapter Ticket x 1〉 | D40: =IFERROR(__xludf.DUMMYFUNCTION("""COMPUTED_VALUE"""),171963.0) -> 171963 | E40: =IFERROR(__xludf.DUMMYFUNCTION("""COMPUTED_VALUE"""),"Mystic Matrimony◆Collection Bonus") -> Mystic Matrimony◆Collection Bonus | F40: =IFERROR(__xludf.DUMMYFUNCTION("""COMPUTED_VALUE"""),"Limited Chapter Ticket x 1") -> Limited Chapter Ticket x 1 | G40: Limited Chapter Ticket | H40: 1 | L40: Limited Chapter Ticket | N40: 46058.274
A41: 11257 | B41: 370 | C41: 171964▸Mystic Matrimony◆Collection Bonus〈Masamune with a Lantern x 1〉 | D41: =IFERROR(__xludf.DUMMYFUNCTION("""COMPUTED_VALUE"""),171964.0) -> 171964 | E41: =IFERROR(__xludf.DUMMYFUNCTION("""COMPUTED_VALUE"""),"Mystic Matrimony◆Collection Bonus") -> Mystic Matrimony◆Collection Bonus | F41: =IFERROR(__xludf.DUMMYFUNCTION("""COMPUTED_VALUE"""),"Masamune with a Lantern x 1") -> Masamune with a Lantern x 1 | G41: Masamune with a Lantern | H41: 1 | L41: Masamune with a Lantern | N41: 46058.274
A42: 11258 | B42: 380 | C42: 171965▸Mystic Matrimony◆Collection Bonus〈1500 Gold x 1〉 | D42: =IFERROR(__xludf.DUMMYFUNCTION("""COMPUTED_VALUE"""),171965.0) -> 171965 | E42: =IFERROR(__xludf.DUMMYFUNCTION("""COMPUTED_VALUE"""),"Mystic Matrimony◆Collection Bonus") -> Mystic Matrimony◆Collection Bonus | F42: =IFERROR(__xludf.DUMMYFUNCTION("""COMPUTED_VALUE"""),"1500 Gold x 1") -> 1500 Gold x 1 | G42: 1500 Gold | H42: 1 | L42: 1500 Gold | N42: 46058.274
A43: 11259 | B43: 390 | C43: 171966▸Mystic Matrimony◆Collection Bonus〈Perfume (+500 Grace) x 1〉 | D43: =IFERROR(__xludf.DUMMYFUNCTION("""COMPUTED_VALUE"""),171966.0) -> 171966 | E43: =IFERROR(__xludf.DUMMYFUNCTION("""COMPUTED_VALUE"""),"Mystic Matrimony◆Collection Bonus") -> Mystic Matrimony◆Collection Bonus | F43: =IFERROR(__xludf.DUMMYFUNCTION("""COMPUTED_VALUE"""),"Perfume (+500 Grace) x 1") -> Perfume (+500 Grace) x 1 | G43: Perfume (+500 Grace) | H43: 1 | L43: Perfume (+500 Grace) | N43: 46058.274
A44: 11260 | B44: 400 | C44: 171967▸Mystic Matrimony◆Collection Bonus〈(Main) Romantic Elixir (+1) x 1〉 | D44: =IFERROR(__xludf.DUMMYFUNCTION("""COMPUTED_VALUE"""),171967.0) -> 171967 | E44: =IFERROR(__xludf.DUMMYFUNCTION("""COMPUTED_VALUE"""),"Mystic Matrimony◆Collection Bonus") -> Mystic Matrimony◆Collection Bonus | F44: =IFERROR(__xludf.DUMMYFUNCTION("""COMPUTED_VALUE"""),"(Main) Romantic Elixir (+1) x 1") -> (Main) Romantic Elixir (+1) x 1 | G44: (Main) Romantic Elixir (+1) | H44: 1 | L44: (Main) Romantic Elixir (+1) | N44: 46058.274
A45: 11261 | B45: 410 | I45: 6316▸Mystic Matrimony Bonus Story ～Kanetsugu～ | J45: =IFERROR(__xludf.DUMMYFUNCTION("""COMPUTED_VALUE"""),6316.0) -> 6316 | K45: =IFERROR(__xludf.DUMMYFUNCTION("""COMPUTED_VALUE"""),"Mystic Matrimony Bonus Story ～Kanetsugu～") -> Mystic Matrimony Bonus Story ～Kanetsugu～ | L45: Mystic Matrimony Bonus Story ～Kanetsugu～ | N45: 46058.274
A46: 11262 | B46: 420 | C46: 171968▸Mystic Matrimony◆Collection Bonus〈Shaved Ice (+100 Stamina) x 1〉 | D46: =IFERROR(__xludf.DUMMYFUNCTION("""COMPUTED_VALUE"""),171968.0) -> 171968 | E46: =IFERROR(__xludf.DUMMYFUNCTION("""COMPUTED_VALUE"""),"Mystic Matrimony◆Collection Bonus") -> Mystic Matrimony◆Collection Bonus | F46: =IFERROR(__xludf.DUMMYFUNCTION("""COMPUTED_VALUE"""),"Shaved Ice (+100 Stamina) x 1") -> Shaved Ice (+100 Stamina) x 1 | G46: Shaved Ice (+100 Stamina) | H46: 1 | L46: Shaved Ice (+100 Stamina) | N46: 46058.274
A47: 11263 | B47: 430 | C47: 171969▸Mystic Matrimony◆Collection Bonus〈Closet Storage x 1〉 | D47: =IFERROR(__xludf.DUMMYFUNCTION("""COMPUTED_VALUE"""),171969.0) -> 171969 | E47: =IFERROR(__xludf.DUMMYFUNCTION("""COMPUTED_VALUE"""),"Mystic Matrimony◆Collection Bonus") -> Mystic Matrimony◆Collection Bonus | F47: =IFERROR(__xludf.DUMMYFUNCTION("""COMPUTED_VALUE"""),"Closet Storage x 1") -> Closet Storage x 1 | G47: Closet Storage | H47: 1 | L47: Closet Storage | N47: 46058.274
A48: 11264 | B48: 440 | C48: 171970▸Mystic Matrimony◆Collection Bonus〈Vampire Wings x 1〉 | D48: =IFERROR(__xludf.DUMMYFUNCTION("""COMPUTED_VALUE"""),171970.0) -> 171970 | E48: =IFERROR(__xludf.DUMMYFUNCTION("""COMPUTED_VALUE"""),"Mystic Matrimony◆Collection Bonus") -> Mystic Matrimony◆Collection Bonus | F48: =IFERROR(__xludf.DUMMYFUNCTION("""COMPUTED_VALUE"""),"Vampire Wings x 1") -> Vampire Wings x 1 | G48: Vampire Wings | H48: 1 | L48: Vampire Wings | N48: 46058.274
A49: 11265 | B49: 450 | C49: 171971▸Mystic Matrimony◆Collection Bonus〈(Main) Elixir of Love (+1:+1) x 1〉 | D49: =IFERROR(__xludf.DUMMYFUNCTION("""COMPUTED_VALUE"""),171971.0) -> 171971 | E49: =IFERROR(__xludf.DUMMYFUNCTION("""COMPUTED_VALUE"""),"Mystic Matrimony◆Collection Bonus") -> Mystic Matrimony◆Collection Bonus | F49: =IFERROR(__xludf.DUMMYFUNCTION("""COMPUTED_VALUE"""),"(Main) Elixir of Love (+1:+1) x 1") -> (Main) Elixir of Love (+1:+1) x 1 | G49: (Main) Elixir of Love (+1:+1) | H49: 1 | L49: (Main) Elixir of Love (+1:+1) | N49: 46058.274
A50: 11266 | B50: 460 | C50: 171972▸Mystic Matrimony◆Collection Bonus〈Closet Storage x 1〉 | D50: =IFERROR(__xludf.DUMMYFUNCTION("""COMPUTED_VALUE"""),171972.0) -> 171972 | E50: =IFERROR(__xludf.DUMMYFUNCTION("""COMPUTED_VALUE"""),"Mystic Matrimony◆Collection Bonus") -> Mystic Matrimony◆Collection Bonus | F50: =IFERROR(__xludf.DUMMYFUNCTION("""COMPUTED_VALUE"""),"Closet Storage x 1") -> Closet Storage x 1 | G50: Closet Storage | H50: 1 | L50: Closet Storage | N50: 46058.274
A51: 11267 | B51: 470 | C51: 171973▸Mystic Matrimony◆Collection Bonus〈Dragon Horns x 1〉 | D51: =IFERROR(__xludf.DUMMYFUNCTION("""COMPUTED_VALUE"""),171973.0) -> 171973 | E51: =IFERROR(__xludf.DUMMYFUNCTION("""COMPUTED_VALUE"""),"Mystic Matrimony◆Collection Bonus") -> Mystic Matrimony◆Collection Bonus | F51: =IFERROR(__xludf.DUMMYFUNCTION("""COMPUTED_VALUE"""),"Dragon Horns x 1") -> Dragon Horns x 1 | G51: Dragon Horns | H51: 1 | L51: Dragon Horns | N51: 46058.274
A52: 11268 | B52: 480 | C52: 171974▸Mystic Matrimony◆Collection Bonus〈Closet Storage x 1〉 | D52: =IFERROR(__xludf.DUMMYFUNCTION("""COMPUTED_VALUE"""),171974.0) -> 171974 | E52: =IFERROR(__xludf.DUMMYFUNCTION("""COMPUTED_VALUE"""),"Mystic Matrimony◆Collection Bonus") -> Mystic Matrimony◆Collection Bonus | F52: =IFERROR(__xludf.DUMMYFUNCTION("""COMPUTED_VALUE"""),"Closet Storage x 1") -> Closet Storage x 1 | G52: Closet Storage | H52: 1 | L52: Closet Storage | N52: 46058.274
A53: 11269 | B53: 490 | C53: 171975▸Mystic Matrimony◆Collection Bonus〈Shaved Ice (+50 Stamina) x 1〉 | D53: =IFERROR(__xludf.DUMMYFUNCTION("""COMPUTED_VALUE"""),171975.0) -> 171975 | E53: =IFERROR(__xludf.DUMMYFUNCTION("""COMPUTED_VALUE"""),"Mystic Matrimony◆Collection Bonus") -> Mystic Matrimony◆Collection Bonus | F53: =IFERROR(__xludf.DUMMYFUNCTION("""COMPUTED_VALUE"""),"Shaved Ice (+50 Stamina) x 1") -> Shaved Ice (+50 Stamina) x 1 | G53: Shaved Ice (+50 Stamina) | H53: 1 | L53: Shaved Ice (+50 Stamina) | N53: 46058.274
A54: 11270 | B54: 500 | I54: 6315▸Mystic Matrimony Bonus Story ～Nobunaga～ | J54: =IFERROR(__xludf.DUMMYFUNCTION("""COMPUTED_VALUE"""),6315.0) -> 6315 | K54: =IFERROR(__xludf.DUMMYFUNCTION("""COMPUTED_VALUE"""),"Mystic Matrimony Bonus Story ～Nobunaga～") -> Mystic Matrimony Bonus Story ～Nobunaga～ | L54: Mystic Matrimony Bonus Story ～Nobunaga～ | N54: 46058.274
A55: 11271 | B55: 510 | C55: 171976▸Mystic Matrimony◆Collection Bonus〈3000 Gold x 1〉 | D55: =IFERROR(__xludf.DUMMYFUNCTION("""COMPUTED_VALUE"""),171976.0) -> 171976 | E55: =IFERROR(__xludf.DUMMYFUNCTION("""COMPUTED_VALUE"""),"Mystic Matrimony◆Collection Bonus") -> Mystic Matrimony◆Collection Bonus | F55: =IFERROR(__xludf.DUMMYFUNCTION("""COMPUTED_VALUE"""),"3000 Gold x 1") -> 3000 Gold x 1 | G55: 3000 Gold | H55: 1 | L55: 3000 Gold | N55: 46058.274
A56: 11272 | B56: 520 | C56: 171977▸Mystic Matrimony◆Collection Bonus〈Ogre Horns x 1〉 | D56: =IFERROR(__xludf.DUMMYFUNCTION("""COMPUTED_VALUE"""),171977.0) -> 171977 | E56: =IFERROR(__xludf.DUMMYFUNCTION("""COMPUTED_VALUE"""),"Mystic Matrimony◆Collection Bonus") -> Mystic Matrimony◆Collection Bonus | F56: =IFERROR(__xludf.DUMMYFUNCTION("""COMPUTED_VALUE"""),"Ogre Horns x 1") -> Ogre Horns x 1 | G56: Ogre Horns | H56: 1 | L56: Ogre Horns | N56: 46058.274
A57: 11273 | B57: 530 | C57: 171978▸Mystic Matrimony◆Collection Bonus〈Midnight Parkview Veranda x 1〉 | D57: =IFERROR(__xludf.DUMMYFUNCTION("""COMPUTED_VALUE"""),171978.0) -> 171978 | E57: =IFERROR(__xludf.DUMMYFUNCTION("""COMPUTED_VALUE"""),"Mystic Matrimony◆Collection Bonus") -> Mystic Matrimony◆Collection Bonus | F57: =IFERROR(__xludf.DUMMYFUNCTION("""COMPUTED_VALUE"""),"Midnight Parkview Veranda x 1") -> Midnight Parkview Veranda x 1 | G57: Midnight Parkview Veranda | H57: 1 | L57: Midnight Parkview Veranda | N57: 46058.274
A58: 11274 | B58: 540 | C58: 171979▸Mystic Matrimony◆Collection Bonus〈Gacha Token x 1〉 | D58: =IFERROR(__xludf.DUMMYFUNCTION("""COMPUTED_VALUE"""),171979.0) -> 171979 | E58: =IFERROR(__xludf.DUMMYFUNCTION("""COMPUTED_VALUE"""),"Mystic Matrimony◆Collection Bonus") -> Mystic Matrimony◆Collection Bonus | F58: =IFERROR(__xludf.DUMMYFUNCTION("""COMPUTED_VALUE"""),"Gacha Token x 1") -> Gacha Token x 1 | G58: Gacha Token | H58: 1 | L58: Gacha Token | N58: 46058.274
A59: 11275 | B59: 550 | I59: 6314▸Mystic Matrimony Bonus Story ～Masamune～ | J59: =IFERROR(__xludf.DUMMYFUNCTION("""COMPUTED_VALUE"""),6314.0) -> 6314 | K59: =IFERROR(__xludf.DUMMYFUNCTION("""COMPUTED_VALUE"""),"Mystic Matrimony Bonus Story ～Masamune～") -> Mystic Matrimony Bonus Story ～Masamune～ | L59: Mystic Matrimony Bonus Story ～Masamune～ | N59: 46058.274
A60: 11276 | B60: 560 | C60: 171980▸Mystic Matrimony◆Collection Bonus〈Mystic Matrimony Trophy x 1〉 | D60: =IFERROR(__xludf.DUMMYFUNCTION("""COMPUTED_VALUE"""),171980.0) -> 171980 | E60: =IFERROR(__xludf.DUMMYFUNCTION("""COMPUTED_VALUE"""),"Mystic Matrimony◆Collection Bonus") -> Mystic Matrimony◆Collection Bonus | F60: =IFERROR(__xludf.DUMMYFUNCTION("""COMPUTED_VALUE"""),"Mystic Matrimony Trophy x 1") -> Mystic Matrimony Trophy x 1 | G60: Mystic Matrimony Trophy | H60: 1 | L60: Mystic Matrimony Trophy | N60: 46058.274
A61: 11277 | B61: 0 | C61: 171981▸Mystic Matrimony◆Collection Bonus〈Shaved Ice (+10 Stamina) x 1〉 | D61: =IFERROR(__xludf.DUMMYFUNCTION("""COMPUTED_VALUE"""),171981.0) -> 171981 | E61: =IFERROR(__xludf.DUMMYFUNCTION("""COMPUTED_VALUE"""),"Mystic Matrimony◆Collection Bonus") -> Mystic Matrimony◆Collection Bonus | F61: =IFERROR(__xludf.DUMMYFUNCTION("""COMPUTED_VALUE"""),"Shaved Ice (+10 Stamina) x 1") -> Shaved Ice (+10 Stamina) x 1 | G61: Shaved Ice (+10 Stamina) | H61: 1 | L61: Shaved Ice (+10 Stamina) | N61: 46058.274

Sheet フィーバー
A1: No | B1: 項目 | C1: 確認方法 | D1: 確認事項 | E1: 項目 | F1: 確認方法 | G1: 確認事項 | H1: 確認箇所・詳細 | I1: ID | J1: Column | K1: Result | L1: テスト環境 | P1: 本番環境 | T1: 備考 | U1: テスターコメント | V1: チケットURL
L2: 確認 | M2: 担当 | N2: 担当者 | O2: 日付 | P2: 確認 | Q2: 担当 | R2: 担当者 | S2: 日付
A3: =ROW()-2 -> 1 | B3: ='参照_概要'!B23 -> 物語フィーバー① | C3: 管理ツール コレクションイベント＞該当イベント＞フィーバー設定 | D3: 開始日時が左記の通り設定されているか | E3: ='参照_概要'!B23 -> 物語フィーバー① | F3: 管理工具 收集活動＞該活動＞Fever 設定 | G3: 開始日期時間是否按右側設定 | H3: ='参照_概要'!$C$23 -> 46074.708 | I3: 2325 | J3: 4 | K3: {=IF(LEN(I3:I29),VLOOKUP(I3:I29,Fever!$A$5:$F29,J3:J29,0),)} -> 46074.708 | L3: {=IF(H3:H29=K3:K29,{"OK","IW","Bill"},U3:U29)} -> OK | M3: IW | N3: Bill | O3: 46062
A4: =ROW()-2 -> 2 | D4: 終了日時が左記の通り設定されているか | G4: 結束日期時間是否按右側設定 | H4: ='参照_概要'!$D$23 -> 46075.208 | I4: 2325 | J4: 5 | K4: 46075.208 | L4: OK | M4: IW | N4: Bill | O4: 46062
A5: =ROW()-2 -> 3 | D5: ミニゲームFV倍率が左記の通り設定されているか | G5: 小遊戲Fever倍率是否按右側設定 | H5: ='参照_概要'!$E$23 -> 1 | I5: 2325 | J5: 2 | K5: 1 | L5: OK | M5: IW | N5: Bill | O5: 46062
A6: =ROW()-2 -> 4 | D6: ストーリーFV倍率が左記の通り設定されているか | G6: 故事Fever倍率是否按右側設定 | H6: ='参照_概要'!$F$23 -> 3 | I6: 2325 | J6: 3 | K6: 3 | L6: OK | M6: IW | N6: Bill | O6: 46062
A7: =ROW()-2 -> 5 | C7: 実機 | D7: FVが正しく動作しているか | F7: 實體機台 | G7: Fever 是否正常運作 | L7: OK | M7: IW | N7: Bill | P7: OK | Q7: IW | R7: Bill | S7: 46064
A8: =ROW()-2 -> 6 | B8: ='参照_概要'!B24 -> 姫磨きフィーバー① | C8: コレクションイベント＞該当イベント＞フィーバー設定 | D8: 開始日時が左記の通り設定されているか | E8: ='参照_概要'!B24 -> 姫磨きフィーバー① | F8: 收集活動＞該活動＞Fever 設定 | G8: 開始日期時間是否按右側設定 | H8: ='参照_概要'!$C$24 -> 46075.458 | I8: 2326 | J8: 4 | K8: 46075.458 | L8: OK | M8: IW | N8: Bill | O8: 46062
A9: =ROW()-2 -> 7 | D9: 終了日時が左記の通り設定されているか | G9: 結束日期時間是否按右側設定 | H9: ='参照_概要'!$D$24 -> 46076.208 | I9: 2326 | J9: 5 | K9: 46076.208 | L9: OK | M9: IW | N9: Bill | O9: 46062
A10: =ROW()-2 -> 8 | D10: ミニゲームFV倍率が左記の通り設定されているか | G10: 小遊戲Fever倍率是否按右側設定 | H10: ='参照_概要'!$E$24 -> 3 | I10: 2326 | J10: 2 | K10: 3 | L10: OK | M10: IW | N10: Bill | O10: 46062
A11: =ROW()-2 -> 9 | D11: ストーリーFV倍率が左記の通り設定されているか | G11: 故事Fever倍率是否按右側設定 | H11: ='参照_概要'!$F$24 -> 1 | I11: 2326 | J11: 3 | K11: 1 | L11: OK | M11: IW | N11: Bill | O11: 46062
A12: =ROW()-2 -> 10 | D12: ミニゲーム表示用文言が左記の通り設定されているか | G12: 小遊戲顯示用文案是否按右側設定 | H12: Do Princess Lessons & get 3x Hearts! | I12: 2326 | J12: 6 | K12: Do Princess Lessons & get 3x Hearts! | L12: OK | M12: IW | N12: Bill | O12: 46062
A13: =ROW()-2 -> 11 | B13: ='参照_概要'!B25 -> 物語フィーバー② | C13: コレクションイベント＞該当イベント＞フィーバー設定 | D13: 開始日時が左記の通り設定されているか | E13: ='参照_概要'!B25 -> 物語フィーバー② | F13: 收集活動＞該活動＞Fever 設定 | G13: 開始日期時間是否按右側設定 | H13: ='参照_概要'!$C$25 -> 46076.708 | I13: 2327 | J13: 4 | K13: 46076.708 | L13: OK | M13: IW | N13: Bill | O13: 46062
A14: =ROW()-2 -> 12 | D14: 終了日時が左記の通り設定されているか | G14: 結束日期時間是否按右側設定 | H14: ='参照_概要'!$D$25 -> 46077.208 | I14: 2327 | J14: 5 | K14: 46077.208 | L14: OK | M14: IW | N14: Bill | O14: 46062
A15: =ROW()-2 -> 13 | D15: ミニゲームFV倍率が左記の通り設定されているか | G15: 小遊戲Fever倍率是否按右側設定 | H15: ='参照_概要'!$E$25 -> 1 | I15: 2327 | J15: 2 | K15: 1 | L15: OK | M15: IW | N15: Bill | O15: 46062
A16: =ROW()-2 -> 14 | D16: ストーリーFV倍率が左記の通り設定されているか | G16: 故事Fever倍率是否按右側設定 | H16: ='参照_概要'!$F$25 -> 3 | I16: 2327 | J16: 3 | K16: 3 | L16: OK | M16: IW | N16: Bill | O16: 46062
A17: =ROW()-2 -> 15 | B17: ='参照_概要'!B26 -> 物語フィーバー③ | C17: コレクションイベント＞該当イベント＞フィーバー設定 | D17: 開始日時が左記の通り設定されているか | E17: ='参照_概要'!B26 -> 物語フィーバー③ | F17: 收集活動＞該活動＞Fever 設定 | G17: 開始日期時間是否按右側設定 | H17: ='参照_概要'!$C$26 -> 46077.708 | I17: 2328 | J17: 4 | K17: 46077.708 | L17: OK | M17: IW | N17: Bill | O17: 46062
A18: =ROW()-2 -> 16 | D18: 終了日時が左記の通り設定されているか | G18: 結束日期時間是否按右側設定 | H18: ='参照_概要'!$D$26 -> 46078.208 | I18: 2328 | J18: 5 | K18: 46078.208 | L18: OK | M18: IW | N18: Bill | O18: 46062
A19: =ROW()-2 -> 17 | D19: ミニゲームFV倍率が左記の通り設定されているか | G19: 小遊戲Fever倍率是否按右側設定 | H19: ='参照_概要'!$E$26 -> 1 | I19: 2328 | J19: 2 | K19: 1 | L19: OK | M19: IW | N19: Bill | O19: 46062
A20: =ROW()-2 -> 18 | D20: ストーリーFV倍率が左記の通り設定されているか | G20: 故事Fever倍率是否按右側設定 | H20: ='参照_概要'!$F$26 -> 3 | I20: 2328 | J20: 3 | K20: 3 | L20: OK | M20: IW | N20: Bill | O20: 46062
A21: =ROW()-2 -> 19 | B21: ='参照_概要'!B27 -> 姫磨きフィーバー② | C21: コレクションイベント＞該当イベント＞フィーバー設定 | D21: 開始日時が左記の通り設定されているか | E21: ='参照_概要'!B27 -> 姫磨きフィーバー② | F21: 收集活動＞該活動＞Fever 設定 | G21: 開始日期時間是否按右側設定 | H21: ='参照_概要'!$C$27 -> 46078.458 | I21: 2329 | J21: 4 | K21: 46078.458 | L21: OK | M21: IW | N21: Bill | O21: 46062
A22: =ROW()-2 -> 20 | D22: 終了日時が左記の通り設定されているか | G22: 結束日期時間是否按右側設定 | H22: ='参照_概要'!$D$27 -> 46078.958 | I22: 2329 | J22: 5 | K22: 46078.958 | L22: OK | M22: IW | N22: Bill | O22: 46062
A23: =ROW()-2 -> 21 | D23: ミニゲームFV倍率が左記の通り設定されているか | G23: 小遊戲Fever倍率是否按右側設定 | H23: ='参照_概要'!$E$27 -> 3 | I23: 2329 | J23: 2 | K23: 3 | L23: OK | M23: IW | N23: Bill | O23: 46062
A24: =ROW()-2 -> 22 | D24: ストーリーFV倍率が左記の通り設定されているか | G24: 故事Fever倍率是否按右側設定 | H24: ='参照_概要'!$F$27 -> 1 | I24: 2329 | J24: 3 | K24: 1 | L24: OK | M24: IW | N24: Bill | O24: 46062
A25: =ROW()-2 -> 23 | D25: ミニゲーム表示用文言が左記の通り設定されているか | G25: 小遊戲顯示用文案是否按右側設定 | H25: Do Princess Lessons & get 3x Hearts! | I25: 2329 | J25: 6 | K25: Do Princess Lessons & get 3x Hearts! | L25: OK | M25: IW | N25: Bill | O25: 46062
A26: =ROW()-2 -> 24 | B26: ='参照_概要'!B28 -> 物語フィーバー④ | C26: コレクションイベント＞該当イベント＞フィーバー設定 | D26: 開始日時が左記の通り設定されているか | E26: ='参照_概要'!B28 -> 物語フィーバー④ | F26: 收集活動＞該活動＞Fever 設定 | G26: 開始日期時間是否按右側設定 | H26: ='参照_概要'!$C$28 -> 46080.208 | I26: 2330 | J26: 4 | K26: 46080.208 | L26: OK | M26: IW | N26: Bill | O26: 46064 | U26: 2026/2/9 驗證單配置資料與後台不符
A27: =ROW()-2 -> 25 | D27: 終了日時が左記の通り設定されているか | G27: 結束日期時間是否按右側設定 | H27: ='参照_概要'!$D$28 -> 46080.708 | I27: 2330 | J27: 5 | K27: 46080.708 | L27: OK | M27: IW | N27: Bill | O27: 46064 | U27: 2026/2/9 驗證單配置資料與後台不符
A28: =ROW()-2 -> 26 | D28: ミニゲームFV倍率が左記の通り設定されているか | G28: 小遊戲Fever倍率是否按右側設定 | H28: ='参照_概要'!$E$28 -> 1 | I28: 2330 | J28: 2 | K28: 1 | L28: OK | M28: IW | N28: Bill | O28: 46062
A29: =ROW()-2 -> 27 | D29: ストーリーFV倍率が左記の通り設定されているか | G29: 故事Fever倍率是否按右側設定 | H29: ='参照_概要'!$F$28 -> 3 | I29: 2330 | J29: 3 | K29: 3 | L29: OK | M29: IW | N29: Bill | O29: 46062

Sheet Fever
A1: https://common-legacy-app-admin.us.ikemen-sengoku.jp/admin/isgame/collection/all_setting/203#event_fever_mst
A2: https://common-legacy-app-admin.us.ikemen-sengoku.jp/admin/collection/collect_fever_mst/collect_214
A3: {=SEQUENCE(1,COLUMNS(A:F))} -> 1 | B3: 2 | C3: 3 | D3: 4 | E3: 5 | F3: 6
A4: ID | B4: coefficient minigame | C4: coefficient story | D4: start | E4: end | F4: ミニゲーム 表示用文言
A5: 2325 | B5: 1 | C5: 3 | D5: 46074.708 | E5: 46075.208
A6: 2326 | B6: 3 | C6: 1 | D6: 46075.458 | E6: 46076.208 | F6: Do Princess Lessons & get 3x Hearts!
A7: 2327 | B7: 1 | C7: 3 | D7: 46076.708 | E7: 46077.208
A8: 2328 | B8: 1 | C8: 3 | D8: 46077.708 | E8: 46078.208
A9: 2329 | B9: 3 | C9: 1 | D9: 46078.458 | E9: 46078.958 | F9: Do Princess Lessons & get 3x Hearts!
A10: 2330 | B10: 1 | C10: 3 | D10: 46080.208 | E10: 46080.708

Sheet ストーリー
A1: No | B1: 項目 | C1: 確認環境 | D1: 確認項目 | E1: 項目 | F1: 確認環境 | G1: 確認項目 | H1: 話数 / タイトル | I1: 参照_仕様 other data | J1: テスト環境 | N1: 本番環境 | R1: 備考 | S1: テスターコメント | T1: チケットURL
J2: 確認 | K2: 担当 | L2: 担当者 | M2: 日付 | N2: 確認 | O2: 担当 | P2: 担当者 | Q2: 日付
A3: =ROW()-2 -> 1 | B3: ='参照_仕様'!$D$11&" "&'参照_仕様'!$E$11 -> 政宗 恋遊戯『特別ストーリー』 | C3: 実機 | D3: 保存先のキャラクターが右記の通りか | E3: ='参照_仕様'!$D$11&" "&'参照_仕様'!$E$11 -> 政宗 恋遊戯『特別ストーリー』 | F3: 實體機台 | G3: 保存目標角色是否如右方所示 | H3: ='参照_仕様'!$D$11 -> 政宗 | I3: {=LET( _tmp, XLOOKUP($H3,'参照_仕様'!$D$11:$D$28,'参照_仕様'!$C$11:$C$28), _tmp2, RIGHT(_tmp,LEN(_tmp)-30), LEFT(_tmp2,LEN(_tmp2)-1) )} -> Masamune | J3: OK | K3: IW | L3: Bill | M3: 46062
A4: =ROW()-2 -> 2 | D4: タイトルが右記の通り表示されているか | G4: 標題是否如右方所示顯示 | H4: ='参照_仕様'!$C$11 -> Mystic Matrimony Bonus Story ～Masamune～ | I4: =VLOOKUP(H4,'参照_仕様'!$C$11:$E$31,3,0) -> 恋遊戯『特別ストーリー』 | J4: OK | K4: IW | L4: Bill | M4: 46064
A5: =ROW()-2 -> 3 | D5: ストーリーが正常に再生できるか | G5: 故事是否能正常播放 | J5: OK | K5: IW | L5: Bill | M5: 46064
A6: =ROW()-2 -> 4 | C6: 管理ツール ストーリー管理＞チャプター編集 | D6: スクリプト内に画像のリンク切れや、日本語が残っていないか | F6: 管理工具 故事管理＞章節編輯 | G6: 腳本內是否沒有圖片連結失效或殘留日文 | I6: Masamune | J6: OK | K6: IW | L6: Bill | M6: 46062
A7: =ROW()-2 -> 5 | D7: スクリプトが本番反映されているか | G7: 腳本是否已反映至正式環境 | N7: OK | O7: {=IF(N7:N136="OK",{"IW","Bill","2/12"},)} -> IW | P7: Bill | Q7: 2/12 | S7: タイトルの日本語名称で検索する
A8: =ROW()-2 -> 6 | C8: 管理ツール ストーリー管理＞スクリプトリソース状況一覧 | D8: スクリプトリソースが反映されているか | F8: 管理工具 故事管理＞腳本資源狀況一覽 | G8: 腳本資源是否已反映 | N8: OK | O8: IW | P8: Bill | Q8: 2/12
A9: =ROW()-2 -> 7 | B9: ='参照_仕様'!$D$12&" "&'参照_仕様'!$E$12 -> 信長 恋遊戯『特別ストーリー』 | C9: 実機 | D9: 保存先のキャラクターが右記の通りか | E9: ='参照_仕様'!$D$12&" "&'参照_仕様'!$E$12 -> 信長 恋遊戯『特別ストーリー』 | F9: 實體機台 | G9: 保存目標角色是否如右方所示 | H9: ='参照_仕様'!$D$12 -> 信長 | I9: {=LET( _tmp, XLOOKUP($H9,'参照_仕様'!$D$11:$D$28,'参照_仕様'!$C$11:$C$28), _tmp2, RIGHT(_tmp,LEN(_tmp)-30), LEFT(_tmp2,LEN(_tmp2)-1) )} -> Nobunaga | J9: OK | K9: IW | L9: Bill | M9: 46062
A10: =ROW()-2 -> 8 | D10: タイトルが右記の通り表示されているか | G10: 標題是否如右方所示顯示 | H10: ='参照_仕様'!$C$12 -> Mystic Matrimony Bonus Story ～Nobunaga～ | I10: =VLOOKUP(H10,'参照_仕様'!$C$11:$E$31,3,0) -> 恋遊戯『特別ストーリー』 | J10: OK | K10: IW | L10: Bill | M10: 46064
A11: =ROW()-2 -> 9 | D11: ストーリーが正常に再生できるか | G11: 故事是否能正常播放 | J11: OK | K11: IW | L11: Bill | M11: 46064
A12: =ROW()-2 -> 10 | C12: 管理ツール ストーリー管理＞チャプター編集 | D12: スクリプト内に画像のリンク切れや、日本語が残っていないか | F12: 管理工具 故事管理＞章節編輯 | G12: 腳本內是否沒有圖片連結失效或殘留日文 | I12: Nobunaga | J12: OK | K12: IW | L12: Bill | M12: 46062
A13: =ROW()-2 -> 11 | D13: スクリプトが本番反映されているか | G13: 腳本是否已反映至正式環境 | N13: OK | O13: IW | P13: Bill | Q13: 2/12
A14: =ROW()-2 -> 12 | C14: 管理ツール ストーリー管理＞スクリプトリソース状況一覧 | D14: スクリプトリソースが反映されているか | F14: 管理工具 故事管理＞腳本資源狀況一覽 | G14: 腳本資源是否已反映 | N14: OK | O14: IW | P14: Bill | Q14: 2/12
A15: =ROW()-2 -> 13 | B15: ='参照_仕様'!$D$13&" "&'参照_仕様'!$E$13 -> 兼続 恋遊戯『特別ストーリー』 | C15: 実機 | D15: 保存先のキャラクターが右記の通りか | E15: ='参照_仕様'!$D$13&" "&'参照_仕様'!$E$13 -> 兼続 恋遊戯『特別ストーリー』 | F15: 實體機台 | G15: 保存目標角色是否如右方所示 | H15: ='参照_仕様'!$D$13 -> 兼続 | I15: {=LET( _tmp, XLOOKUP($H15,'参照_仕様'!$D$11:$D$28,'参照_仕様'!$C$11:$C$28), _tmp2, RIGHT(_tmp,LEN(_tmp)-30), LEFT(_tmp2,LEN(_tmp2)-1) )} -> Kanetsugu | J15: OK | K15: IW | L15: Bill | M15: 46062
A16: =ROW()-2 -> 14 | D16: タイトルが右記の通り表示されているか | G16: 標題是否如右方所示顯示 | H16: ='参照_仕様'!$C$13 -> Mystic Matrimony Bonus Story ～Kanetsugu～ | I16: =VLOOKUP(H16,'参照_仕様'!$C$11:$E$31,3,0) -> 恋遊戯『特別ストーリー』 | J16: OK | K16: IW | L16: Bill | M16: 46064
A17: =ROW()-2 -> 15 | D17: ストーリーが正常に再生できるか | G17: 故事是否能正常播放 | J17: OK | K17: IW | L17: Bill | M17: 46064
A18: =ROW()-2 -> 16 | C18: 管理ツール ストーリー管理＞チャプター編集 | D18: スクリプト内に画像のリンク切れや、日本語が残っていないか | F18: 管理工具 故事管理＞章節編輯 | G18: 腳本內是否沒有圖片連結失效或殘留日文 | I18: Kanetsugu | J18: OK | K18: IW | L18: Bill | M18: 46062
A19: =ROW()-2 -> 17 | D19: スクリプトが本番反映されているか | G19: 腳本是否已反映至正式環境 | N19: OK | O19: IW | P19: Bill | Q19: 2/12
A20: =ROW()-2 -> 18 | C20: 管理ツール ストーリー管理＞スクリプトリソース状況一覧 | D20: スクリプトリソースが反映されているか | F20: 管理工具 故事管理＞腳本資源狀況一覽 | G20: 腳本資源是否已反映 | N20: OK | O20: IW | P20: Bill | Q20: 2/12
A21: =ROW()-2 -> 19 | B21: ='参照_仕様'!$D$14&" "&'参照_仕様'!$E$14 -> 帰蝶 恋遊戯『特別ストーリー』 | C21: 実機 | D21: 保存先のキャラクターが右記の通りか | E21: ='参照_仕様'!$D$14&" "&'参照_仕様'!$E$14 -> 帰蝶 恋遊戯『特別ストーリー』 | F21: 實體機台 | G21: 保存目標角色是否如右方所示 | H21: ='参照_仕様'!$D$14 -> 帰蝶 | I21: {=LET( _tmp, XLOOKUP($H21,'参照_仕様'!$D$11:$D$28,'参照_仕様'!$C$11:$C$28), _tmp2, RIGHT(_tmp,LEN(_tmp)-30), LEFT(_tmp2,LEN(_tmp2)-1) )} -> Kicho | J21: OK | K21: IW | L21: Bill | M21: 46062
A22: =ROW()-2 -> 20 | D22: タイトルが右記の通り表示されているか | G22: 標題是否如右方所示顯示 | H22: ='参照_仕様'!$C$14 -> Mystic Matrimony Bonus Story ～Kicho～ | I22: =VLOOKUP(H22,'参照_仕様'!$C$11:$E$31,3,0) -> 恋遊戯『特別ストーリー』 | J22: OK | K22: IW | L22: Bill | M22: 46064
A23: =ROW()-2 -> 21 | D23: ストーリーが正常に再生できるか | G23: 故事是否能正常播放 | J23: OK | K23: IW | L23: Bill | M23: 46064
A24: =ROW()-2 -> 22 | C24: 管理ツール ストーリー管理＞チャプター編集 | D24: スクリプト内に画像のリンク切れや、日本語が残っていないか | F24: 管理工具 故事管理＞章節編輯 | G24: 腳本內是否沒有圖片連結失效或殘留日文 | I24: Kicho | J24: OK | K24: IW | L24: Bill | M24: 46062
A25: =ROW()-2 -> 23 | D25: スクリプトが本番反映されているか | G25: 腳本是否已反映至正式環境 | N25: OK | O25: IW | P25: Bill | Q25: 2/12
A26: =ROW()-2 -> 24 | C26: 管理ツール ストーリー管理＞スクリプトリソース状況一覧 | D26: スクリプトリソースが反映されているか | F26: 管理工具 故事管理＞腳本資源狀況一覽 | G26: 腳本資源是否已反映 | N26: OK | O26: IW | P26: Bill | Q26: 2/12
A27: =ROW()-2 -> 25 | B27: ='参照_仕様'!$D$15&" "&'参照_仕様'!$E$15 -> 元就 恋遊戯『特別ストーリー』 | C27: 実機 | D27: 保存先のキャラクターが右記の通りか | E27: ='参照_仕様'!$D$15&" "&'参照_仕様'!$E$15 -> 元就 恋遊戯『特別ストーリー』 | F27: 實體機台 | G27: 保存目標角色是否如右方所示 | H27: ='参照_仕様'!$D$15 -> 元就 | I27: {=LET( _tmp, XLOOKUP($H27,'参照_仕様'!$D$11:$D$28,'参照_仕様'!$C$11:$C$28), _tmp2, RIGHT(_tmp,LEN(_tmp)-30), LEFT(_tmp2,LEN(_tmp2)-1) )} -> Motonari | J27: OK | K27: IW | L27: Bill | M27: 46062
A28: =ROW()-2 -> 26 | D28: タイトルが右記の通り表示されているか | G28: 標題是否如右方所示顯示 | H28: ='参照_仕様'!$C$15 -> Mystic Matrimony Bonus Story ～Motonari～ | I28: =VLOOKUP(H28,'参照_仕様'!$C$11:$E$31,3,0) -> 恋遊戯『特別ストーリー』 | J28: OK | K28: IW | L28: Bill | M28: 46064
A29: =ROW()-2 -> 27 | D29: ストーリーが正常に再生できるか | G29: 故事是否能正常播放 | J29: OK | K29: IW | L29: Bill | M29: 46064
A30: =ROW()-2 -> 28 | C30: 管理ツール ストーリー管理＞チャプター編集 | D30: スクリプト内に画像のリンク切れや、日本語が残っていないか | F30: 管理工具 故事管理＞章節編輯 | G30: 腳本內是否沒有圖片連結失效或殘留日文 | I30: Motonari | J30: OK | K30: IW | L30: Bill | M30: 46062
A31: =ROW()-2 -> 29 | D31: スクリプトが本番反映されているか | G31: 腳本是否已反映至正式環境 | N31: OK | O31: IW | P31: Bill | Q31: 2/12
A32: =ROW()-2 -> 30 | C32: 管理ツール ストーリー管理＞スクリプトリソース状況一覧 | D32: スクリプトリソースが反映されているか | F32: 管理工具 故事管理＞腳本資源狀況一覽 | G32: 腳本資源是否已反映 | N32: OK | O32: IW | P32: Bill | Q32: 2/12
A33: =ROW()-2 -> 31 | B33: ='参照_仕様'!$D$16&" "&'参照_仕様'!$E$16 -> 義元 恋遊戯『特別ストーリー』 | C33: 実機 | D33: 保存先のキャラクターが右記の通りか | E33: ='参照_仕様'!$D$16&" "&'参照_仕様'!$E$16 -> 義元 恋遊戯『特別ストーリー』 | F33: 實體機台 | G33: 保存目標角色是否如右方所示 | H33: ='参照_仕様'!$D$16 -> 義元 | I33: {=LET( _tmp, XLOOKUP($H33,'参照_仕様'!$D$11:$D$28,'参照_仕様'!$C$11:$C$28), _tmp2, RIGHT(_tmp,LEN(_tmp)-30), LEFT(_tmp2,LEN(_tmp2)-1) )} -> Yoshimoto | J33: OK | K33: IW | L33: Bill | M33: 46062
A34: =ROW()-2 -> 32 | D34: タイトルが右記の通り表示されているか | G34: 標題是否如右方所示顯示 | H34: ='参照_仕様'!$C$16 -> Mystic Matrimony Bonus Story ～Yoshimoto～ | I34: =VLOOKUP(H34,'参照_仕様'!$C$11:$E$31,3,0) -> 恋遊戯『特別ストーリー』 | J34: OK | K34: IW | L34: Bill | M34: 46064
A35: =ROW()-2 -> 33 | D35: ストーリーが正常に再生できるか | G35: 故事是否能正常播放 | J35: OK | K35: IW | L35: Bill | M35: 46064
A36: =ROW()-2 -> 34 | C36: 管理ツール ストーリー管理＞チャプター編集 | D36: スクリプト内に画像のリンク切れや、日本語が残っていないか | F36: 管理工具 故事管理＞章節編輯 | G36: 腳本內是否沒有圖片連結失效或殘留日文 | I36: Yoshimoto | J36: OK | K36: IW | L36: Bill | M36: 46062
A37: =ROW()-2 -> 35 | D37: スクリプトが本番反映されているか | G37: 腳本是否已反映至正式環境 | N37: OK | O37: IW | P37: Bill | Q37: 2/12
A38: =ROW()-2 -> 36 | C38: 管理ツール ストーリー管理＞スクリプトリソース状況一覧 | D38: スクリプトリソースが反映されているか | F38: 管理工具 故事管理＞腳本資源狀況一覽 | G38: 腳本資源是否已反映 | N38: OK | O38: IW | P38: Bill | Q38: 2/12
A39: =ROW()-2 -> 37 | B39: ='参照_仕様'!$D$17&" "&'参照_仕様'!$E$17 -> 政宗 恋遊戯『アフターストーリー』 | C39: 実機 | D39: 保存先のキャラクターが右記の通りか | E39: ='参照_仕様'!$D$17&" "&'参照_仕様'!$E$17 -> 政宗 恋遊戯『アフターストーリー』 | F39: 實體機台 | G39: 保存目標角色是否如右方所示 | H39: ='参照_仕様'!$D$17 -> 政宗 | I39: {=LET( _tmp, XLOOKUP($H39,'参照_仕様'!$D$11:$D$28,'参照_仕様'!$C$11:$C$28), _tmp2, RIGHT(_tmp,LEN(_tmp)-30), LEFT(_tmp2,LEN(_tmp2)-1) )} -> Masamune | J39: OK | K39: IW | L39: Bill | M39: 46062
A40: =ROW()-2 -> 38 | D40: タイトルが右記の通り表示されているか | G40: 標題是否如右方所示顯示 | H40: ='参照_仕様'!$C$17 -> Mystic Matrimony After Story ～Masamune～ | I40: =VLOOKUP(H40,'参照_仕様'!$C$11:$E$31,3,0) -> 恋遊戯『アフターストーリー』 | J40: OK | K40: IW | L40: Bill | M40: 46064
A41: =ROW()-2 -> 39 | D41: ストーリーが正常に再生できるか | G41: 故事是否能正常播放 | J41: OK | K41: IW | L41: Bill | M41: 46064
A42: =ROW()-2 -> 40 | C42: 管理ツール ストーリー管理＞チャプター編集 | D42: スクリプト内に画像のリンク切れや、日本語が残っていないか | F42: 管理工具 故事管理＞章節編輯 | G42: 腳本內是否沒有圖片連結失效或殘留日文 | I42: Masamune | J42: OK | K42: IW | L42: Bill | M42: 46062
A43: =ROW()-2 -> 41 | D43: スクリプトが本番反映されているか | G43: 腳本是否已反映至正式環境 | N43: OK | O43: IW | P43: Bill | Q43: 2/12
A44: =ROW()-2 -> 42 | C44: 管理ツール ストーリー管理＞スクリプトリソース状況一覧 | D44: スクリプトリソースが反映されているか | F44: 管理工具 故事管理＞腳本資源狀況一覽 | G44: 腳本資源是否已反映 | N44: OK | O44: IW | P44: Bill | Q44: 2/12
A45: =ROW()-2 -> 43 | B45: ='参照_仕様'!$D$18&" "&'参照_仕様'!$E$18 -> 信長 恋遊戯『アフターストーリー』 | C45: 実機 | D45: 保存先のキャラクターが右記の通りか | E45: ='参照_仕様'!$D$18&" "&'参照_仕様'!$E$18 -> 信長 恋遊戯『アフターストーリー』 | F45: 實體機台 | G45: 保存目標角色是否如右方所示 | H45: ='参照_仕様'!$D$18 -> 信長 | I45: {=LET( _tmp, XLOOKUP($H45,'参照_仕様'!$D$11:$D$28,'参照_仕様'!$C$11:$C$28), _tmp2, RIGHT(_tmp,LEN(_tmp)-30), LEFT(_tmp2,LEN(_tmp2)-1) )} -> Nobunaga | J45: OK | K45: IW | L45: Bill | M45: 46062
A46: =ROW()-2 -> 44 | D46: タイトルが右記の通り表示されているか | G46: 標題是否如右方所示顯示 | H46: ='参照_仕様'!$C$18 -> Mystic Matrimony After Story ～Nobunaga～ | I46: =VLOOKUP(H46,'参照_仕様'!$C$11:$E$31,3,0) -> 恋遊戯『アフターストーリー』 | J46: OK | K46: IW | L46: Bill | M46: 46064
A47: =ROW()-2 -> 45 | D47: ストーリーが正常に再生できるか | G47: 故事是否能正常播放 | J47: OK | K47: IW | L47: Bill | M47: 46064
A48: =ROW()-2 -> 46 | C48: 管理ツール ストーリー管理＞チャプター編集 | D48: スクリプト内に画像のリンク切れや、日本語が残っていないか | F48: 管理工具 故事管理＞章節編輯 | G48: 腳本內是否沒有圖片連結失效或殘留日文 | I48: Nobunaga | J48: OK | K48: IW | L48: Bill | M48: 46062
A49: =ROW()-2 -> 47 | D49: スクリプトが本番反映されているか | G49: 腳本是否已反映至正式環境 | N49: OK | O49: IW | P49: Bill | Q49: 2/12
A50: =ROW()-2 -> 48 | C50: 管理ツール ストーリー管理＞スクリプトリソース状況一覧 | D50: スクリプトリソースが反映されているか | F50: 管理工具 故事管理＞腳本資源狀況一覽 | G50: 腳本資源是否已反映 | N50: OK | O50: IW | P50: Bill | Q50: 2/12
A51: =ROW()-2 -> 49 | B51: ='参照_仕様'!$D$19&" "&'参照_仕様'!$E$19 -> 兼続 恋遊戯『アフターストーリー』 | C51: 実機 | D51: 保存先のキャラクターが右記の通りか | E51: ='参照_仕様'!$D$19&" "&'参照_仕様'!$E$19 -> 兼続 恋遊戯『アフターストーリー』 | F51: 實體機台 | G51: 保存目標角色是否如右方所示 | H51: ='参照_仕様'!$D$19 -> 兼続 | I51: {=LET( _tmp, XLOOKUP($H51,'参照_仕様'!$D$11:$D$28,'参照_仕様'!$C$11:$C$28), _tmp2, RIGHT(_tmp,LEN(_tmp)-30), LEFT(_tmp2,LEN(_tmp2)-1) )} -> Kanetsugu | J51: OK | K51: IW | L51: Bill | M51: 46062
A52: =ROW()-2 -> 50 | D52: タイトルが右記の通り表示されているか | G52: 標題是否如右方所示顯示 | H52: ='参照_仕様'!$C$19 -> Mystic Matrimony After Story ～Kanetsugu～ | I52: =VLOOKUP(H52,'参照_仕様'!$C$11:$E$31,3,0) -> 恋遊戯『アフターストーリー』 | J52: OK | K52: IW | L52: Bill | M52: 46064
A53: =ROW()-2 -> 51 | D53: ストーリーが正常に再生できるか | G53: 故事是否能正常播放 | J53: OK | K53: IW | L53: Bill | M53: 46064
A54: =ROW()-2 -> 52 | C54: 管理ツール ストーリー管理＞チャプター編集 | D54: スクリプト内に画像のリンク切れや、日本語が残っていないか | F54: 管理工具 故事管理＞章節編輯 | G54: 腳本內是否沒有圖片連結失效或殘留日文 | I54: Kanetsugu | J54: OK | K54: IW | L54: Bill | M54: 46062
A55: =ROW()-2 -> 53 | D55: スクリプトが本番反映されているか | G55: 腳本是否已反映至正式環境 | N55: OK | O55: IW | P55: Bill | Q55: 2/12
A56: =ROW()-2 -> 54 | C56: 管理ツール ストーリー管理＞スクリプトリソース状況一覧 | D56: スクリプトリソースが反映されているか | F56: 管理工具 故事管理＞腳本資源狀況一覽 | G56: 腳本資源是否已反映 | N56: OK | O56: IW | P56: Bill | Q56: 2/12
A57: =ROW()-2 -> 55 | B57: ='参照_仕様'!$D$20&" "&'参照_仕様'!$E$20 -> 帰蝶 恋遊戯『アフターストーリー』 | C57: 実機 | D57: 保存先のキャラクターが右記の通りか | E57: ='参照_仕様'!$D$20&" "&'参照_仕様'!$E$20 -> 帰蝶 恋遊戯『アフターストーリー』 | F57: 實體機台 | G57: 保存目標角色是否如右方所示 | H57: ='参照_仕様'!$D$20 -> 帰蝶 | I57: {=LET( _tmp, XLOOKUP($H57,'参照_仕様'!$D$11:$D$28,'参照_仕様'!$C$11:$C$28), _tmp2, RIGHT(_tmp,LEN(_tmp)-30), LEFT(_tmp2,LEN(_tmp2)-1) )} -> Kicho | J57: OK | K57: IW | L57: Bill | M57: 46062
A58: =ROW()-2 -> 56 | D58: タイトルが右記の通り表示されているか | G58: 標題是否如右方所示顯示 | H58: ='参照_仕様'!$C$20 -> Mystic Matrimony After Story ～Kicho～ | I58: =VLOOKUP(H58,'参照_仕様'!$C$11:$E$31,3,0) -> 恋遊戯『アフターストーリー』 | J58: OK | K58: IW | L58: Bill | M58: 46064
A59: =ROW()-2 -> 57 | D59: ストーリーが正常に再生できるか | G59: 故事是否能正常播放 | J59: OK | K59: IW | L59: Bill | M59: 46064
A60: =ROW()-2 -> 58 | C60: 管理ツール ストーリー管理＞チャプター編集 | D60: スクリプト内に画像のリンク切れや、日本語が残っていないか | F60: 管理工具 故事管理＞章節編輯 | G60: 腳本內是否沒有圖片連結失效或殘留日文 | I60: Kicho | J60: OK | K60: IW | L60: Bill | M60: 46062
A61: =ROW()-2 -> 59 | D61: スクリプトが本番反映されているか | G61: 腳本是否已反映至正式環境 | N61: OK | O61: IW | P61: Bill | Q61: 2/12
A62: =ROW()-2 -> 60 | C62: 管理ツール ストーリー管理＞スクリプトリソース状況一覧 | D62: スクリプトリソースが反映されているか | F62: 管理工具 故事管理＞腳本資源狀況一覽 | G62: 腳本資源是否已反映 | N62: OK | O62: IW | P62: Bill | Q62: 2/12
A63: =ROW()-2 -> 61 | B63: ='参照_仕様'!$D$21&" "&'参照_仕様'!$E$21 -> 元就 恋遊戯『アフターストーリー』 | C63: 実機 | D63: 保存先のキャラクターが右記の通りか | E63: ='参照_仕様'!$D$21&" "&'参照_仕様'!$E$21 -> 元就 恋遊戯『アフターストーリー』 | F63: 實體機台 | G63: 保存目標角色是否如右方所示 | H63: ='参照_仕様'!$D$21 -> 元就 | I63: {=LET( _tmp, XLOOKUP($H63,'参照_仕様'!$D$11:$D$28,'参照_仕様'!$C$11:$C$28), _tmp2, RIGHT(_tmp,LEN(_tmp)-30), LEFT(_tmp2,LEN(_tmp2)-1) )} -> Motonari | J63: OK | K63: IW | L63: Bill | M63: 46062
A64: =ROW()-2 -> 62 | D64: タイトルが右記の通り表示されているか | G64: 標題是否如右方所示顯示 | H64: ='参照_仕様'!$C$21 -> Mystic Matrimony After Story ～Motonari～ | I64: =VLOOKUP(H64,'参照_仕様'!$C$11:$E$31,3,0) -> 恋遊戯『アフターストーリー』 | J64: OK | K64: IW | L64: Bill | M64: 46064
A65: =ROW()-2 -> 63 | D65: ストーリーが正常に再生できるか | G65: 故事是否能正常播放 | J65: OK | K65: IW | L65: Bill | M65: 46064
A66: =ROW()-2 -> 64 | C66: 管理ツール ストーリー管理＞チャプター編集 | D66: スクリプト内に画像のリンク切れや、日本語が残っていないか | F66: 管理工具 故事管理＞章節編輯 | G66: 腳本內是否沒有圖片連結失效或殘留日文 | I66: Motonari | J66: OK | K66: IW | L66: Bill | M66: 46062
A67: =ROW()-2 -> 65 | D67: スクリプトが本番反映されているか | G67: 腳本是否已反映至正式環境 | N67: OK | O67: IW | P67: Bill | Q67: 2/12
A68: =ROW()-2 -> 66 | C68: 管理ツール ストーリー管理＞スクリプトリソース状況一覧 | D68: スクリプトリソースが反映されているか | F68: 管理工具 故事管理＞腳本資源狀況一覽 | G68: 腳本資源是否已反映 | N68: OK | O68: IW | P68: Bill | Q68: 2/12
A69: =ROW()-2 -> 67 | B69: ='参照_仕様'!$D$22&" "&'参照_仕様'!$E$22 -> 義元 恋遊戯『アフターストーリー』 | C69: 実機 | D69: 保存先のキャラクターが右記の通りか | E69: ='参照_仕様'!$D$22&" "&'参照_仕様'!$E$22 -> 義元 恋遊戯『アフターストーリー』 | F69: 實體機台 | G69: 保存目標角色是否如右方所示 | H69: ='参照_仕様'!$D$22 -> 義元 | I69: {=LET( _tmp, XLOOKUP($H69,'参照_仕様'!$D$11:$D$28,'参照_仕様'!$C$11:$C$28), _tmp2, RIGHT(_tmp,LEN(_tmp)-30), LEFT(_tmp2,LEN(_tmp2)-1) )} -> Yoshimoto | J69: OK | K69: IW | L69: Bill | M69: 46062
A70: =ROW()-2 -> 68 | D70: タイトルが右記の通り表示されているか | G70: 標題是否如右方所示顯示 | H70: ='参照_仕様'!$C$22 -> Mystic Matrimony After Story ～Yoshimoto～ | I70: =VLOOKUP(H70,'参照_仕様'!$C$11:$E$31,3,0) -> 恋遊戯『アフターストーリー』 | J70: OK | K70: IW | L70: Bill | M70: 46064
A71: =ROW()-2 -> 69 | D71: ストーリーが正常に再生できるか | G71: 故事是否能正常播放 | J71: OK | K71: IW | L71: Bill | M71: 46064
A72: =ROW()-2 -> 70 | C72: 管理ツール ストーリー管理＞チャプター編集 | D72: スクリプト内に画像のリンク切れや、日本語が残っていないか | F72: 管理工具 故事管理＞章節編輯 | G72: 腳本內是否沒有圖片連結失效或殘留日文 | I72: Yoshimoto | J72: OK | K72: IW | L72: Bill | M72: 46062
A73: =ROW()-2 -> 71 | D73: スクリプトが本番反映されているか | G73: 腳本是否已反映至正式環境 | N73: OK | O73: IW | P73: Bill | Q73: 2/12
A74: =ROW()-2 -> 72 | C74: 管理ツール ストーリー管理＞スクリプトリソース状況一覧 | D74: スクリプトリソースが反映されているか | F74: 管理工具 故事管理＞腳本資源狀況一覽 | G74: 腳本資源是否已反映 | N74: OK | O74: IW | P74: Bill | Q74: 2/12
A75: =ROW()-2 -> 73 | B75: ='参照_仕様'!$D$23&" "&'参照_仕様'!$E$23 -> 信長 戦国妖絵巻『鬼の彼に求められて…♡』 | C75: 実機 | D75: 保存先のキャラクターが右記の通りか | E75: ='参照_仕様'!$D$23&" "&'参照_仕様'!$E$23 -> 信長 戦国妖絵巻『鬼の彼に求められて…♡』 | F75: 實體機台 | G75: 保存目標角色是否如右方所示 | H75: ='参照_仕様'!$D$23 -> 信長 | I75: {=LET( _tmp, XLOOKUP($H75,'参照_仕様'!$D$11:$D$28,'参照_仕様'!$C$11:$C$28), _tmp2, RIGHT(_tmp,LEN(_tmp)-30), LEFT(_tmp2,LEN(_tmp2)-1) )} -> Nobunaga | J75: OK | K75: IW | L75: Bill | M75: 46062
A76: =ROW()-2 -> 74 | D76: タイトルが右記の通り表示されているか | G76: 標題是否如右方所示顯示 | H76: ='参照_仕様'!$C$23 -> Demon of My Dreams (Nobunaga) | I76: =VLOOKUP(H76,'参照_仕様'!$C$11:$E$31,3,0) -> 戦国妖絵巻『鬼の彼に求められて…♡』 | J76: OK | K76: IW | L76: Bill | M76: 46064
A77: =ROW()-2 -> 75 | D77: ストーリーが正常に再生できるか | G77: 故事是否能正常播放 | J77: OK | K77: IW | L77: Bill | M77: 46064
A78: =ROW()-2 -> 76 | C78: 管理ツール ストーリー管理＞チャプター編集 | D78: スクリプト内に画像のリンク切れや、日本語が残っていないか | F78: 管理工具 故事管理＞章節編輯 | G78: 腳本內是否沒有圖片連結失效或殘留日文 | I78: Nobunaga | J78: OK | K78: IW | L78: Bill | M78: 46062
A79: =ROW()-2 -> 77 | D79: スクリプトが本番反映されているか | G79: 腳本是否已反映至正式環境 | N79: OK | O79: IW | P79: Bill | Q79: 2/12
A80: =ROW()-2 -> 78 | C80: 管理ツール ストーリー管理＞スクリプトリソース状況一覧 | D80: スクリプトリソースが反映されているか | F80: 管理工具 故事管理＞腳本資源狀況一覽 | G80: 腳本資源是否已反映 | N80: OK | O80: IW | P80: Bill | Q80: 2/12
A81: =ROW()-2 -> 79 | B81: ='参照_仕様'!$D$24&" "&'参照_仕様'!$E$24 -> 政宗 戦国妖絵巻『鬼の彼に求められて…♡』 | C81: 実機 | D81: 保存先のキャラクターが右記の通りか | E81: ='参照_仕様'!$D$24&" "&'参照_仕様'!$E$24 -> 政宗 戦国妖絵巻『鬼の彼に求められて…♡』 | F81: 實體機台 | G81: 保存目標角色是否如右方所示 | H81: ='参照_仕様'!$D$24 -> 政宗 | I81: {=LET( _tmp, XLOOKUP($H81,'参照_仕様'!$D$11:$D$28,'参照_仕様'!$C$11:$C$28), _tmp2, RIGHT(_tmp,LEN(_tmp)-30), LEFT(_tmp2,LEN(_tmp2)-1) )} -> Masamune | J81: OK | K81: IW | L81: Bill | M81: 46062
A82: =ROW()-2 -> 80 | D82: タイトルが右記の通り表示されているか | G82: 標題是否如右方所示顯示 | H82: ='参照_仕様'!$C$24 -> Demon of My Dreams (Masamune) | I82: =VLOOKUP(H82,'参照_仕様'!$C$11:$E$31,3,0) -> 戦国妖絵巻『鬼の彼に求められて…♡』 | J82: OK | K82: IW | L82: Bill | M82: 46064
A83: =ROW()-2 -> 81 | D83: ストーリーが正常に再生できるか | G83: 故事是否能正常播放 | J83: OK | K83: IW | L83: Bill | M83: 46064
A84: =ROW()-2 -> 82 | C84: 管理ツール ストーリー管理＞チャプター編集 | D84: スクリプト内に画像のリンク切れや、日本語が残っていないか | F84: 管理工具 故事管理＞章節編輯 | G84: 腳本內是否沒有圖片連結失效或殘留日文 | I84: Masamune | J84: OK | K84: IW | L84: Bill | M84: 46062
A85: =ROW()-2 -> 83 | D85: スクリプトが本番反映されているか | G85: 腳本是否已反映至正式環境 | N85: OK | O85: IW | P85: Bill | Q85: 2/12
A86: =ROW()-2 -> 84 | C86: 管理ツール ストーリー管理＞スクリプトリソース状況一覧 | D86: スクリプトリソースが反映されているか | F86: 管理工具 故事管理＞腳本資源狀況一覽 | G86: 腳本資源是否已反映 | N86: OK | O86: IW | P86: Bill | Q86: 2/12
A87: =ROW()-2 -> 85 | B87: ='参照_仕様'!$D$25&" "&'参照_仕様'!$E$25 -> 義元 戦国妖絵巻『龍の彼に求められて…♡』 | C87: 実機 | D87: 保存先のキャラクターが右記の通りか | E87: ='参照_仕様'!$D$25&" "&'参照_仕様'!$E$25 -> 義元 戦国妖絵巻『龍の彼に求められて…♡』 | F87: 實體機台 | G87: 保存目標角色是否如右方所示 | H87: ='参照_仕様'!$D$25 -> 義元 | I87: {=LET( _tmp, XLOOKUP($H87,'参照_仕様'!$D$11:$D$28,'参照_仕様'!$C$11:$C$28), _tmp2, RIGHT(_tmp,LEN(_tmp)-30), LEFT(_tmp2,LEN(_tmp2)-1) )} -> Yoshimoto | J87: OK | K87: IW | L87: Bill | M87: 46062
A88: =ROW()-2 -> 86 | D88: タイトルが右記の通り表示されているか | G88: 標題是否如右方所示顯示 | H88: ='参照_仕様'!$C$25 -> Demon of My Dreams (Yoshimoto) | I88: =VLOOKUP(H88,'参照_仕様'!$C$11:$E$31,3,0) -> 戦国妖絵巻『龍の彼に求められて…♡』 | J88: OK | K88: IW | L88: Bill | M88: 46064
A89: =ROW()-2 -> 87 | D89: ストーリーが正常に再生できるか | G89: 故事是否能正常播放 | J89: OK | K89: IW | L89: Bill | M89: 46064
A90: =ROW()-2 -> 88 | C90: 管理ツール ストーリー管理＞チャプター編集 | D90: スクリプト内に画像のリンク切れや、日本語が残っていないか | F90: 管理工具 故事管理＞章節編輯 | G90: 腳本內是否沒有圖片連結失效或殘留日文 | I90: Yoshimoto | J90: OK | K90: IW | L90: Bill | M90: 46062
A91: =ROW()-2 -> 89 | D91: スクリプトが本番反映されているか | G91: 腳本是否已反映至正式環境 | N91: OK | O91: IW | P91: Bill | Q91: 2/12
A92: =ROW()-2 -> 90 | C92: 管理ツール ストーリー管理＞スクリプトリソース状況一覧 | D92: スクリプトリソースが反映されているか | F92: 管理工具 故事管理＞腳本資源狀況一覽 | G92: 腳本資源是否已反映 | N92: OK | O92: IW | P92: Bill | Q92: 2/12
A93: =ROW()-2 -> 91 | B93: ='参照_仕様'!$D$26&" "&'参照_仕様'!$E$26 -> 元就 戦国妖絵巻『吸血鬼の彼に求められて…♡』 | C93: 実機 | D93: 保存先のキャラクターが右記の通りか | E93: ='参照_仕様'!$D$26&" "&'参照_仕様'!$E$26 -> 元就 戦国妖絵巻『吸血鬼の彼に求められて…♡』 | F93: 實體機台 | G93: 保存目標角色是否如右方所示 | H93: ='参照_仕様'!$D$26 -> 元就 | I93: {=LET( _tmp, XLOOKUP($H93,'参照_仕様'!$D$11:$D$28,'参照_仕様'!$C$11:$C$28), _tmp2, RIGHT(_tmp,LEN(_tmp)-30), LEFT(_tmp2,LEN(_tmp2)-1) )} -> Motonari | J93: OK | K93: IW | L93: Bill | M93: 46062
A94: =ROW()-2 -> 92 | D94: タイトルが右記の通り表示されているか | G94: 標題是否如右方所示顯示 | H94: ='参照_仕様'!$C$26 -> Demon of My Dreams (Motonari) | I94: =VLOOKUP(H94,'参照_仕様'!$C$11:$E$31,3,0) -> 戦国妖絵巻『吸血鬼の彼に求められて…♡』 | J94: OK | K94: IW | L94: Bill | M94: 46064
A95: =ROW()-2 -> 93 | D95: ストーリーが正常に再生できるか | G95: 故事是否能正常播放 | J95: OK | K95: IW | L95: Bill | M95: 46064
A96: =ROW()-2 -> 94 | C96: 管理ツール ストーリー管理＞チャプター編集 | D96: スクリプト内に画像のリンク切れや、日本語が残っていないか | F96: 管理工具 故事管理＞章節編輯 | G96: 腳本內是否沒有圖片連結失效或殘留日文 | I96: Motonari | J96: OK | K96: IW | L96: Bill | M96: 46062
A97: =ROW()-2 -> 95 | D97: スクリプトが本番反映されているか | G97: 腳本是否已反映至正式環境 | N97: OK | O97: IW | P97: Bill | Q97: 2/12
A98: =ROW()-2 -> 96 | C98: 管理ツール ストーリー管理＞スクリプトリソース状況一覧 | D98: スクリプトリソースが反映されているか | F98: 管理工具 故事管理＞腳本資源狀況一覽 | G98: 腳本資源是否已反映 | N98: OK | O98: IW | P98: Bill | Q98: 2/12
A99: =ROW()-2 -> 97 | B99: ='参照_仕様'!$D$27&" "&'参照_仕様'!$E$27 -> 兼続 戦国妖絵巻『龍の彼に求められて…♡』 | C99: 実機 | D99: 保存先のキャラクターが右記の通りか | E99: ='参照_仕様'!$D$27&" "&'参照_仕様'!$E$27 -> 兼続 戦国妖絵巻『龍の彼に求められて…♡』 | F99: 實體機台 | G99: 保存目標角色是否如右方所示 | H99: ='参照_仕様'!$D$27 -> 兼続 | I99: {=LET( _tmp, XLOOKUP($H99,'参照_仕様'!$D$11:$D$28,'参照_仕様'!$C$11:$C$28), _tmp2, RIGHT(_tmp,LEN(_tmp)-30), LEFT(_tmp2,LEN(_tmp2)-1) )} -> Kanetsugu | J99: OK | K99: IW | L99: Bill | M99: 46062
A100: =ROW()-2 -> 98 | D100: タイトルが右記の通り表示されているか | G100: 標題是否如右方所示顯示 | H100: ='参照_仕様'!$C$27 -> Demon of My Dreams (Kanetsugu) | I100: =VLOOKUP(H100,'参照_仕様'!$C$11:$E$31,3,0) -> 戦国妖絵巻『龍の彼に求められて…♡』 | J100: OK | K100: IW | L100: Bill | M100: 46064
...

Sheet 新規アバター
A1: No | B1: 項目 | C1: 確認方法 | D1: 確認項目 | E1: 項目 | F1: 確認方法 | G1: 確認項目 | H1: 確認箇所・詳細 | I1: English Name | L1: テスト環境 | P1: 本番環境 | T1: 備考 | U1: テスターコメント | V1: チケットURL
J2: ID | K2: Link | L2: 確認 | M2: 担当 | N2: 担当者 | O2: 日付 | P2: 確認 | Q2: 担当 | R2: 担当者 | S2: 日付
A3: =ROW()-2 -> 1 | B3: ='参照_特典詳細'!C5 -> 夜を練り歩く義元 | C3: 実機 | D3: アバターサムネイルが表示されているか | E3: ='参照_特典詳細'!C5 -> 夜を練り歩く義元 | F3: 實體機台 | G3: 裝扮縮圖是否顯示 | I3: {=IF(LEN(E3:E157), VLOOKUP(E3:E157,'参照_特典詳細'!$C$5:$G$50,2,0), )} -> Yoshimoto with a Lantern | J3: {=IF(LEN(E3:E157),VLOOKUP(E3:E157,'参照_特典詳細'!$C$5:$G$55,5,0),)} -> 6_1_3882 | K3: {=IF(LEN(J3:J157), HYPERLINK("https://common-legacy-app-admin.us.ikemen-sengoku.jp/admin/avatar/material_list/"&J3:J157,"Search"),)} -> Search | L3: OK | M3: IW | N3: Bill | O3: 46064 | P3: OK | Q3: {=IF(P3:P157="OK",{"IW","Bill","2/12"},)} -> IW | R3: Bill | S3: 2/12
A4: =ROW()-2 -> 2 | D4: アバターが着用できるか | G4: 是否可穿脫，且穿著時的裝扮是否正確顯示 | L4: OK | M4: IW | N4: Bill | O4: 46064 | P4: OK | Q4: IW | R4: Bill | S4: 2/12
A5: =ROW()-2 -> 3 | C5: 管理ツール アバター素材管理 | D5: アバター名が左記の通り設定されているか | F5: 管理工具 管理工具 裝扮(Avatar)素材管理 | G5: 裝扮名稱是否如右方所示設定 | H5: ='参照_特典詳細'!$D$5 -> Yoshimoto with a Lantern | L5: OK | M5: IW | N5: Bill | O5: 46063
A6: =ROW()-2 -> 4 | D6: 魅力値が左記の通り設定されているか | G6: 魅力值是否如右方所示設定 | H6: ='参照_特典詳細'!$E$5 -> 30 | L6: OK | M6: IW | N6: Bill | O6: 46063
A7: =ROW()-2 -> 5 | D7: アバターカテゴリが左記の通り設定されているか | G7: 裝扮分類是否如右方所示設定 | H7: ='参照_特典詳細'!$F$5 -> 置物
A8: =ROW()-2 -> 6 | B8: ='参照_特典詳細'!C6 -> 夜を練り歩く元就 | C8: 実機 | D8: アバターサムネイルが表示されているか | E8: ='参照_特典詳細'!C6 -> 夜を練り歩く元就 | F8: 實體機台 | G8: 裝扮縮圖是否顯示 | I8: Motonari with a Lantern | J8: 6_1_3883 | K8: Search | L8: OK | M8: IW | N8: Bill | O8: 46064 | P8: OK | Q8: IW | R8: Bill | S8: 2/12
